Workbook
Name beta0: [1]DemandProfitPrediction!$E$2
Name capacity: DemandPredictionModel!$C$23
Name cost: [1]DemandProfitPrediction!$B$2
Name demand: DemandPredictionModel!$C$30
Name exp_vc: [1]DemandProfitPrediction!$I$8
Name fixedCost: DemandPredictionModel!$C$21
Name marginalCost: DemandPredictionModel!$C$22
Name market: [1]DemandProfitPrediction!$E$6
Name marketSize: DemandPredictionModel!$C$17
Name price: DemandPredictionModel!$C$31
Name profit: DemandPredictionModel!$C$33
Name revenue: DemandPredictionModel!$C$32
Name riskTolerance: Utility!$C$1
Name utility: Utility!$C$3
Name xin1: DemandPredictionModel!$C$24
Name xin2: DemandPredictionModel!$C$25
Name xin3: DemandPredictionModel!$C$26

Sheet Introduction
A1: Introduction to the Project and Survey
A3: In this survey, you will be asked to express your preferences about a new portable electric kettle under design. The new kettle is targeted for the general public but some key potential customers include people working at construction sites, camping or spending time outdoors. If your preference would be influenced by attributes not specified in the survey, assume kettle characteristics similar to these comparable vehicles. You will be asked to focus on four specific attributes of the new kettle. System context and details of each attribute are listed below. Please review the information on this tab/page, then proceed to the Survey tab to complete the survey. NOTE: Please find your Student Number on the "Roster" tab and then enter your number in the Survey Number cell of the "Survey" tab. This step is necessary to enable the survey. Otherwise you will not be able to complete the survey.
A5: Some Details About the System
A7: The purpose of the Portable Electric Kettle (PEK) is to bring fluid to a boil without the need for a wall outlet for power. The PEK utilizes an on board heating element to pull power from an internal battery bank to bring fluid to a boil. The kettle is vacuum insulated with an insulated lid to provide efficient heating. The kettle has multiple temperature settings, allowing the operator to select the appropriate temperature according to his or her preference.
A9: Assumptions
A11: The outer diameter of the kettle will be no larger than a Nalgene (3.5in) The kettle will be charged with a PD USB-C cable. The unit will be capable of being charged from empty to full in less than 3 hours.
A13: Attributes Appearing in the Survey
A14: Attribute Name | B14: Units | C14: Low | D14: Medium | E14: High | F14: Description
A15: =SurveySetup!A3 -> price | B15: =SurveySetup!B3 -> $ | C15: =SurveySetup!C3 -> 50 | D15: =SurveySetup!D3 -> 100 | E15: =SurveySetup!E3 -> 200 | F15: The price of the kettle
A16: =SurveySetup!A4 -> Fluid Capacity | B16: =SurveySetup!B4 -> liters | C16: =SurveySetup!C4 -> 0.25 | D16: =SurveySetup!D4 -> 1 | E16: =SurveySetup!E4 -> 2 | F16: The total fluid the kettle can boil at a time
A17: =SurveySetup!A5 -> Time to boil | B17: =SurveySetup!B5 -> sec | C17: =SurveySetup!C5 -> 120 | D17: =SurveySetup!D5 -> 240 | E17: =SurveySetup!E5 -> 600 | F17: The time it takes for the kettle to boil the maximum fluid capacity at sea level
A18: =SurveySetup!A6 -> Boils per charge | B18: =SurveySetup!B6 -> # | C18: =SurveySetup!C6 -> 1 | D18: =SurveySetup!D6 -> 5 | E18: =SurveySetup!E6 -> 10 | F18: The number of full boils the kettle can achieve on a single charge

Sheet Roster
A1: Roster with Survey ID Assignments
A2: Survey ID# | B2: Student Name | C2: E-mail
A3: 1 | B3: Abdirizak, Miski A | C3: mabdirizak3@gatech.edu
A4: 2 | B4: Adhikari, Samrat | C4: sadhikari65@gatech.edu
A5: 3 | B5: Adhikary, Meghan Turie | C5: madhikary3@gatech.edu
A6: 4 | B6: Aghamyan, Arman | C6: aaghamyan3@gatech.edu
A7: 5 | B7: Alarcon Chavez, Andros | C7: androsac@gatech.edu
A8: 6 | B8: Alcocer, Jathzel | C8: jalcocer3@gatech.edu
A9: 7 | B9: Alcorn-Ferrell, Nyra' Tyrie | C9: nta31@gatech.edu
A10: 8 | B10: Bailey, Michael Scott | C10: mbailey44@gatech.edu
A11: 9 | B11: Boman, Alex S | C11: aboman3@gatech.edu
A12: 10 | B12: Brown, Destiny S | C12: dbrown469@gatech.edu
A13: 11 | B13: Bundu, Zainab | C13: zbundu3@gatech.edu
A14: 12 | B14: Calimlim, Luke | C14: lcalimlim3@gatech.edu
... A65: 63 | B65: Zomiti, Wajdi | C65: wajdi.zomiti@gatech.edu

Sheet Survey
A1: Survey number: | B1: 9 | C1: =IF(COUNTIF(J:J,0)=1,"Survey Complete","SURVEY INCOMPLETE--Revisit questions marked:") -> Survey Complete | J1: =IF(COUNTIF(J11:J127,0)=0,1,0) -> 1
A3: Attribute Name | B3: Units | C3: Preference Direction | D3: Low | E3: Medium | F3: High | K3: green | L3: red
A4: =SurveySetup!A3 -> price | B4: =SurveySetup!B3 -> $ | C4: less is better | D4: =SurveySetup!C3 -> 50 | E4: =SurveySetup!D3 -> 100 | F4: =SurveySetup!E3 -> 200 | K4: =IF(C4="less is better",MIN(D4:F4),MAX(D4:F4)) -> 50 | L4: =IF(C4="more is better",MIN(D4:F4),MAX(D4:F4)) -> 200
A5: =SurveySetup!A4 -> Fluid Capacity | B5: =SurveySetup!B4 -> liters | C5: more is better | D5: =SurveySetup!C4 -> 0.25 | E5: =SurveySetup!D4 -> 1 | F5: =SurveySetup!E4 -> 2 | K5: =IF(C5="less is better",MIN(D5:F5),MAX(D5:F5)) -> 2 | L5: =IF(C5="more is better",MIN(D5:F5),MAX(D5:F5)) -> 0.25
A6: =SurveySetup!A5 -> Time to boil | B6: =SurveySetup!B5 -> sec | C6: less is better | D6: =SurveySetup!C5 -> 120 | E6: =SurveySetup!D5 -> 240 | F6: =SurveySetup!E5 -> 600 | K6: =IF(C6="less is better",MIN(D6:F6),MAX(D6:F6)) -> 120 | L6: =IF(C6="more is better",MIN(D6:F6),MAX(D6:F6)) -> 600
A7: =SurveySetup!A6 -> Boils per charge | B7: =SurveySetup!B6 -> # | C7: more is better | D7: =SurveySetup!C6 -> 1 | E7: =SurveySetup!D6 -> 5 | F7: =SurveySetup!E6 -> 10 | K7: =IF(C7="less is better",MIN(D7:F7),MAX(D7:F7)) -> 10 | L7: =IF(C7="more is better",MIN(D7:F7),MAX(D7:F7)) -> 1
A9: Question
A10: 1 | B10: =DOE!$B$2 -> price ($) | C10: =DOE!$C$2 -> Fluid Capacity (liters) | D10: =DOE!$D$2 -> Time to boil (sec) | E10: =DOE!$E$2 -> Boils per charge (#) | F10: Choice (mark with "1") | G10: Alt ID | M10: dominated? | N10: =B10 -> price ($) | O10: =C10 -> Fluid Capacity (liters) | P10: =D10 -> Time to boil (sec) | Q10: =E10 -> Boils per charge (#)
A11: Option 1 | B11: =INDEX(DOE!$A$4:$E$84,$G11,COLUMN(B:B)) -> 200 | C11: =INDEX(DOE!$A$4:$E$84,$G11,COLUMN(C:C)) -> 0.25 | D11: =INDEX(DOE!$A$4:$E$84,$G11,COLUMN(D:D)) -> 120 | E11: =INDEX(DOE!$A$4:$E$84,$G11,COLUMN(E:E)) -> 1 | G11: =INDEX(StaticRandomNumbers!$A$4:$BJ$93,A10*3-2,$B$1+1) -> 55 | H11: =F11*G11 -> 0 | J11: =IF(AND(COUNTIF(F11:F13,"")=2,COUNTIF(F11:F13,1)=1),1,0) -> 1 | M11: =OR(AND(N11>=N12,O11>=O12,P11>=P12,Q11>=Q12),AND(N11>=N13,O11>=O13,P11>=P13,Q11>=Q13)) -> TRUE | N11: =IF(B11=$K$4,1,IF(B11=$L$4,3,2)) -> 3 | O11: =IF(C11=$K$5,1,IF(C11=$L$5,3,2)) -> 3 | P11: =IF(D11=$K$6,1,IF(D11=$L$6,3,2)) -> 1 | Q11: =IF(E11=$K$7,1,IF(E11=$L$7,3,2)) -> 3
A12: Option 2 | B12: =INDEX(DOE!$A$4:$E$84,$G12,COLUMN(B:B)) -> 50 | C12: =INDEX(DOE!$A$4:$E$84,$G12,COLUMN(C:C)) -> 0.25 | D12: =INDEX(DOE!$A$4:$E$84,$G12,COLUMN(D:D)) -> 600 | E12: =INDEX(DOE!$A$4:$E$84,$G12,COLUMN(E:E)) -> 1 | G12: =INDEX(StaticRandomNumbers!$A$4:$BJ$93,A10*3-1,$B$1+1) -> 7 | H12: =F12*G12 -> 0 | M12: =OR(AND(N11<=N12,O11<=O12,P11<=P12,Q11<=Q12),AND(N12>=N13,O12>=O13,P12>=P13,Q12>=Q13)) -> TRUE | N12: =IF(B12=$K$4,1,IF(B12=$L$4,3,2)) -> 1 | O12: =IF(C12=$K$5,1,IF(C12=$L$5,3,2)) -> 3 | P12: =IF(D12=$K$6,1,IF(D12=$L$6,3,2)) -> 3 | Q12: =IF(E12=$K$7,1,IF(E12=$L$7,3,2)) -> 3
A13: Option 3 | B13: =INDEX(DOE!$A$4:$E$84,$G13,COLUMN(B:B)) -> 50 | C13: =INDEX(DOE!$A$4:$E$84,$G13,COLUMN(C:C)) -> 2 | D13: =INDEX(DOE!$A$4:$E$84,$G13,COLUMN(D:D)) -> 120 | E13: =INDEX(DOE!$A$4:$E$84,$G13,COLUMN(E:E)) -> 10 | F13: 1 | G13: =INDEX(StaticRandomNumbers!$A$4:$BJ$93,A10*3,$B$1+1) -> 21 | H13: =F13*G13 -> 21 | M13: =OR(AND(N13>=N12,O13>=O12,P13>=P12,Q13>=Q12),AND(N13>=N11,O13>=O11,P13>=P11,Q13>=Q11)) -> FALSE | N13: =IF(B13=$K$4,1,IF(B13=$L$4,3,2)) -> 1 | O13: =IF(C13=$K$5,1,IF(C13=$L$5,3,2)) -> 1 | P13: =IF(D13=$K$6,1,IF(D13=$L$6,3,2)) -> 1 | Q13: =IF(E13=$K$7,1,IF(E13=$L$7,3,2)) -> 1
A15: Question
A16: =A10+1 -> 2 | B16: =DOE!$B$2 -> price ($) | C16: =DOE!$C$2 -> Fluid Capacity (liters) | D16: =DOE!$D$2 -> Time to boil (sec) | E16: =DOE!$E$2 -> Boils per charge (#) | F16: Choice (mark with "1") | G16: Alt ID | M16: dominated? | N16: =B16 -> price ($) | O16: =C16 -> Fluid Capacity (liters) | P16: =D16 -> Time to boil (sec) | Q16: =E16 -> Boils per charge (#)
A17: Option 1 | B17: =INDEX(DOE!$A$4:$E$84,$G17,COLUMN(B:B)) -> 200 | C17: =INDEX(DOE!$A$4:$E$84,$G17,COLUMN(C:C)) -> 1 | D17: =INDEX(DOE!$A$4:$E$84,$G17,COLUMN(D:D)) -> 120 | E17: =INDEX(DOE!$A$4:$E$84,$G17,COLUMN(E:E)) -> 10 | F17: 1 | G17: =INDEX(StaticRandomNumbers!$A$4:$BJ$93,A16*3-2,$B$1+1) -> 66 | H17: =F17*G17 -> 66 | J17: =IF(AND(COUNTIF(F17:F19,"")=2,COUNTIF(F17:F19,1)=1),1,0) -> 1 | M17: =OR(AND(N17>=N18,O17>=O18,P17>=P18,Q17>=Q18),AND(N17>=N19,O17>=O19,P17>=P19,Q17>=Q19)) -> FALSE | N17: =IF(B17=$K$4,1,IF(B17=$L$4,3,2)) -> 3 | O17: =IF(C17=$K$5,1,IF(C17=$L$5,3,2)) -> 2 | P17: =IF(D17=$K$6,1,IF(D17=$L$6,3,2)) -> 1 | Q17: =IF(E17=$K$7,1,IF(E17=$L$7,3,2)) -> 1
A18: Option 2 | B18: =INDEX(DOE!$A$4:$E$84,$G18,COLUMN(B:B)) -> 50 | C18: =INDEX(DOE!$A$4:$E$84,$G18,COLUMN(C:C)) -> 0.25 | D18: =INDEX(DOE!$A$4:$E$84,$G18,COLUMN(D:D)) -> 600 | E18: =INDEX(DOE!$A$4:$E$84,$G18,COLUMN(E:E)) -> 5 | G18: =INDEX(StaticRandomNumbers!$A$4:$BJ$93,A16*3-1,$B$1+1) -> 8 | H18: =F18*G18 -> 0 | M18: =OR(AND(N17<=N18,O17<=O18,P17<=P18,Q17<=Q18),AND(N18>=N19,O18>=O19,P18>=P19,Q18>=Q19)) -> FALSE | N18: =IF(B18=$K$4,1,IF(B18=$L$4,3,2)) -> 1 | O18: =IF(C18=$K$5,1,IF(C18=$L$5,3,2)) -> 3 | P18: =IF(D18=$K$6,1,IF(D18=$L$6,3,2)) -> 3 | Q18: =IF(E18=$K$7,1,IF(E18=$L$7,3,2)) -> 2
A19: Option 3 | B19: =INDEX(DOE!$A$4:$E$84,$G19,COLUMN(B:B)) -> 200 | C19: =INDEX(DOE!$A$4:$E$84,$G19,COLUMN(C:C)) -> 1 | D19: =INDEX(DOE!$A$4:$E$84,$G19,COLUMN(D:D)) -> 600 | E19: =INDEX(DOE!$A$4:$E$84,$G19,COLUMN(E:E)) -> 5 | G19: =INDEX(StaticRandomNumbers!$A$4:$BJ$93,A16*3,$B$1+1) -> 71 | H19: =F19*G19 -> 0 | M19: =OR(AND(N19>=N18,O19>=O18,P19>=P18,Q19>=Q18),AND(N19>=N17,O19>=O17,P19>=P17,Q19>=Q17)) -> TRUE | N19: =IF(B19=$K$4,1,IF(B19=$L$4,3,2)) -> 3 | O19: =IF(C19=$K$5,1,IF(C19=$L$5,3,2)) -> 2 | P19: =IF(D19=$K$6,1,IF(D19=$L$6,3,2)) -> 3 | Q19: =IF(E19=$K$7,1,IF(E19=$L$7,3,2)) -> 2
A21: Question
A22: =A16+1 -> 3 | B22: =DOE!$B$2 -> price ($) | C22: =DOE!$C$2 -> Fluid Capacity (liters) | D22: =DOE!$D$2 -> Time to boil (sec) | E22: =DOE!$E$2 -> Boils per charge (#) | F22: Choice (mark with "1") | G22: Alt ID | M22: dominated? | N22: =B22 -> price ($) | O22: =C22 -> Fluid Capacity (liters) | P22: =D22 -> Time to boil (sec) | Q22: =E22 -> Boils per charge (#)
A23: Option 1 | B23: =INDEX(DOE!$A$4:$E$84,$G23,COLUMN(B:B)) -> 50 | C23: =INDEX(DOE!$A$4:$E$84,$G23,COLUMN(C:C)) -> 0.25 | D23: =INDEX(DOE!$A$4:$E$84,$G23,COLUMN(D:D)) -> 120 | E23: =INDEX(DOE!$A$4:$E$84,$G23,COLUMN(E:E)) -> 1 | G23: =INDEX(StaticRandomNumbers!$A$4:$BJ$93,A22*3-2,$B$1+1) -> 1 | H23: =F23*G23 -> 0 | J23: =IF(AND(COUNTIF(F23:F25,"")=2,COUNTIF(F23:F25,1)=1),1,0) -> 1 | M23: =OR(AND(N23>=N24,O23>=O24,P23>=P24,Q23>=Q24),AND(N23>=N25,O23>=O25,P23>=P25,Q23>=Q25)) -> FALSE | N23: =IF(B23=$K$4,1,IF(B23=$L$4,3,2)) -> 1 | O23: =IF(C23=$K$5,1,IF(C23=$L$5,3,2)) -> 3 | P23: =IF(D23=$K$6,1,IF(D23=$L$6,3,2)) -> 1 | Q23: =IF(E23=$K$7,1,IF(E23=$L$7,3,2)) -> 3
A24: Option 2 | B24: =INDEX(DOE!$A$4:$E$84,$G24,COLUMN(B:B)) -> 50 | C24: =INDEX(DOE!$A$4:$E$84,$G24,COLUMN(C:C)) -> 1 | D24: =INDEX(DOE!$A$4:$E$84,$G24,COLUMN(D:D)) -> 600 | E24: =INDEX(DOE!$A$4:$E$84,$G24,COLUMN(E:E)) -> 5 | G24: =INDEX(StaticRandomNumbers!$A$4:$BJ$93,A22*3-1,$B$1+1) -> 17 | H24: =F24*G24 -> 0 | M24: =OR(AND(N23<=N24,O23<=O24,P23<=P24,Q23<=Q24),AND(N24>=N25,O24>=O25,P24>=P25,Q24>=Q25)) -> TRUE | N24: =IF(B24=$K$4,1,IF(B24=$L$4,3,2)) -> 1 | O24: =IF(C24=$K$5,1,IF(C24=$L$5,3,2)) -> 2 | P24: =IF(D24=$K$6,1,IF(D24=$L$6,3,2)) -> 3 | Q24: =IF(E24=$K$7,1,IF(E24=$L$7,3,2)) -> 2
A25: Option 3 | B25: =INDEX(DOE!$A$4:$E$84,$G25,COLUMN(B:B)) -> 50 | C25: =INDEX(DOE!$A$4:$E$84,$G25,COLUMN(C:C)) -> 2 | D25: =INDEX(DOE!$A$4:$E$84,$G25,COLUMN(D:D)) -> 600 | E25: =INDEX(DOE!$A$4:$E$84,$G25,COLUMN(E:E)) -> 5 | F25: 1 | G25: =INDEX(StaticRandomNumbers!$A$4:$BJ$93,A22*3,$B$1+1) -> 26 | H25: =F25*G25 -> 26 | M25: =OR(AND(N25>=N24,O25>=O24,P25>=P24,Q25>=Q24),AND(N25>=N23,O25>=O23,P25>=P23,Q25>=Q23)) -> FALSE | N25: =IF(B25=$K$4,1,IF(B25=$L$4,3,2)) -> 1 | O25: =IF(C25=$K$5,1,IF(C25=$L$5,3,2)) -> 1 | P25: =IF(D25=$K$6,1,IF(D25=$L$6,3,2)) -> 3 | Q25: =IF(E25=$K$7,1,IF(E25=$L$7,3,2)) -> 2
A27: Question
A28: =A22+1 -> 4 | B28: =DOE!$B$2 -> price ($) | C28: =DOE!$C$2 -> Fluid Capacity (liters) | D28: =DOE!$D$2 -> Time to boil (sec) | E28: =DOE!$E$2 -> Boils per charge (#) | F28: Choice (mark with "1") | G28: Alt ID | M28: dominated? | N28: =B28 -> price ($) | O28: =C28 -> Fluid Capacity (liters) | P28: =D28 -> Time to boil (sec) | Q28: =E28 -> Boils per charge (#)
A29: Option 1 | B29: =INDEX(DOE!$A$4:$E$84,$G29,COLUMN(B:B)) -> 50 | C29: =INDEX(DOE!$A$4:$E$84,$G29,COLUMN(C:C)) -> 2 | D29: =INDEX(DOE!$A$4:$E$84,$G29,COLUMN(D:D)) -> 600 | E29: =INDEX(DOE!$A$4:$E$84,$G29,COLUMN(E:E)) -> 5 | G29: =INDEX(StaticRandomNumbers!$A$4:$BJ$93,A28*3-2,$B$1+1) -> 26 | H29: =F29*G29 -> 0 | J29: =IF(AND(COUNTIF(F29:F31,"")=2,COUNTIF(F29:F31,1)=1),1,0) -> 1 | M29: =OR(AND(N29>=N30,O29>=O30,P29>=P30,Q29>=Q30),AND(N29>=N31,O29>=O31,P29>=P31,Q29>=Q31)) -> FALSE | N29: =IF(B29=$K$4,1,IF(B29=$L$4,3,2)) -> 1 | O29: =IF(C29=$K$5,1,IF(C29=$L$5,3,2)) -> 1 | P29: =IF(D29=$K$6,1,IF(D29=$L$6,3,2)) -> 3 | Q29: =IF(E29=$K$7,1,IF(E29=$L$7,3,2)) -> 2
A30: Option 2 | B30: =INDEX(DOE!$A$4:$E$84,$G30,COLUMN(B:B)) -> 100 | C30: =INDEX(DOE!$A$4:$E$84,$G30,COLUMN(C:C)) -> 1 | D30: =INDEX(DOE!$A$4:$E$84,$G30,COLUMN(D:D)) -> 120 | E30: =INDEX(DOE!$A$4:$E$84,$G30,COLUMN(E:E)) -> 1 | F30: 1 | G30: =INDEX(StaticRandomNumbers!$A$4:$BJ$93,A28*3-1,$B$1+1) -> 37 | H30: =F30*G30 -> 37 | M30: =OR(AND(N29<=N30,O29<=O30,P29<=P30,Q29<=Q30),AND(N30>=N31,O30>=O31,P30>=P31,Q30>=Q31)) -> FALSE | N30: =IF(B30=$K$4,1,IF(B30=$L$4,3,2)) -> 2 | O30: =IF(C30=$K$5,1,IF(C30=$L$5,3,2)) -> 2 | P30: =IF(D30=$K$6,1,IF(D30=$L$6,3,2)) -> 1 | Q30: =IF(E30=$K$7,1,IF(E30=$L$7,3,2)) -> 3
A31: Option 3 | B31: =INDEX(DOE!$A$4:$E$84,$G31,COLUMN(B:B)) -> 50 | C31: =INDEX(DOE!$A$4:$E$84,$G31,COLUMN(C:C)) -> 0.25 | D31: =INDEX(DOE!$A$4:$E$84,$G31,COLUMN(D:D)) -> 240 | E31: =INDEX(DOE!$A$4:$E$84,$G31,COLUMN(E:E)) -> 5 | G31: =INDEX(StaticRandomNumbers!$A$4:$BJ$93,A28*3,$B$1+1) -> 5 | H31: =F31*G31 -> 0 | M31: =OR(AND(N31>=N30,O31>=O30,P31>=P30,Q31>=Q30),AND(N31>=N29,O31>=O29,P31>=P29,Q31>=Q29)) -> FALSE | N31: =IF(B31=$K$4,1,IF(B31=$L$4,3,2)) -> 1 | O31: =IF(C31=$K$5,1,IF(C31=$L$5,3,2)) -> 3 | P31: =IF(D31=$K$6,1,IF(D31=$L$6,3,2)) -> 2 | Q31: =IF(E31=$K$7,1,IF(E31=$L$7,3,2)) -> 2
A33: Question
A34: =A28+1 -> 5 | B34: =DOE!$B$2 -> price ($) | C34: =DOE!$C$2 -> Fluid Capacity (liters) | D34: =DOE!$D$2 -> Time to boil (sec) | E34: =DOE!$E$2 -> Boils per charge (#) | F34: Choice (mark with "1") | G34: Alt ID | M34: dominated? | N34: =B34 -> price ($) | O34: =C34 -> Fluid Capacity (liters) | P34: =D34 -> Time to boil (sec) | Q34: =E34 -> Boils per charge (#)
A35: Option 1 | B35: =INDEX(DOE!$A$4:$E$84,$G35,COLUMN(B:B)) -> 100 | C35: =INDEX(DOE!$A$4:$E$84,$G35,COLUMN(C:C)) -> 1 | D35: =INDEX(DOE!$A$4:$E$84,$G35,COLUMN(D:D)) -> 120 | E35: =INDEX(DOE!$A$4:$E$84,$G35,COLUMN(E:E)) -> 10 | F35: 1 | G35: =INDEX(StaticRandomNumbers!$A$4:$BJ$93,A34*3-2,$B$1+1) -> 39 | H35: =F35*G35 -> 39 | J35: =IF(AND(COUNTIF(F35:F37,"")=2,COUNTIF(F35:F37,1)=1),1,0) -> 1 | M35: =OR(AND(N35>=N36,O35>=O36,P35>=P36,Q35>=Q36),AND(N35>=N37,O35>=O37,P35>=P37,Q35>=Q37)) -> FALSE | N35: =IF(B35=$K$4,1,IF(B35=$L$4,3,2)) -> 2 | O35: =IF(C35=$K$5,1,IF(C35=$L$5,3,2)) -> 2 | P35: =IF(D35=$K$6,1,IF(D35=$L$6,3,2)) -> 1 | Q35: =IF(E35=$K$7,1,IF(E35=$L$7,3,2)) -> 1
A36: Option 2 | B36: =INDEX(DOE!$A$4:$E$84,$G36,COLUMN(B:B)) -> 50 | C36: =INDEX(DOE!$A$4:$E$84,$G36,COLUMN(C:C)) -> 2 | D36: =INDEX(DOE!$A$4:$E$84,$G36,COLUMN(D:D)) -> 120 | E36: =INDEX(DOE!$A$4:$E$84,$G36,COLUMN(E:E)) -> 5 | G36: =INDEX(StaticRandomNumbers!$A$4:$BJ$93,A34*3-1,$B$1+1) -> 20 | H36: =F36*G36 -> 0 | M36: =OR(AND(N35<=N36,O35<=O36,P35<=P36,Q35<=Q36),AND(N36>=N37,O36>=O37,P36>=P37,Q36>=Q37)) -> FALSE | N36: =IF(B36=$K$4,1,IF(B36=$L$4,3,2)) -> 1 | O36: =IF(C36=$K$5,1,IF(C36=$L$5,3,2)) -> 1 | P36: =IF(D36=$K$6,1,IF(D36=$L$6,3,2)) -> 1 | Q36: =IF(E36=$K$7,1,IF(E36=$L$7,3,2)) -> 2
A37: Option 3 | B37: =INDEX(DOE!$A$4:$E$84,$G37,COLUMN(B:B)) -> 50 | C37: =INDEX(DOE!$A$4:$E$84,$G37,COLUMN(C:C)) -> 0.25 | D37: =INDEX(DOE!$A$4:$E$84,$G37,COLUMN(D:D)) -> 600 | E37: =INDEX(DOE!$A$4:$E$84,$G37,COLUMN(E:E)) -> 5 | G37: =INDEX(StaticRandomNumbers!$A$4:$BJ$93,A34*3,$B$1+1) -> 8 | H37: =F37*G37 -> 0 | M37: =OR(AND(N37>=N36,O37>=O36,P37>=P36,Q37>=Q36),AND(N37>=N35,O37>=O35,P37>=P35,Q37>=Q35)) -> TRUE | N37: =IF(B37=$K$4,1,IF(B37=$L$4,3,2)) -> 1 | O37: =IF(C37=$K$5,1,IF(C37=$L$5,3,2)) -> 3 | P37: =IF(D37=$K$6,1,IF(D37=$L$6,3,2)) -> 3 | Q37: =IF(E37=$K$7,1,IF(E37=$L$7,3,2)) -> 2
A39: Question
A40: =A34+1 -> 6 | B40: =DOE!$B$2 -> price ($) | C40: =DOE!$C$2 -> Fluid Capacity (liters) | D40: =DOE!$D$2 -> Time to boil (sec) | E40: =DOE!$E$2 -> Boils per charge (#) | F40: Choice (mark with "1") | G40: Alt ID | M40: dominated? | N40: =B40 -> price ($) | O40: =C40 -> Fluid Capacity (liters) | P40: =D40 -> Time to boil (sec) | Q40: =E40 -> Boils per charge (#)
A41: Option 1 | B41: =INDEX(DOE!$A$4:$E$84,$G41,COLUMN(B:B)) -> 100 | C41: =INDEX(DOE!$A$4:$E$84,$G41,COLUMN(C:C)) -> 2 | D41: =INDEX(DOE!$A$4:$E$84,$G41,COLUMN(D:D)) -> 240 | E41: =INDEX(DOE!$A$4:$E$84,$G41,COLUMN(E:E)) -> 5 | F41: 1 | G41: =INDEX(StaticRandomNumbers!$A$4:$BJ$93,A40*3-2,$B$1+1) -> 50 | H41: =F41*G41 -> 50 | J41: =IF(AND(COUNTIF(F41:F43,"")=2,COUNTIF(F41:F43,1)=1),1,0) -> 1 | M41: =OR(AND(N41>=N42,O41>=O42,P41>=P42,Q41>=Q42),AND(N41>=N43,O41>=O43,P41>=P43,Q41>=Q43)) -> FALSE | N41: =IF(B41=$K$4,1,IF(B41=$L$4,3,2)) -> 2 | O41: =IF(C41=$K$5,1,IF(C41=$L$5,3,2)) -> 1 | P41: =IF(D41=$K$6,1,IF(D41=$L$6,3,2)) -> 2 | Q41: =IF(E41=$K$7,1,IF(E41=$L$7,3,2)) -> 2
A42: Option 2 | B42: =INDEX(DOE!$A$4:$E$84,$G42,COLUMN(B:B)) -> 50 | C42: =INDEX(DOE!$A$4:$E$84,$G42,COLUMN(C:C)) -> 1 | D42: =INDEX(DOE!$A$4:$E$84,$G42,COLUMN(D:D)) -> 240 | E42: =INDEX(DOE!$A$4:$E$84,$G42,COLUMN(E:E)) -> 10 | G42: =INDEX(StaticRandomNumbers!$A$4:$BJ$93,A40*3-1,$B$1+1) -> 15 | H42: =F42*G42 -> 0 | M42: =OR(AND(N41<=N42,O41<=O42,P41<=P42,Q41<=Q42),AND(N42>=N43,O42>=O43,P42>=P43,Q42>=Q43)) -> FALSE | N42: =IF(B42=$K$4,1,IF(B42=$L$4,3,2)) -> 1 | O42: =IF(C42=$K$5,1,IF(C42=$L$5,3,2)) -> 2 | P42: =IF(D42=$K$6,1,IF(D42=$L$6,3,2)) -> 2 | Q42: =IF(E42=$K$7,1,IF(E42=$L$7,3,2)) -> 1
A43: Option 3 | B43: =INDEX(DOE!$A$4:$E$84,$G43,COLUMN(B:B)) -> 100 | C43: =INDEX(DOE!$A$4:$E$84,$G43,COLUMN(C:C)) -> 2 | D43: =INDEX(DOE!$A$4:$E$84,$G43,COLUMN(D:D)) -> 600 | E43: =INDEX(DOE!$A$4:$E$84,$G43,COLUMN(E:E)) -> 10 | G43: =INDEX(StaticRandomNumbers!$A$4:$BJ$93,A40*3,$B$1+1) -> 54 | H43: =F43*G43 -> 0 | M43: =OR(AND(N43>=N42,O43>=O42,P43>=P42,Q43>=Q42),AND(N43>=N41,O43>=O41,P43>=P41,Q43>=Q41)) -> FALSE | N43: =IF(B43=$K$4,1,IF(B43=$L$4,3,2)) -> 2 | O43: =IF(C43=$K$5,1,IF(C43=$L$5,3,2)) -> 1 | P43: =IF(D43=$K$6,1,IF(D43=$L$6,3,2)) -> 3 | Q43: =IF(E43=$K$7,1,IF(E43=$L$7,3,2)) -> 1
A45: Question
A46: =A40+1 -> 7 | B46: =DOE!$B$2 -> price ($) | C46: =DOE!$C$2 -> Fluid Capacity (liters) | D46: =DOE!$D$2 -> Time to boil (sec) | E46: =DOE!$E$2 -> Boils per charge (#) | F46: Choice (mark with "1") | G46: Alt ID | M46: dominated? | N46: =B46 -> price ($) | O46: =C46 -> Fluid Capacity (liters) | P46: =D46 -> Time to boil (sec) | Q46: =E46 -> Boils per charge (#)
A47: Option 1 | B47: =INDEX(DOE!$A$4:$E$84,$G47,COLUMN(B:B)) -> 100 | C47: =INDEX(DOE!$A$4:$E$84,$G47,COLUMN(C:C)) -> 0.25 | D47: =INDEX(DOE!$A$4:$E$84,$G47,COLUMN(D:D)) -> 600 | E47: =INDEX(DOE!$A$4:$E$84,$G47,COLUMN(E:E)) -> 1 | G47: =INDEX(StaticRandomNumbers!$A$4:$BJ$93,A46*3-2,$B$1+1) -> 34 | H47: =F47*G47 -> 0 | J47: =IF(AND(COUNTIF(F47:F49,"")=2,COUNTIF(F47:F49,1)=1),1,0) -> 1 | M47: =OR(AND(N47>=N48,O47>=O48,P47>=P48,Q47>=Q48),AND(N47>=N49,O47>=O49,P47>=P49,Q47>=Q49)) -> TRUE | N47: =IF(B47=$K$4,1,IF(B47=$L$4,3,2)) -> 2 | O47: =IF(C47=$K$5,1,IF(C47=$L$5,3,2)) -> 3 | P47: =IF(D47=$K$6,1,IF(D47=$L$6,3,2)) -> 3 | Q47: =IF(E47=$K$7,1,IF(E47=$L$7,3,2)) -> 3
A48: Option 2 | B48: =INDEX(DOE!$A$4:$E$84,$G48,COLUMN(B:B)) -> 100 | C48: =INDEX(DOE!$A$4:$E$84,$G48,COLUMN(C:C)) -> 0.25 | D48: =INDEX(DOE!$A$4:$E$84,$G48,COLUMN(D:D)) -> 120 | E48: =INDEX(DOE!$A$4:$E$84,$G48,COLUMN(E:E)) -> 1 | G48: =INDEX(StaticRandomNumbers!$A$4:$BJ$93,A46*3-1,$B$1+1) -> 28 | H48: =F48*G48 -> 0 | M48: =OR(AND(N47<=N48,O47<=O48,P47<=P48,Q47<=Q48),AND(N48>=N49,O48>=O49,P48>=P49,Q48>=Q49)) -> FALSE | N48: =IF(B48=$K$4,1,IF(B48=$L$4,3,2)) -> 2 | O48: =IF(C48=$K$5,1,IF(C48=$L$5,3,2)) -> 3 | P48: =IF(D48=$K$6,1,IF(D48=$L$6,3,2)) -> 1 | Q48: =IF(E48=$K$7,1,IF(E48=$L$7,3,2)) -> 3
A49: Option 3 | B49: =INDEX(DOE!$A$4:$E$84,$G49,COLUMN(B:B)) -> 100 | C49: =INDEX(DOE!$A$4:$E$84,$G49,COLUMN(C:C)) -> 2 | D49: =INDEX(DOE!$A$4:$E$84,$G49,COLUMN(D:D)) -> 600 | E49: =INDEX(DOE!$A$4:$E$84,$G49,COLUMN(E:E)) -> 1 | F49: 1 | G49: =INDEX(StaticRandomNumbers!$A$4:$BJ$93,A46*3,$B$1+1) -> 52 | H49: =F49*G49 -> 52 | M49: =OR(AND(N49>=N48,O49>=O48,P49>=P48,Q49>=Q48),AND(N49>=N47,O49>=O47,P49>=P47,Q49>=Q47)) -> FALSE | N49: =IF(B49=$K$4,1,IF(B49=$L$4,3,2)) -> 2 | O49: =IF(C49=$K$5,1,IF(C49=$L$5,3,2)) -> 1 | P49: =IF(D49=$K$6,1,IF(D49=$L$6,3,2)) -> 3 | Q49: =IF(E49=$K$7,1,IF(E49=$L$7,3,2)) -> 3
A51: Question
A52: =A46+1 -> 8 | B52: =DOE!$B$2 -> price ($) | C52: =DOE!$C$2 -> Fluid Capacity (liters) | D52: =DOE!$D$2 -> Time to boil (sec) | E52: =DOE!$E$2 -> Boils per charge (#) | F52: Choice (mark with "1") | G52: Alt ID | M52: dominated? | N52: =B52 -> price ($) | O52: =C52 -> Fluid Capacity (liters) | P52: =D52 -> Time to boil (sec) | Q52: =E52 -> Boils per charge (#)
A53: Option 1 | B53: =INDEX(DOE!$A$4:$E$84,$G53,COLUMN(B:B)) -> 50 | C53: =INDEX(DOE!$A$4:$E$84,$G53,COLUMN(C:C)) -> 2 | D53: =INDEX(DOE!$A$4:$E$84,$G53,COLUMN(D:D)) -> 240 | E53: =INDEX(DOE!$A$4:$E$84,$G53,COLUMN(E:E)) -> 5 | F53: 1 | G53: =INDEX(StaticRandomNumbers!$A$4:$BJ$93,A52*3-2,$B$1+1) -> 23 | H53: =F53*G53 -> 23 | J53: =IF(AND(COUNTIF(F53:F55,"")=2,COUNTIF(F53:F55,1)=1),1,0) -> 1 | M53: =OR(AND(N53>=N54,O53>=O54,P53>=P54,Q53>=Q54),AND(N53>=N55,O53>=O55,P53>=P55,Q53>=Q55)) -> FALSE | N53: =IF(B53=$K$4,1,IF(B53=$L$4,3,2)) -> 1 | O53: =IF(C53=$K$5,1,IF(C53=$L$5,3,2)) -> 1 | P53: =IF(D53=$K$6,1,IF(D53=$L$6,3,2)) -> 2 | Q53: =IF(E53=$K$7,1,IF(E53=$L$7,3,2)) -> 2
A54: Option 2 | B54: =INDEX(DOE!$A$4:$E$84,$G54,COLUMN(B:B)) -> 200 | C54: =INDEX(DOE!$A$4:$E$84,$G54,COLUMN(C:C)) -> 0.25 | D54: =INDEX(DOE!$A$4:$E$84,$G54,COLUMN(D:D)) -> 240 | E54: =INDEX(DOE!$A$4:$E$84,$G54,COLUMN(E:E)) -> 1 | G54: =INDEX(StaticRandomNumbers!$A$4:$BJ$93,A52*3-1,$B$1+1) -> 58 | H54: =F54*G54 -> 0 | M54: =OR(AND(N53<=N54,O53<=O54,P53<=P54,Q53<=Q54),AND(N54>=N55,O54>=O55,P54>=P55,Q54>=Q55)) -> TRUE | N54: =IF(B54=$K$4,1,IF(B54=$L$4,3,2)) -> 3 | O54: =IF(C54=$K$5,1,IF(C54=$L$5,3,2)) -> 3 | P54: =IF(D54=$K$6,1,IF(D54=$L$6,3,2)) -> 2 | Q54: =IF(E54=$K$7,1,IF(E54=$L$7,3,2)) -> 3
A55: Option 3 | B55: =INDEX(DOE!$A$4:$E$84,$G55,COLUMN(B:B)) -> 200 | C55: =INDEX(DOE!$A$4:$E$84,$G55,COLUMN(C:C)) -> 2 | D55: =INDEX(DOE!$A$4:$E$84,$G55,COLUMN(D:D)) -> 240 | E55: =INDEX(DOE!$A$4:$E$84,$G55,COLUMN(E:E)) -> 5 | G55: =INDEX(StaticRandomNumbers!$A$4:$BJ$93,A52*3,$B$1+1) -> 77 | H55: =F55*G55 -> 0 | M55: =OR(AND(N55>=N54,O55>=O54,P55>=P54,Q55>=Q54),AND(N55>=N53,O55>=O53,P55>=P53,Q55>=Q53)) -> TRUE | N55: =IF(B55=$K$4,1,IF(B55=$L$4,3,2)) -> 3 | O55: =IF(C55=$K$5,1,IF(C55=$L$5,3,2)) -> 1 | P55: =IF(D55=$K$6,1,IF(D55=$L$6,3,2)) -> 2 | Q55: =IF(E55=$K$7,1,IF(E55=$L$7,3,2)) -> 2
A57: Question
A58: =A52+1 -> 9 | B58: =DOE!$B$2 -> price ($) | C58: =DOE!$C$2 -> Fluid Capacity (liters) | D58: =DOE!$D$2 -> Time to boil (sec) | E58: =DOE!$E$2 -> Boils per charge (#) | F58: Choice (mark with "1") | G58: Alt ID | M58: dominated? | N58: =B58 -> price ($) | O58: =C58 -> Fluid Capacity (liters) | P58: =D58 -> Time to boil (sec) | Q58: =E58 -> Boils per charge (#)
A59: Option 1 | B59: =INDEX(DOE!$A$4:$E$84,$G59,COLUMN(B:B)) -> 200 | C59: =INDEX(DOE!$A$4:$E$84,$G59,COLUMN(C:C)) -> 1 | D59: =INDEX(DOE!$A$4:$E$84,$G59,COLUMN(D:D)) -> 240 | E59: =INDEX(DOE!$A$4:$E$84,$G59,COLUMN(E:E)) -> 10 | G59: =INDEX(StaticRandomNumbers!$A$4:$BJ$93,A58*3-2,$B$1+1) -> 69 | H59: =F59*G59 -> 0 | J59: =IF(AND(COUNTIF(F59:F61,"")=2,COUNTIF(F59:F61,1)=1),1,0) -> 1 | M59: =OR(AND(N59>=N60,O59>=O60,P59>=P60,Q59>=Q60),AND(N59>=N61,O59>=O61,P59>=P61,Q59>=Q61)) -> FALSE | N59: =IF(B59=$K$4,1,IF(B59=$L$4,3,2)) -> 3 | O59: =IF(C59=$K$5,1,IF(C59=$L$5,3,2)) -> 2 | P59: =IF(D59=$K$6,1,IF(D59=$L$6,3,2)) -> 2 | Q59: =IF(E59=$K$7,1,IF(E59=$L$7,3,2)) -> 1
A60: Option 2 | B60: =INDEX(DOE!$A$4:$E$84,$G60,COLUMN(B:B)) -> 200 | C60: =INDEX(DOE!$A$4:$E$84,$G60,COLUMN(C:C)) -> 1 | D60: =INDEX(DOE!$A$4:$E$84,$G60,COLUMN(D:D)) -> 600 | E60: =INDEX(DOE!$A$4:$E$84,$G60,COLUMN(E:E)) -> 5 | G60: =INDEX(StaticRandomNumbers!$A$4:$BJ$93,A58*3-1,$B$1+1) -> 71 | H60: =F60*G60 -> 0 | M60: =OR(AND(N59<=N60,O59<=O60,P59<=P60,Q59<=Q60),AND(N60>=N61,O60>=O61,P60>=P61,Q60>=Q61)) -> TRUE | N60: =IF(B60=$K$4,1,IF(B60=$L$4,3,2)) -> 3 | O60: =IF(C60=$K$5,1,IF(C60=$L$5,3,2)) -> 2 | P60: =IF(D60=$K$6,1,IF(D60=$L$6,3,2)) -> 3 | Q60: =IF(E60=$K$7,1,IF(E60=$L$7,3,2)) -> 2
A61: Option 3 | B61: =INDEX(DOE!$A$4:$E$84,$G61,COLUMN(B:B)) -> 50 | C61: =INDEX(DOE!$A$4:$E$84,$G61,COLUMN(C:C)) -> 1 | D61: =INDEX(DOE!$A$4:$E$84,$G61,COLUMN(D:D)) -> 120 | E61: =INDEX(DOE!$A$4:$E$84,$G61,COLUMN(E:E)) -> 1 | F61: 1 | G61: =INDEX(StaticRandomNumbers!$A$4:$BJ$93,A58*3,$B$1+1) -> 10 | H61: =F61*G61 -> 10 | M61: =OR(AND(N61>=N60,O61>=O60,P61>=P60,Q61>=Q60),AND(N61>=N59,O61>=O59,P61>=P59,Q61>=Q59)) -> FALSE | N61: =IF(B61=$K$4,1,IF(B61=$L$4,3,2)) -> 1 | O61: =IF(C61=$K$5,1,IF(C61=$L$5,3,2)) -> 2 | P61: =IF(D61=$K$6,1,IF(D61=$L$6,3,2)) -> 1 | Q61: =IF(E61=$K$7,1,IF(E61=$L$7,3,2)) -> 3
A63: Question
A64: =A58+1 -> 10 | B64: =DOE!$B$2 -> price ($) | C64: =DOE!$C$2 -> Fluid Capacity (liters) | D64: =DOE!$D$2 -> Time to boil (sec) | E64: =DOE!$E$2 -> Boils per charge (#) | F64: Choice (mark with "1") | G64: Alt ID | M64: dominated? | N64: =B64 -> price ($) | O64: =C64 -> Fluid Capacity (liters) | P64: =D64 -> Time to boil (sec) | Q64: =E64 -> Boils per charge (#)
A65: Option 1 | B65: =INDEX(DOE!$A$4:$E$84,$G65,COLUMN(B:B)) -> 100 | C65: =INDEX(DOE!$A$4:$E$84,$G65,COLUMN(C:C)) -> 0.25 | D65: =INDEX(DOE!$A$4:$E$84,$G65,COLUMN(D:D)) -> 240 | E65: =INDEX(DOE!$A$4:$E$84,$G65,COLUMN(E:E)) -> 1 | G65: =INDEX(StaticRandomNumbers!$A$4:$BJ$93,A64*3-2,$B$1+1) -> 31 | H65: =F65*G65 -> 0 | J65: =IF(AND(COUNTIF(F65:F67,"")=2,COUNTIF(F65:F67,1)=1),1,0) -> 1 | M65: =OR(AND(N65>=N66,O65>=O66,P65>=P66,Q65>=Q66),AND(N65>=N67,O65>=O67,P65>=P67,Q65>=Q67)) -> FALSE | N65: =IF(B65=$K$4,1,IF(B65=$L$4,3,2)) -> 2 | O65: =IF(C65=$K$5,1,IF(C65=$L$5,3,2)) -> 3 | P65: =IF(D65=$K$6,1,IF(D65=$L$6,3,2)) -> 2 | Q65: =IF(E65=$K$7,1,IF(E65=$L$7,3,2)) -> 3
A66: Option 2 | B66: =INDEX(DOE!$A$4:$E$84,$G66,COLUMN(B:B)) -> 50 | C66: =INDEX(DOE!$A$4:$E$84,$G66,COLUMN(C:C)) -> 1 | D66: =INDEX(DOE!$A$4:$E$84,$G66,COLUMN(D:D)) -> 600 | E66: =INDEX(DOE!$A$4:$E$84,$G66,COLUMN(E:E)) -> 5 | F66: 1 | G66: =INDEX(StaticRandomNumbers!$A$4:$BJ$93,A64*3-1,$B$1+1) -> 17 | H66: =#REF!*G66 -> #REF! | M66: =OR(AND(N65<=N66,O65<=O66,P65<=P66,Q65<=Q66),AND(N66>=N67,O66>=O67,P66>=P67,Q66>=Q67)) -> FALSE | N66: =IF(B66=$K$4,1,IF(B66=$L$4,3,2)) -> 1 | O66: =IF(C66=$K$5,1,IF(C66=$L$5,3,2)) -> 2 | P66: =IF(D66=$K$6,1,IF(D66=$L$6,3,2)) -> 3 | Q66: =IF(E66=$K$7,1,IF(E66=$L$7,3,2)) -> 2
A67: Option 3 | B67: =INDEX(DOE!$A$4:$E$84,$G67,COLUMN(B:B)) -> 200 | C67: =INDEX(DOE!$A$4:$E$84,$G67,COLUMN(C:C)) -> 2 | D67: =INDEX(DOE!$A$4:$E$84,$G67,COLUMN(D:D)) -> 600 | E67: =INDEX(DOE!$A$4:$E$84,$G67,COLUMN(E:E)) -> 5 | G67: =INDEX(StaticRandomNumbers!$A$4:$BJ$93,A64*3,$B$1+1) -> 80 | H67: =F66*G67 -> 80 | M67: =OR(AND(N67>=N66,O67>=O66,P67>=P66,Q67>=Q66),AND(N67>=N65,O67>=O65,P67>=P65,Q67>=Q65)) -> FALSE | N67: =IF(B67=$K$4,1,IF(B67=$L$4,3,2)) -> 3 | O67: =IF(C67=$K$5,1,IF(C67=$L$5,3,2)) -> 1 | P67: =IF(D67=$K$6,1,IF(D67=$L$6,3,2)) -> 3 | Q67: =IF(E67=$K$7,1,IF(E67=$L$7,3,2)) -> 2
A69: Question
A70: =A64+1 -> 11 | B70: =DOE!$B$2 -> price ($) | C70: =DOE!$C$2 -> Fluid Capacity (liters) | D70: =DOE!$D$2 -> Time to boil (sec) | E70: =DOE!$E$2 -> Boils per charge (#) | F70: Choice (mark with "1") | G70: Alt ID | M70: dominated? | N70: =B70 -> price ($) | O70: =C70 -> Fluid Capacity (liters) | P70: =D70 -> Time to boil (sec) | Q70: =E70 -> Boils per charge (#)
A71: Option 1 | B71: =INDEX(DOE!$A$4:$E$84,$G71,COLUMN(B:B)) -> 50 | C71: =INDEX(DOE!$A$4:$E$84,$G71,COLUMN(C:C)) -> 2 | D71: =INDEX(DOE!$A$4:$E$84,$G71,COLUMN(D:D)) -> 240 | E71: =INDEX(DOE!$A$4:$E$84,$G71,COLUMN(E:E)) -> 1 | F71: 1 | G71: =INDEX(StaticRandomNumbers!$A$4:$BJ$93,A70*3-2,$B$1+1) -> 22 | H71: =F71*G71 -> 22 | J71: =IF(AND(COUNTIF(F71:F73,"")=2,COUNTIF(F71:F73,1)=1),1,0) -> 1 | M71: =OR(AND(N71>=N72,O71>=O72,P71>=P72,Q71>=Q72),AND(N71>=N73,O71>=O73,P71>=P73,Q71>=Q73)) -> FALSE | N71: =IF(B71=$K$4,1,IF(B71=$L$4,3,2)) -> 1 | O71: =IF(C71=$K$5,1,IF(C71=$L$5,3,2)) -> 1 | P71: =IF(D71=$K$6,1,IF(D71=$L$6,3,2)) -> 2 | Q71: =IF(E71=$K$7,1,IF(E71=$L$7,3,2)) -> 3
A72: Option 2 | B72: =INDEX(DOE!$A$4:$E$84,$G72,COLUMN(B:B)) -> 100 | C72: =INDEX(DOE!$A$4:$E$84,$G72,COLUMN(C:C)) -> 0.25 | D72: =INDEX(DOE!$A$4:$E$84,$G72,COLUMN(D:D)) -> 240 | E72: =INDEX(DOE!$A$4:$E$84,$G72,COLUMN(E:E)) -> 1 | G72: =INDEX(StaticRandomNumbers!$A$4:$BJ$93,A70*3-1,$B$1+1) -> 31 | H72: =F72*G72 -> 0 | M72: =OR(AND(N71<=N72,O71<=O72,P71<=P72,Q71<=Q72),AND(N72>=N73,O72>=O73,P72>=P73,Q72>=Q73)) -> TRUE | N72: =IF(B72=$K$4,1,IF(B72=$L$4,3,2)) -> 2 | O72: =IF(C72=$K$5,1,IF(C72=$L$5,3,2)) -> 3 | P72: =IF(D72=$K$6,1,IF(D72=$L$6,3,2)) -> 2 | Q72: =IF(E72=$K$7,1,IF(E72=$L$7,3,2)) -> 3
A73: Option 3 | B73: =INDEX(DOE!$A$4:$E$84,$G73,COLUMN(B:B)) -> 200 | C73: =INDEX(DOE!$A$4:$E$84,$G73,COLUMN(C:C)) -> 2 | D73: =INDEX(DOE!$A$4:$E$84,$G73,COLUMN(D:D)) -> 600 | E73: =INDEX(DOE!$A$4:$E$84,$G73,COLUMN(E:E)) -> 1 | G73: =INDEX(StaticRandomNumbers!$A$4:$BJ$93,A70*3,$B$1+1) -> 79 | H73: =F73*G73 -> 0 | M73: =OR(AND(N73>=N72,O73>=O72,P73>=P72,Q73>=Q72),AND(N73>=N71,O73>=O71,P73>=P71,Q73>=Q71)) -> TRUE | N73: =IF(B73=$K$4,1,IF(B73=$L$4,3,2)) -> 3 | O73: =IF(C73=$K$5,1,IF(C73=$L$5,3,2)) -> 1 | P73: =IF(D73=$K$6,1,IF(D73=$L$6,3,2)) -> 3 | Q73: =IF(E73=$K$7,1,IF(E73=$L$7,3,2)) -> 3
A75: Question
A76: =A70+1 -> 12 | B76: =DOE!$B$2 -> price ($) | C76: =DOE!$C$2 -> Fluid Capacity (liters) | D76: =DOE!$D$2 -> Time to boil (sec) | E76: =DOE!$E$2 -> Boils per charge (#) | F76: Choice (mark with "1") | G76: Alt ID | M76: dominated? | N76: =B76 -> price ($) | O76: =C76 -> Fluid Capacity (liters) | P76: =D76 -> Time to boil (sec) | Q76: =E76 -> Boils per charge (#)
A77: Option 1 | B77: =INDEX(DOE!$A$4:$E$84,$G77,COLUMN(B:B)) -> 50 | C77: =INDEX(DOE!$A$4:$E$84,$G77,COLUMN(C:C)) -> 2 | D77: =INDEX(DOE!$A$4:$E$84,$G77,COLUMN(D:D)) -> 120 | E77: =INDEX(DOE!$A$4:$E$84,$G77,COLUMN(E:E)) -> 1 | F77: 1 | G77: =INDEX(StaticRandomNumbers!$A$4:$BJ$93,A76*3-2,$B$1+1) -> 19 | H77: =F77*G77 -> 19 | J77: =IF(AND(COUNTIF(F77:F79,"")=2,COUNTIF(F77:F79,1)=1),1,0) -> 1 | M77: =OR(AND(N77>=N78,O77>=O78,P77>=P78,Q77>=Q78),AND(N77>=N79,O77>=O79,P77>=P79,Q77>=Q79)) -> FALSE | N77: =IF(B77=$K$4,1,IF(B77=$L$4,3,2)) -> 1 | O77: =IF(C77=$K$5,1,IF(C77=$L$5,3,2)) -> 1 | P77: =IF(D77=$K$6,1,IF(D77=$L$6,3,2)) -> 1 | Q77: =IF(E77=$K$7,1,IF(E77=$L$7,3,2)) -> 3
A78: Option 2 | B78: =INDEX(DOE!$A$4:$E$84,$G78,COLUMN(B:B)) -> 200 | C78: =INDEX(DOE!$A$4:$E$84,$G78,COLUMN(C:C)) -> 2 | D78: =INDEX(DOE!$A$4:$E$84,$G78,COLUMN(D:D)) -> 600 | E78: =INDEX(DOE!$A$4:$E$84,$G78,COLUMN(E:E)) -> 5 | G78: =INDEX(StaticRandomNumbers!$A$4:$BJ$93,A76*3-1,$B$1+1) -> 80 | H78: =F78*G78 -> 0 | M78: =OR(AND(N77<=N78,O77<=O78,P77<=P78,Q77<=Q78),AND(N78>=N79,O78>=O79,P78>=P79,Q78>=Q79)) -> FALSE | N78: =IF(B78=$K$4,1,IF(B78=$L$4,3,2)) -> 3 | O78: =IF(C78=$K$5,1,IF(C78=$L$5,3,2)) -> 1 | P78: =IF(D78=$K$6,1,IF(D78=$L$6,3,2)) -> 3 | Q78: =IF(E78=$K$7,1,IF(E78=$L$7,3,2)) -> 2
A79: Option 3 | B79: =INDEX(DOE!$A$4:$E$84,$G79,COLUMN(B:B)) -> 50 | C79: =INDEX(DOE!$A$4:$E$84,$G79,COLUMN(C:C)) -> 0.25 | D79: =INDEX(DOE!$A$4:$E$84,$G79,COLUMN(D:D)) -> 240 | E79: =INDEX(DOE!$A$4:$E$84,$G79,COLUMN(E:E)) -> 10 | G79: =INDEX(StaticRandomNumbers!$A$4:$BJ$93,A76*3,$B$1+1) -> 6 | H79: =F79*G79 -> 0 | M79: =OR(AND(N79>=N78,O79>=O78,P79>=P78,Q79>=Q78),AND(N79>=N77,O79>=O77,P79>=P77,Q79>=Q77)) -> FALSE | N79: =IF(B79=$K$4,1,IF(B79=$L$4,3,2)) -> 1 | O79: =IF(C79=$K$5,1,IF(C79=$L$5,3,2)) -> 3 | P79: =IF(D79=$K$6,1,IF(D79=$L$6,3,2)) -> 2 | Q79: =IF(E79=$K$7,1,IF(E79=$L$7,3,2)) -> 1
A81: Question
A82: =A76+1 -> 13 | B82: =DOE!$B$2 -> price ($) | C82: =DOE!$C$2 -> Fluid Capacity (liters) | D82: =DOE!$D$2 -> Time to boil (sec) | E82: =DOE!$E$2 -> Boils per charge (#) | F82: Choice (mark with "1") | G82: Alt ID | M82: dominated? | N82: =B82 -> price ($) | O82: =C82 -> Fluid Capacity (liters) | P82: =D82 -> Time to boil (sec) | Q82: =E82 -> Boils per charge (#)
A83: Option 1 | B83: =INDEX(DOE!$A$4:$E$84,$G83,COLUMN(B:B)) -> 50 | C83: =INDEX(DOE!$A$4:$E$84,$G83,COLUMN(C:C)) -> 1 | D83: =INDEX(DOE!$A$4:$E$84,$G83,COLUMN(D:D)) -> 240 | E83: =INDEX(DOE!$A$4:$E$84,$G83,COLUMN(E:E)) -> 5 | F83: 1 | G83: =INDEX(StaticRandomNumbers!$A$4:$BJ$93,A82*3-2,$B$1+1) -> 14 | H83: =F83*G83 -> 14 | J83: =IF(AND(COUNTIF(F83:F85,"")=2,COUNTIF(F83:F85,1)=1),1,0) -> 1 | M83: =OR(AND(N83>=N84,O83>=O84,P83>=P84,Q83>=Q84),AND(N83>=N85,O83>=O85,P83>=P85,Q83>=Q85)) -> FALSE | N83: =IF(B83=$K$4,1,IF(B83=$L$4,3,2)) -> 1 | O83: =IF(C83=$K$5,1,IF(C83=$L$5,3,2)) -> 2 | P83: =IF(D83=$K$6,1,IF(D83=$L$6,3,2)) -> 2 | Q83: =IF(E83=$K$7,1,IF(E83=$L$7,3,2)) -> 2
A84: Option 2 | B84: =INDEX(DOE!$A$4:$E$84,$G84,COLUMN(B:B)) -> 50 | C84: =INDEX(DOE!$A$4:$E$84,$G84,COLUMN(C:C)) -> 1 | D84: =INDEX(DOE!$A$4:$E$84,$G84,COLUMN(D:D)) -> 600 | E84: =INDEX(DOE!$A$4:$E$84,$G84,COLUMN(E:E)) -> 1 | G84: =INDEX(StaticRandomNumbers!$A$4:$BJ$93,A82*3-1,$B$1+1) -> 16 | H84: =F84*G84 -> 0 | M84: =OR(AND(N83<=N84,O83<=O84,P83<=P84,Q83<=Q84),AND(N84>=N85,O84>=O85,P84>=P85,Q84>=Q85)) -> TRUE | N84: =IF(B84=$K$4,1,IF(B84=$L$4,3,2)) -> 1 | O84: =IF(C84=$K$5,1,IF(C84=$L$5,3,2)) -> 2 | P84: =IF(D84=$K$6,1,IF(D84=$L$6,3,2)) -> 3 | Q84: =IF(E84=$K$7,1,IF(E84=$L$7,3,2)) -> 3
A85: Option 3 | B85: =INDEX(DOE!$A$4:$E$84,$G85,COLUMN(B:B)) -> 200 | C85: =INDEX(DOE!$A$4:$E$84,$G85,COLUMN(C:C)) -> 0.25 | D85: =INDEX(DOE!$A$4:$E$84,$G85,COLUMN(D:D)) -> 120 | E85: =INDEX(DOE!$A$4:$E$84,$G85,COLUMN(E:E)) -> 5 | G85: =INDEX(StaticRandomNumbers!$A$4:$BJ$93,A82*3,$B$1+1) -> 56 | H85: =F85*G85 -> 0 | M85: =OR(AND(N85>=N84,O85>=O84,P85>=P84,Q85>=Q84),AND(N85>=N83,O85>=O83,P85>=P83,Q85>=Q83)) -> FALSE | N85: =IF(B85=$K$4,1,IF(B85=$L$4,3,2)) -> 3 | O85: =IF(C85=$K$5,1,IF(C85=$L$5,3,2)) -> 3 | P85: =IF(D85=$K$6,1,IF(D85=$L$6,3,2)) -> 1 | Q85: =IF(E85=$K$7,1,IF(E85=$L$7,3,2)) -> 2
A87: Question
A88: =A82+1 -> 14 | B88: =DOE!$B$2 -> price ($) | C88: =DOE!$C$2 -> Fluid Capacity (liters) | D88: =DOE!$D$2 -> Time to boil (sec) | E88: =DOE!$E$2 -> Boils per charge (#) | F88: Choice (mark with "1") | G88: Alt ID | M88: dominated? | N88: =B88 -> price ($) | O88: =C88 -> Fluid Capacity (liters) | P88: =D88 -> Time to boil (sec) | Q88: =E88 -> Boils per charge (#)
A89: Option 1 | B89: =INDEX(DOE!$A$4:$E$84,$G89,COLUMN(B:B)) -> 100 | C89: =INDEX(DOE!$A$4:$E$84,$G89,COLUMN(C:C)) -> 2 | D89: =INDEX(DOE!$A$4:$E$84,$G89,COLUMN(D:D)) -> 600 | E89: =INDEX(DOE!$A$4:$E$84,$G89,COLUMN(E:E)) -> 5 | G89: =INDEX(StaticRandomNumbers!$A$4:$BJ$93,A88*3-2,$B$1+1) -> 53 | H89: =F89*G89 -> 0 | J89: =IF(AND(COUNTIF(F89:F91,"")=2,COUNTIF(F89:F91,1)=1),1,0) -> 1 | M89: =OR(AND(N89>=N90,O89>=O90,P89>=P90,Q89>=Q90),AND(N89>=N91,O89>=O91,P89>=P91,Q89>=Q91)) -> FALSE | N89: =IF(B89=$K$4,1,IF(B89=$L$4,3,2)) -> 2 | O89: =IF(C89=$K$5,1,IF(C89=$L$5,3,2)) -> 1 | P89: =IF(D89=$K$6,1,IF(D89=$L$6,3,2)) -> 3 | Q89: =IF(E89=$K$7,1,IF(E89=$L$7,3,2)) -> 2
A90: Option 2 | B90: =INDEX(DOE!$A$4:$E$84,$G90,COLUMN(B:B)) -> 200 | C90: =INDEX(DOE!$A$4:$E$84,$G90,COLUMN(C:C)) -> 1 | D90: =INDEX(DOE!$A$4:$E$84,$G90,COLUMN(D:D)) -> 240 | E90: =INDEX(DOE!$A$4:$E$84,$G90,COLUMN(E:E)) -> 10 | G90: =INDEX(StaticRandomNumbers!$A$4:$BJ$93,A88*3-1,$B$1+1) -> 69 | H90: =F90*G90 -> 0 | M90: =OR(AND(N89<=N90,O89<=O90,P89<=P90,Q89<=Q90),AND(N90>=N91,O90>=O91,P90>=P91,Q90>=Q91)) -> FALSE | N90: =IF(B90=$K$4,1,IF(B90=$L$4,3,2)) -> 3 | O90: =IF(C90=$K$5,1,IF(C90=$L$5,3,2)) -> 2 | P90: =IF(D90=$K$6,1,IF(D90=$L$6,3,2)) -> 2 | Q90: =IF(E90=$K$7,1,IF(E90=$L$7,3,2)) -> 1
A91: Option 3 | B91: =INDEX(DOE!$A$4:$E$84,$G91,COLUMN(B:B)) -> 50 | C91: =INDEX(DOE!$A$4:$E$84,$G91,COLUMN(C:C)) -> 1 | D91: =INDEX(DOE!$A$4:$E$84,$G91,COLUMN(D:D)) -> 120 | E91: =INDEX(DOE!$A$4:$E$84,$G91,COLUMN(E:E)) -> 5 | F91: 1 | G91: =INDEX(StaticRandomNumbers!$A$4:$BJ$93,A88*3,$B$1+1) -> 11 | H91: =F91*G91 -> 11 | M91: =OR(AND(N91>=N90,O91>=O90,P91>=P90,Q91>=Q90),AND(N91>=N89,O91>=O89,P91>=P89,Q91>=Q89)) -> FALSE | N91: =IF(B91=$K$4,1,IF(B91=$L$4,3,2)) -> 1 | O91: =IF(C91=$K$5,1,IF(C91=$L$5,3,2)) -> 2 | P91: =IF(D91=$K$6,1,IF(D91=$L$6,3,2)) -> 1 | Q91: =IF(E91=$K$7,1,IF(E91=$L$7,3,2)) -> 2
A93: Question
A94: =A88+1 -> 15 | B94: =DOE!$B$2 -> price ($) | C94: =DOE!$C$2 -> Fluid Capacity (liters) | D94: =DOE!$D$2 -> Time to boil (sec) | E94: =DOE!$E$2 -> Boils per charge (#) | F94: Choice (mark with "1") | G94: Alt ID | M94: dominated? | N94: =B94 -> price ($) | O94: =C94 -> Fluid Capacity (liters) | P94: =D94 -> Time to boil (sec) | Q94: =E94 -> Boils per charge (#)
A95: Option 1 | B95: =INDEX(DOE!$A$4:$E$84,$G95,COLUMN(B:B)) -> 200 | C95: =INDEX(DOE!$A$4:$E$84,$G95,COLUMN(C:C)) -> 0.25 | D95: =INDEX(DOE!$A$4:$E$84,$G95,COLUMN(D:D)) -> 240 | E95: =INDEX(DOE!$A$4:$E$84,$G95,COLUMN(E:E)) -> 10 | G95: =INDEX(StaticRandomNumbers!$A$4:$BJ$93,A94*3-2,$B$1+1) -> 60 | H95: =F95*G95 -> 0 | J95: =IF(AND(COUNTIF(F95:F97,"")=2,COUNTIF(F95:F97,1)=1),1,0) -> 1 | M95: =OR(AND(N95>=N96,O95>=O96,P95>=P96,Q95>=Q96),AND(N95>=N97,O95>=O97,P95>=P97,Q95>=Q97)) -> TRUE | N95: =IF(B95=$K$4,1,IF(B95=$L$4,3,2)) -> 3 | O95: =IF(C95=$K$5,1,IF(C95=$L$5,3,2)) -> 3 | P95: =IF(D95=$K$6,1,IF(D95=$L$6,3,2)) -> 2 | Q95: =IF(E95=$K$7,1,IF(E95=$L$7,3,2)) -> 1
A96: Option 2 | B96: =INDEX(DOE!$A$4:$E$84,$G96,COLUMN(B:B)) -> 100 | C96: =INDEX(DOE!$A$4:$E$84,$G96,COLUMN(C:C)) -> 0.25 | D96: =INDEX(DOE!$A$4:$E$84,$G96,COLUMN(D:D)) -> 600 | E96: =INDEX(DOE!$A$4:$E$84,$G96,COLUMN(E:E)) -> 1 | G96: =INDEX(StaticRandomNumbers!$A$4:$BJ$93,A94*3-1,$B$1+1) -> 34 | H96: =F96*G96 -> 0 | M96: =OR(AND(N95<=N96,O95<=O96,P95<=P96,Q95<=Q96),AND(N96>=N97,O96>=O97,P96>=P97,Q96>=Q97)) -> TRUE | N96: =IF(B96=$K$4,1,IF(B96=$L$4,3,2)) -> 2 | O96: =IF(C96=$K$5,1,IF(C96=$L$5,3,2)) -> 3 | P96: =IF(D96=$K$6,1,IF(D96=$L$6,3,2)) -> 3 | Q96: =IF(E96=$K$7,1,IF(E96=$L$7,3,2)) -> 3
A97: Option 3 | B97: =INDEX(DOE!$A$4:$E$84,$G97,COLUMN(B:B)) -> 50 | C97: =INDEX(DOE!$A$4:$E$84,$G97,COLUMN(C:C)) -> 2 | D97: =INDEX(DOE!$A$4:$E$84,$G97,COLUMN(D:D)) -> 240 | E97: =INDEX(DOE!$A$4:$E$84,$G97,COLUMN(E:E)) -> 10 | F97: 1 | G97: =INDEX(StaticRandomNumbers!$A$4:$BJ$93,A94*3,$B$1+1) -> 24 | H97: =F97*G97 -> 24 | M97: =OR(AND(N97>=N96,O97>=O96,P97>=P96,Q97>=Q96),AND(N97>=N95,O97>=O95,P97>=P95,Q97>=Q95)) -> FALSE | N97: =IF(B97=$K$4,1,IF(B97=$L$4,3,2)) -> 1 | O97: =IF(C97=$K$5,1,IF(C97=$L$5,3,2)) -> 1 | P97: =IF(D97=$K$6,1,IF(D97=$L$6,3,2)) -> 2 | Q97: =IF(E97=$K$7,1,IF(E97=$L$7,3,2)) -> 1
A99: Question
A100: =A94+1 -> 16 | B100: =DOE!$B$2 -> price ($) | C100: =DOE!$C$2 -> Fluid Capacity (liters) | D100: =DOE!$D$2 -> Time to boil (sec) | E100: =DOE!$E$2 -> Boils per charge (#) | F100: Choice (mark with "1") | G100: Alt ID | M100: dominated? | N100: =B100 -> price ($) | O100: =C100 -> Fluid Capacity (liters) | P100: =D100 -> Time to boil (sec) | Q100: =E100 -> Boils per charge (#)
A101: Option 1 | B101: =INDEX(DOE!$A$4:$E$84,$G101,COLUMN(B:B)) -> 100 | C101: =INDEX(DOE!$A$4:$E$84,$G101,COLUMN(C:C)) -> 2 | D101: =INDEX(DOE!$A$4:$E$84,$G101,COLUMN(D:D)) -> 120 | E101: =INDEX(DOE!$A$4:$E$84,$G101,COLUMN(E:E)) -> 10 | F101: 1 | G101: =INDEX(StaticRandomNumbers!$A$4:$BJ$93,A100*3-2,$B$1+1) -> 48 | H101: =F101*G101 -> 48 | J101: =IF(AND(COUNTIF(F101:F103,"")=2,COUNTIF(F101:F103,1)=1),1,0) -> 1 | M101: =OR(AND(N101>=N102,O101>=O102,P101>=P102,Q101>=Q102),AND(N101>=N103,O101>=O103,P101>=P103,Q101>=Q103)) -> FALSE | N101: =IF(B101=$K$4,1,IF(B101=$L$4,3,2)) -> 2 | O101: =IF(C101=$K$5,1,IF(C101=$L$5,3,2)) -> 1 | P101: =IF(D101=$K$6,1,IF(D101=$L$6,3,2)) -> 1 | Q101: =IF(E101=$K$7,1,IF(E101=$L$7,3,2)) -> 1
A102: Option 2 | B102: =INDEX(DOE!$A$4:$E$84,$G102,COLUMN(B:B)) -> 100 | C102: =INDEX(DOE!$A$4:$E$84,$G102,COLUMN(C:C)) -> 0.25 | D102: =INDEX(DOE!$A$4:$E$84,$G102,COLUMN(D:D)) -> 600 | E102: =INDEX(DOE!$A$4:$E$84,$G102,COLUMN(E:E)) -> 1 | G102: =INDEX(StaticRandomNumbers!$A$4:$BJ$93,A100*3-1,$B$1+1) -> 34 | H102: =F102*G102 -> 0 | M102: =OR(AND(N101<=N102,O101<=O102,P101<=P102,Q101<=Q102),AND(N102>=N103,O102>=O103,P102>=P103,Q102>=Q103)) -> TRUE | N102: =IF(B102=$K$4,1,IF(B102=$L$4,3,2)) -> 2 | O102: =IF(C102=$K$5,1,IF(C102=$L$5,3,2)) -> 3 | P102: =IF(D102=$K$6,1,IF(D102=$L$6,3,2)) -> 3 | Q102: =IF(E102=$K$7,1,IF(E102=$L$7,3,2)) -> 3
A103: Option 3 | B103: =INDEX(DOE!$A$4:$E$84,$G103,COLUMN(B:B)) -> 200 | C103: =INDEX(DOE!$A$4:$E$84,$G103,COLUMN(C:C)) -> 2 | D103: =INDEX(DOE!$A$4:$E$84,$G103,COLUMN(D:D)) -> 240 | E103: =INDEX(DOE!$A$4:$E$84,$G103,COLUMN(E:E)) -> 10 | G103: =INDEX(StaticRandomNumbers!$A$4:$BJ$93,A100*3,$B$1+1) -> 78 | H103: =F103*G103 -> 0 | M103: =OR(AND(N103>=N102,O103>=O102,P103>=P102,Q103>=Q102),AND(N103>=N101,O103>=O101,P103>=P101,Q103>=Q101)) -> TRUE | N103: =IF(B103=$K$4,1,IF(B103=$L$4,3,2)) -> 3 | O103: =IF(C103=$K$5,1,IF(C103=$L$5,3,2)) -> 1 | P103: =IF(D103=$K$6,1,IF(D103=$L$6,3,2)) -> 2 | Q103: =IF(E103=$K$7,1,IF(E103=$L$7,3,2)) -> 1
A105: Question
A106: =A100+1 -> 17 | B106: =DOE!$B$2 -> price ($) | C106: =DOE!$C$2 -> Fluid Capacity (liters) | D106: =DOE!$D$2 -> Time to boil (sec) | E106: =DOE!$E$2 -> Boils per charge (#) | F106: Choice (mark with "1") | G106: Alt ID | M106: dominated? | N106: =B106 -> price ($) | O106: =C106 -> Fluid Capacity (liters) | P106: =D106 -> Time to boil (sec) | Q106: =E106 -> Boils per charge (#)
A107: Option 1 | B107: =INDEX(DOE!$A$4:$E$84,$G107,COLUMN(B:B)) -> 100 | C107: =INDEX(DOE!$A$4:$E$84,$G107,COLUMN(C:C)) -> 1 | D107: =INDEX(DOE!$A$4:$E$84,$G107,COLUMN(D:D)) -> 120 | E107: =INDEX(DOE!$A$4:$E$84,$G107,COLUMN(E:E)) -> 10 | G107: =INDEX(StaticRandomNumbers!$A$4:$BJ$93,A106*3-2,$B$1+1) -> 39 | H107: =F107*G107 -> 0 | J107: =IF(AND(COUNTIF(F107:F109,"")=2,COUNTIF(F107:F109,1)=1),1,0) -> 1 | M107: =OR(AND(N107>=N108,O107>=O108,P107>=P108,Q107>=Q108),AND(N107>=N109,O107>=O109,P107>=P109,Q107>=Q109)) -> FALSE | N107: =IF(B107=$K$4,1,IF(B107=$L$4,3,2)) -> 2 | O107: =IF(C107=$K$5,1,IF(C107=$L$5,3,2)) -> 2 | P107: =IF(D107=$K$6,1,IF(D107=$L$6,3,2)) -> 1 | Q107: =IF(E107=$K$7,1,IF(E107=$L$7,3,2)) -> 1
A108: Option 2 | B108: =INDEX(DOE!$A$4:$E$84,$G108,COLUMN(B:B)) -> 100 | C108: =INDEX(DOE!$A$4:$E$84,$G108,COLUMN(C:C)) -> 0.25 | D108: =INDEX(DOE!$A$4:$E$84,$G108,COLUMN(D:D)) -> 600 | E108: =INDEX(DOE!$A$4:$E$84,$G108,COLUMN(E:E)) -> 5 | G108: =INDEX(StaticRandomNumbers!$A$4:$BJ$93,A106*3-1,$B$1+1) -> 35 | H108: =F108*G108 -> 0 | M108: =OR(AND(N107<=N108,O107<=O108,P107<=P108,Q107<=Q108),AND(N108>=N109,O108>=O109,P108>=P109,Q108>=Q109)) -> TRUE | N108: =IF(B108=$K$4,1,IF(B108=$L$4,3,2)) -> 2 | O108: =IF(C108=$K$5,1,IF(C108=$L$5,3,2)) -> 3 | P108: =IF(D108=$K$6,1,IF(D108=$L$6,3,2)) -> 3 | Q108: =IF(E108=$K$7,1,IF(E108=$L$7,3,2)) -> 2
A109: Option 3 | B109: =INDEX(DOE!$A$4:$E$84,$G109,COLUMN(B:B)) -> 100 | C109: =INDEX(DOE!$A$4:$E$84,$G109,COLUMN(C:C)) -> 2 | D109: =INDEX(DOE!$A$4:$E$84,$G109,COLUMN(D:D)) -> 120 | E109: =INDEX(DOE!$A$4:$E$84,$G109,COLUMN(E:E)) -> 5 | F109: 1 | G109: =INDEX(StaticRandomNumbers!$A$4:$BJ$93,A106*3,$B$1+1) -> 47 | H109: =F109*G109 -> 47 | M109: =OR(AND(N109>=N108,O109>=O108,P109>=P108,Q109>=Q108),AND(N109>=N107,O109>=O107,P109>=P107,Q109>=Q107)) -> FALSE | N109: =IF(B109=$K$4,1,IF(B109=$L$4,3,2)) -> 2 | O109: =IF(C109=$K$5,1,IF(C109=$L$5,3,2)) -> 1 | P109: =IF(D109=$K$6,1,IF(D109=$L$6,3,2)) -> 1 | Q109: =IF(E109=$K$7,1,IF(E109=$L$7,3,2)) -> 2
A111: Question
A112: =A106+1 -> 18 | B112: =DOE!$B$2 -> price ($) | C112: =DOE!$C$2 -> Fluid Capacity (liters) | D112: =DOE!$D$2 -> Time to boil (sec) | E112: =DOE!$E$2 -> Boils per charge (#) | F112: Choice (mark with "1") | G112: Alt ID | M112: dominated? | N112: =B112 -> price ($) | O112: =C112 -> Fluid Capacity (liters) | P112: =D112 -> Time to boil (sec) | Q112: =E112 -> Boils per charge (#)
A113: Option 1 | B113: =INDEX(DOE!$A$4:$E$84,$G113,COLUMN(B:B)) -> 100 | C113: =INDEX(DOE!$A$4:$E$84,$G113,COLUMN(C:C)) -> 1 | D113: =INDEX(DOE!$A$4:$E$84,$G113,COLUMN(D:D)) -> 240 | E113: =INDEX(DOE!$A$4:$E$84,$G113,COLUMN(E:E)) -> 1 | F113: 1 | G113: =INDEX(StaticRandomNumbers!$A$4:$BJ$93,A112*3-2,$B$1+1) -> 40 | H113: =F113*G113 -> 40 | J113: =IF(AND(COUNTIF(F113:F115,"")=2,COUNTIF(F113:F115,1)=1),1,0) -> 1 | M113: =OR(AND(N113>=N114,O113>=O114,P113>=P114,Q113>=Q114),AND(N113>=N115,O113>=O115,P113>=P115,Q113>=Q115)) -> FALSE | N113: =IF(B113=$K$4,1,IF(B113=$L$4,3,2)) -> 2 | O113: =IF(C113=$K$5,1,IF(C113=$L$5,3,2)) -> 2 | P113: =IF(D113=$K$6,1,IF(D113=$L$6,3,2)) -> 2 | Q113: =IF(E113=$K$7,1,IF(E113=$L$7,3,2)) -> 3
A114: Option 2 | B114: =INDEX(DOE!$A$4:$E$84,$G114,COLUMN(B:B)) -> 100 | C114: =INDEX(DOE!$A$4:$E$84,$G114,COLUMN(C:C)) -> 0.25 | D114: =INDEX(DOE!$A$4:$E$84,$G114,COLUMN(D:D)) -> 240 | E114: =INDEX(DOE!$A$4:$E$84,$G114,COLUMN(E:E)) -> 10 | G114: =INDEX(StaticRandomNumbers!$A$4:$BJ$93,A112*3-1,$B$1+1) -> 33 | H114: =F114*G114 -> 0 | M114: =OR(AND(N113<=N114,O113<=O114,P113<=P114,Q113<=Q114),AND(N114>=N115,O114>=O115,P114>=P115,Q114>=Q115)) -> FALSE | N114: =IF(B114=$K$4,1,IF(B114=$L$4,3,2)) -> 2 | O114: =IF(C114=$K$5,1,IF(C114=$L$5,3,2)) -> 3 | P114: =IF(D114=$K$6,1,IF(D114=$L$6,3,2)) -> 2 | Q114: =IF(E114=$K$7,1,IF(E114=$L$7,3,2)) -> 1
A115: Option 3 | B115: =INDEX(DOE!$A$4:$E$84,$G115,COLUMN(B:B)) -> 200 | C115: =INDEX(DOE!$A$4:$E$84,$G115,COLUMN(C:C)) -> 0.25 | D115: =INDEX(DOE!$A$4:$E$84,$G115,COLUMN(D:D)) -> 120 | E115: =INDEX(DOE!$A$4:$E$84,$G115,COLUMN(E:E)) -> 1 | G115: =INDEX(StaticRandomNumbers!$A$4:$BJ$93,A112*3,$B$1+1) -> 55 | H115: =F115*G115 -> 0 | M115: =OR(AND(N115>=N114,O115>=O114,P115>=P114,Q115>=Q114),AND(N115>=N113,O115>=O113,P115>=P113,Q115>=Q113)) -> FALSE | N115: =IF(B115=$K$4,1,IF(B115=$L$4,3,2)) -> 3 | O115: =IF(C115=$K$5,1,IF(C115=$L$5,3,2)) -> 3 | P115: =IF(D115=$K$6,1,IF(D115=$L$6,3,2)) -> 1 | Q115: =IF(E115=$K$7,1,IF(E115=$L$7,3,2)) -> 3
A117: Question
A118: =A112+1 -> 19 | B118: =DOE!$B$2 -> price ($) | C118: =DOE!$C$2 -> Fluid Capacity (liters) | D118: =DOE!$D$2 -> Time to boil (sec) | E118: =DOE!$E$2 -> Boils per charge (#) | F118: Choice (mark with "1") | G118: Alt ID | M118: dominated? | N118: =B118 -> price ($) | O118: =C118 -> Fluid Capacity (liters) | P118: =D118 -> Time to boil (sec) | Q118: =E118 -> Boils per charge (#)
A119: Option 1 | B119: =INDEX(DOE!$A$4:$E$84,$G119,COLUMN(B:B)) -> 50 | C119: =INDEX(DOE!$A$4:$E$84,$G119,COLUMN(C:C)) -> 1 | D119: =INDEX(DOE!$A$4:$E$84,$G119,COLUMN(D:D)) -> 120 | E119: =INDEX(DOE!$A$4:$E$84,$G119,COLUMN(E:E)) -> 1 | F119: 1 | G119: =INDEX(StaticRandomNumbers!$A$4:$BJ$93,A118*3-2,$B$1+1) -> 10 | H119: =F119*G119 -> 10 | J119: =IF(AND(COUNTIF(F119:F121,"")=2,COUNTIF(F119:F121,1)=1),1,0) -> 1 | M119: =OR(AND(N119>=N120,O119>=O120,P119>=P120,Q119>=Q120),AND(N119>=N121,O119>=O121,P119>=P121,Q119>=Q121)) -> FALSE | N119: =IF(B119=$K$4,1,IF(B119=$L$4,3,2)) -> 1 | O119: =IF(C119=$K$5,1,IF(C119=$L$5,3,2)) -> 2 | P119: =IF(D119=$K$6,1,IF(D119=$L$6,3,2)) -> 1 | Q119: =IF(E119=$K$7,1,IF(E119=$L$7,3,2)) -> 3
A120: Option 2 | B120: =INDEX(DOE!$A$4:$E$84,$G120,COLUMN(B:B)) -> 200 | C120: =INDEX(DOE!$A$4:$E$84,$G120,COLUMN(C:C)) -> 1 | D120: =INDEX(DOE!$A$4:$E$84,$G120,COLUMN(D:D)) -> 600 | E120: =INDEX(DOE!$A$4:$E$84,$G120,COLUMN(E:E)) -> 1 | G120: =INDEX(StaticRandomNumbers!$A$4:$BJ$93,A118*3-1,$B$1+1) -> 70 | H120: =F120*G120 -> 0 | M120: =OR(AND(N119<=N120,O119<=O120,P119<=P120,Q119<=Q120),AND(N120>=N121,O120>=O121,P120>=P121,Q120>=Q121)) -> TRUE | N120: =IF(B120=$K$4,1,IF(B120=$L$4,3,2)) -> 3 | O120: =IF(C120=$K$5,1,IF(C120=$L$5,3,2)) -> 2 | P120: =IF(D120=$K$6,1,IF(D120=$L$6,3,2)) -> 3 | Q120: =IF(E120=$K$7,1,IF(E120=$L$7,3,2)) -> 3
...

Sheet SurveyResultAggregation
A1: This Survey | B1: Result Aggregation
A2: ="ID = "&Survey!B1 -> ID = 9 | B2: Alt ID | C2: TOTAL | D2: Survey 1 | E2: Survey 2 | F2: Survey 3 | G2: Survey 4 | H2: Survey 5 | I2: Survey 6 | J2: Survey 7 | K2: Survey 8 | L2: Survey 9 | M2: Survey 10 | N2: Survey 11 | O2: Survey 12 | P2: Survey 13 | Q2: Survey 14 | R2: Survey 15 | S2: Survey 16 | T2: Survey 17 | U2: Survey 18 | V2: Survey 19 | W2: Survey 20 | X2: Survey 21 | Y2: Survey 22 | Z2: Survey 23 | AA2: Survey 24 | AB2: Survey 25 | AC2: Survey 26 | AD2: Survey 27 | AE2: Survey 28 | AF2: Survey 29 | AG2: Survey 30 | AH2: Survey 31 | AI2: Survey 32 | AJ2: Survey 33 | AK2: Survey 34 | AL2: Survey 35 | AM2: Survey 36 | AN2: Survey 37 | AO2: Survey 38 | AP2: Survey 39 | AQ2: Survey 40 | AR2: Survey 41 | AS2: Survey 42 | AT2: Survey 43 | AU2: Survey 44 | AV2: Survey 45 | AW2: Survey 46 | AX2: Survey 47 | AY2: Survey 48 | AZ2: Survey 49 | BA2: Survey 50 | BB2: Survey 51 | BC2: Survey 52 | BD2: Survey 53 | BE2: Survey 54 | BF2: Survey 55 | BG2: Survey 56 | BH2: Survey 57 | BI2: Survey 58 | BJ2: Survey 59 | BK2: Survey 60
A3: =COUNTIF(Survey!H:H,DOE!$A4) -> 0 | B3: 1 | C3: =SUM(SurveyResultAggregation!$D3:$BK3) -> 1 | K3: 0 | L3: 0 | O3: 0 | Q3: 0 | AC3: 0 | AW3: 1
A4: =COUNTIF(Survey!H:H,DOE!$A5) -> 0 | B4: 2 | C4: =SUM(SurveyResultAggregation!$D4:$BK4) -> 1 | K4: 0 | L4: 0 | O4: 0 | Q4: 0 | AC4: 0 | AW4: 1
A5: =COUNTIF(Survey!H:H,DOE!$A6) -> 0 | B5: 3 | C5: =SUM(SurveyResultAggregation!$D5:$BK5) -> 0 | K5: 0 | L5: 0 | O5: 0 | Q5: 0 | AC5: 0 | AW5: 0
A6: =COUNTIF(Survey!H:H,DOE!$A7) -> 0 | B6: 4 | C6: =SUM(SurveyResultAggregation!$D6:$BK6) -> 2 | K6: 0 | L6: 0 | O6: 0 | Q6: 1 | AC6: 0 | AW6: 1
A7: =COUNTIF(Survey!H:H,DOE!$A8) -> 0 | B7: 5 | C7: =SUM(SurveyResultAggregation!$D7:$BK7) -> 1 | K7: 0 | L7: 0 | O7: 0 | Q7: 0 | AC7: 0 | AW7: 1
A8: =COUNTIF(Survey!H:H,DOE!$A9) -> 0 | B8: 6 | C8: =SUM(SurveyResultAggregation!$D8:$BK8) -> 2 | K8: 0 | L8: 0 | O8: 0 | Q8: 1 | AC8: 0 | AW8: 1
A9: =COUNTIF(Survey!H:H,DOE!$A10) -> 0 | B9: 7 | C9: =SUM(SurveyResultAggregation!$D9:$BK9) -> 0 | K9: 0 | L9: 0 | O9: 0 | Q9: 0 | AC9: 0 | AW9: 0
A10: =COUNTIF(Survey!H:H,DOE!$A11) -> 0 | B10: 8 | C10: =SUM(SurveyResultAggregation!$D10:$BK10) -> 0 | K10: 0 | L10: 0 | O10: 0 | Q10: 0 | AC10: 0 | AW10: 0
A11: =COUNTIF(Survey!H:H,DOE!$A12) -> 0 | B11: 9 | C11: =SUM(SurveyResultAggregation!$D11:$BK11) -> 0 | K11: 0 | L11: 0 | O11: 0 | Q11: 0 | AC11: 0 | AW11: 0
A12: =COUNTIF(Survey!H:H,DOE!$A13) -> 2 | B12: 10 | C12: =SUM(SurveyResultAggregation!$D12:$BK12) -> 4 | K12: 0 | L12: 2 | O12: 0 | Q12: 1 | AC12: 0 | AW12: 1
A13: =COUNTIF(Survey!H:H,DOE!$A14) -> 2 | B13: 11 | C13: =SUM(SurveyResultAggregation!$D13:$BK13) -> 5 | K13: 1 | L13: 2 | O13: 1 | Q13: 0 | AC13: 1 | AW13: 0
A14: =COUNTIF(Survey!H:H,DOE!$A15) -> 0 | B14: 12 | C14: =SUM(SurveyResultAggregation!$D14:$BK14) -> 2 | K14: 0 | L14: 0 | O14: 0 | Q14: 0 | AC14: 2 | AW14: 0
... A83: =COUNTIF(Survey!H:H,DOE!$A84) -> 0 | B83: 81 | C83: =SUM(SurveyResultAggregation!$D83:$BK83) -> 0 | K83: 0 | L83: 0 | O83: 0 | Q83: 0 | AC83: 0 | AW83: 0

Sheet SurveySetup
A1: Setup Your Survey
A2: Attribute Name | B2: Units | C2: Low | D2: Medium | E2: High
A3: price | B3: $ | C3: 50 | D3: 100 | E3: 200
A4: Fluid Capacity | B4: liters | C4: 0.25 | D4: 1 | E4: 2
A5: Time to boil | B5: sec | C5: 120 | D5: 240 | E5: 600
A6: Boils per charge | B6: # | C6: 1 | D6: 5 | E6: 10

Sheet ResultsInterpretation
A1: Demand Model Results
A2: Attribute Name | B2: Units | C2: bi | D2: si | E2: si [%]
A3: =SurveySetup!A3 -> price | B3: =SurveySetup!B3 -> $ | C3: =MaxLikelihoodSolver!K12 -> -0.0090891018 | D3: =MaxLikelihoodSolver!M12 -> 0.0018304608 | E3: =D3/ABS(C3) -> 0.20139072
A4: =SurveySetup!A4 -> Fluid Capacity | B4: =SurveySetup!B4 -> liters | C4: =MaxLikelihoodSolver!K13 -> 0.71797282 | D4: =MaxLikelihoodSolver!M13 -> 0.13463082 | E4: =D4/ABS(C4) -> 0.18751521
A5: =SurveySetup!A5 -> Time to boil | B5: =SurveySetup!B5 -> sec | C5: =MaxLikelihoodSolver!K14 -> -0.001463119 | D5: =MaxLikelihoodSolver!M14 -> 0.00050345617 | E5: =D5/ABS(C5) -> 0.3440979
A6: =SurveySetup!A6 -> Boils per charge | B6: =SurveySetup!B6 -> # | C6: =MaxLikelihoodSolver!K15 -> 0.080732285 | D6: =MaxLikelihoodSolver!M15 -> 0.025109421 | E6: =D6/ABS(C6) -> 0.31102081
A9: Plots of Relative Utility (with 95% confidence bounds)
A34: Data for Relative Utility Plots
A35: Attribute | B35: min | C35: max | D35: normalized rel util @ min | E35: normalized rel util @ max | F35: 95% low unc bound @ min | G35: 95% low unc bound @ max | H35: 95% up unc bound @ min | I35: 95% up unc bound @ max
A36: p | B36: =MIN(SurveySetup!C3:E3) -> 50 | C36: =MAX(SurveySetup!C3:E3) -> 200 | D36: 0 | E36: =(C36-B36)*C3 -> -1.3633653 | F36: 0 | G36: =(C36-B36)*(C3-2*D3) -> -1.9125035 | H36: 0 | I36: =(C36-B36)*(C3+2*D3) -> -0.81422703
A37: x1 | B37: =MIN(SurveySetup!C4:E4) -> 0.25 | C37: =MAX(SurveySetup!C4:E4) -> 2 | D37: 0 | E37: =(C37-B37)*C4 -> 1.2564524 | F37: 0 | G37: =(C37-B37)*(C4-2*D4) -> 0.78524455 | H37: 0 | I37: =(C37-B37)*(C4+2*D4) -> 1.7276603
A38: x2 | B38: =MIN(SurveySetup!C5:E5) -> 120 | C38: =MAX(SurveySetup!C5:E5) -> 600 | D38: 0 | E38: =(C38-B38)*C5 -> -0.70229711 | F38: 0 | G38: =(C38-B38)*(C5-2*D5) -> -1.185615 | H38: 0 | I38: =(C38-B38)*(C5+2*D5) -> -0.21897919
A39: x3 | B39: =MIN(SurveySetup!C6:E6) -> 1 | C39: =MAX(SurveySetup!C6:E6) -> 10 | D39: 0 | E39: =(C39-B39)*C6 -> 0.72659057 | F39: 0 | G39: =(C39-B39)*(C6-2*D6) -> 0.27462099 | H39: 0 | I39: =(C39-B39)*(C6+2*D6) -> 1.1785601
A40: Overall min | B40: =MIN(ResultsInterpretation!$G$36:$G$39,ResultsInterpretation!$I$36:$I$39) -> -1.9125035
A41: Overall max | B41: =MAX(ResultsInterpretation!$G$36:$G$39,ResultsInterpretation!$I$36:$I$39) -> 1.7276603

Sheet DemandPredictionModel
A1: The Best-Fit Multinomial Logit Model with Utility Linear in the Attributes
A3: Demand Model Results
A4: Attribute Name | B4: Units | C4: bi | D4: si | E4: si [%]
A5: =SurveySetup!A3 -> price | B5: =SurveySetup!B3 -> $ | C5: =MaxLikelihoodSolver!K12 -> -0.0090891018 | D5: =MaxLikelihoodSolver!M12 -> 0.0018304608 | E5: =D5/ABS(C5) -> 0.20139072
A6: =SurveySetup!A4 -> Fluid Capacity | B6: =SurveySetup!B4 -> liters | C6: =MaxLikelihoodSolver!K13 -> 0.71797282 | D6: =MaxLikelihoodSolver!M13 -> 0.13463082 | E6: =D6/ABS(C6) -> 0.18751521
A7: =SurveySetup!A5 -> Time to boil | B7: =SurveySetup!B5 -> sec | C7: =MaxLikelihoodSolver!K14 -> -0.001463119 | D7: =MaxLikelihoodSolver!M14 -> 0.00050345617 | E7: =D7/ABS(C7) -> 0.3440979
A8: =SurveySetup!A6 -> Boils per charge | B8: =SurveySetup!B6 -> # | C8: =MaxLikelihoodSolver!K15 -> 0.080732285 | D8: =MaxLikelihoodSolver!M15 -> 0.025109421 | E8: =D8/ABS(C8) -> 0.31102081
A10: Specify the Market Situation
A11: Attribute Name | B11: Units | C11: Competitor 1 | D11: Competitor 2 | E11: Competitor 3 | F11: Competitor 4
A12: =SurveySetup!A3 -> price | B12: =SurveySetup!B3 -> $ | C12: 95 | D12: 50 | E12: 135 | F12: 200
A13: =SurveySetup!A4 -> Fluid Capacity | B13: =SurveySetup!B4 -> liters | C13: 1 | D13: 0.25 | E13: 2 | F13: 1
A14: =SurveySetup!A5 -> Time to boil | B14: =SurveySetup!B5 -> sec | C14: 600 | D14: 600 | E14: 200 | F14: 125
A15: =SurveySetup!A6 -> Boils per charge | B15: =SurveySetup!B6 -> # | C15: 1 | D15: 2 | E15: 1 | F15: 10
A17: Total Market Size | B17: customers | C17: 20000
A19: Provide Inputs for the Demand Prediction
A20: Attribute Name | B20: Units | C20: Input from ModelCenter
A21: fixedCost | B21: =SurveySetup!B3 -> $ | C21: 150
A22: marginalCost | B22: =SurveySetup!B3 -> $ | C22: 27
A23: capacity | B23: items | C23: 20000
A24: =SurveySetup!A4 -> Fluid Capacity | B24: =SurveySetup!B4 -> liters | C24: 0.2355
A25: =SurveySetup!A5 -> Time to boil | B25: =SurveySetup!B5 -> sec | C25: 42.669274
A26: =SurveySetup!A6 -> Boils per charge | B26: =SurveySetup!B6 -> # | C26: 9.3588135
A28: Demand Prediction Outputs
A29: Attribute Name | B29: Units | C29: Output to ModelCenter
A30: demand | B30: items | C30: =IF(PredictionSolver!$A$133<=capacity,PredictionSolver!$A$133,capacity) -> 3714.3327
A31: price | B31: =SurveySetup!B3 -> $ | C31: =IF(PredictionSolver!$A$133<=capacity,PredictionSolver!$A$132,PredictionSolver!$A$137) -> 162.11497
A32: revenue | B32: =SurveySetup!B3 -> $ | C32: =price*demand -> 602148.94
A33: profit | B33: =SurveySetup!B3 -> $ | C33: =demand*(price-marginalCost)-fixedCost -> 501711.95

Sheet Utility
A1: Risk Tolerance | B1: =SurveySetup!B3 -> $ | C1: 1e+100
A3: utility | B3: utils | C3: =IF(riskTolerance>profit*100000, profit - profit*profit/riskTolerance/2 + profit*profit*profit/riskTolerance/riskTolerance/6, riskTolerance*(1-EXP(-profit/riskTolerance))) -> 501711.95

Sheet DOE
A1: Full Factorial Design
B2: =CONCATENATE(SurveySetup!A3, " (", SurveySetup!B3, ")") -> price ($) | C2: =CONCATENATE(SurveySetup!A4, " (", SurveySetup!B4, ")") -> Fluid Capacity (liters) | D2: =CONCATENATE(SurveySetup!A5, " (", SurveySetup!B5, ")") -> Time to boil (sec) | E2: =CONCATENATE(SurveySetup!A6, " (", SurveySetup!B6, ")") -> Boils per charge (#)
A3: Alt ID | B3: a1 | C3: a2 | D3: a3 | E3: a4
A4: 1 | B4: =SurveySetup!$C$3 -> 50 | C4: =SurveySetup!$C$4 -> 0.25 | D4: =SurveySetup!$C$5 -> 120 | E4: =SurveySetup!$C$6 -> 1
A5: 2 | B5: =SurveySetup!$C$3 -> 50 | C5: =SurveySetup!$C$4 -> 0.25 | D5: =SurveySetup!$C$5 -> 120 | E5: =SurveySetup!$D$6 -> 5
A6: 3 | B6: =SurveySetup!$C$3 -> 50 | C6: =SurveySetup!$C$4 -> 0.25 | D6: =SurveySetup!$C$5 -> 120 | E6: =SurveySetup!$E$6 -> 10
A7: 4 | B7: =SurveySetup!$C$3 -> 50 | C7: =SurveySetup!$C$4 -> 0.25 | D7: =SurveySetup!$D$5 -> 240 | E7: =SurveySetup!$C$6 -> 1
A8: 5 | B8: =SurveySetup!$C$3 -> 50 | C8: =SurveySetup!$C$4 -> 0.25 | D8: =SurveySetup!$D$5 -> 240 | E8: =SurveySetup!$D$6 -> 5
A9: 6 | B9: =SurveySetup!$C$3 -> 50 | C9: =SurveySetup!$C$4 -> 0.25 | D9: =SurveySetup!$D$5 -> 240 | E9: =SurveySetup!$E$6 -> 10
A10: 7 | B10: =SurveySetup!$C$3 -> 50 | C10: =SurveySetup!$C$4 -> 0.25 | D10: =SurveySetup!$E$5 -> 600 | E10: =SurveySetup!$C$6 -> 1
A11: 8 | B11: =SurveySetup!$C$3 -> 50 | C11: =SurveySetup!$C$4 -> 0.25 | D11: =SurveySetup!$E$5 -> 600 | E11: =SurveySetup!$D$6 -> 5
A12: 9 | B12: =SurveySetup!$C$3 -> 50 | C12: =SurveySetup!$C$4 -> 0.25 | D12: =SurveySetup!$E$5 -> 600 | E12: =SurveySetup!$E$6 -> 10
A13: 10 | B13: =SurveySetup!$C$3 -> 50 | C13: =SurveySetup!$D$4 -> 1 | D13: =SurveySetup!$C$5 -> 120 | E13: =SurveySetup!$C$6 -> 1
A14: 11 | B14: =SurveySetup!$C$3 -> 50 | C14: =SurveySetup!$D$4 -> 1 | D14: =SurveySetup!$C$5 -> 120 | E14: =SurveySetup!$D$6 -> 5
A15: 12 | B15: =SurveySetup!$C$3 -> 50 | C15: =SurveySetup!$D$4 -> 1 | D15: =SurveySetup!$C$5 -> 120 | E15: =SurveySetup!$E$6 -> 10
A16: 13 | B16: =SurveySetup!$C$3 -> 50 | C16: =SurveySetup!$D$4 -> 1 | D16: =SurveySetup!$D$5 -> 240 | E16: =SurveySetup!$C$6 -> 1
A17: 14 | B17: =SurveySetup!$C$3 -> 50 | C17: =SurveySetup!$D$4 -> 1 | D17: =SurveySetup!$D$5 -> 240 | E17: =SurveySetup!$D$6 -> 5
A18: 15 | B18: =SurveySetup!$C$3 -> 50 | C18: =SurveySetup!$D$4 -> 1 | D18: =SurveySetup!$D$5 -> 240 | E18: =SurveySetup!$E$6 -> 10
A19: 16 | B19: =SurveySetup!$C$3 -> 50 | C19: =SurveySetup!$D$4 -> 1 | D19: =SurveySetup!$E$5 -> 600 | E19: =SurveySetup!$C$6 -> 1
A20: 17 | B20: =SurveySetup!$C$3 -> 50 | C20: =SurveySetup!$D$4 -> 1 | D20: =SurveySetup!$E$5 -> 600 | E20: =SurveySetup!$D$6 -> 5
A21: 18 | B21: =SurveySetup!$C$3 -> 50 | C21: =SurveySetup!$D$4 -> 1 | D21: =SurveySetup!$E$5 -> 600 | E21: =SurveySetup!$E$6 -> 10
A22: 19 | B22: =SurveySetup!$C$3 -> 50 | C22: =SurveySetup!$E$4 -> 2 | D22: =SurveySetup!$C$5 -> 120 | E22: =SurveySetup!$C$6 -> 1
A23: 20 | B23: =SurveySetup!$C$3 -> 50 | C23: =SurveySetup!$E$4 -> 2 | D23: =SurveySetup!$C$5 -> 120 | E23: =SurveySetup!$D$6 -> 5
A24: 21 | B24: =SurveySetup!$C$3 -> 50 | C24: =SurveySetup!$E$4 -> 2 | D24: =SurveySetup!$C$5 -> 120 | E24: =SurveySetup!$E$6 -> 10
A25: 22 | B25: =SurveySetup!$C$3 -> 50 | C25: =SurveySetup!$E$4 -> 2 | D25: =SurveySetup!$D$5 -> 240 | E25: =SurveySetup!$C$6 -> 1
A26: 23 | B26: =SurveySetup!$C$3 -> 50 | C26: =SurveySetup!$E$4 -> 2 | D26: =SurveySetup!$D$5 -> 240 | E26: =SurveySetup!$D$6 -> 5
A27: 24 | B27: =SurveySetup!$C$3 -> 50 | C27: =SurveySetup!$E$4 -> 2 | D27: =SurveySetup!$D$5 -> 240 | E27: =SurveySetup!$E$6 -> 10
A28: 25 | B28: =SurveySetup!$C$3 -> 50 | C28: =SurveySetup!$E$4 -> 2 | D28: =SurveySetup!$E$5 -> 600 | E28: =SurveySetup!$C$6 -> 1
A29: 26 | B29: =SurveySetup!$C$3 -> 50 | C29: =SurveySetup!$E$4 -> 2 | D29: =SurveySetup!$E$5 -> 600 | E29: =SurveySetup!$D$6 -> 5
A30: 27 | B30: =SurveySetup!$C$3 -> 50 | C30: =SurveySetup!$E$4 -> 2 | D30: =SurveySetup!$E$5 -> 600 | E30: =SurveySetup!$E$6 -> 10
A31: 28 | B31: =SurveySetup!$D$3 -> 100 | C31: =SurveySetup!$C$4 -> 0.25 | D31: =SurveySetup!$C$5 -> 120 | E31: =SurveySetup!$C$6 -> 1
A32: 29 | B32: =SurveySetup!$D$3 -> 100 | C32: =SurveySetup!$C$4 -> 0.25 | D32: =SurveySetup!$C$5 -> 120 | E32: =SurveySetup!$D$6 -> 5
A33: 30 | B33: =SurveySetup!$D$3 -> 100 | C33: =SurveySetup!$C$4 -> 0.25 | D33: =SurveySetup!$C$5 -> 120 | E33: =SurveySetup!$E$6 -> 10
A34: 31 | B34: =SurveySetup!$D$3 -> 100 | C34: =SurveySetup!$C$4 -> 0.25 | D34: =SurveySetup!$D$5 -> 240 | E34: =SurveySetup!$C$6 -> 1
A35: 32 | B35: =SurveySetup!$D$3 -> 100 | C35: =SurveySetup!$C$4 -> 0.25 | D35: =SurveySetup!$D$5 -> 240 | E35: =SurveySetup!$D$6 -> 5
A36: 33 | B36: =SurveySetup!$D$3 -> 100 | C36: =SurveySetup!$C$4 -> 0.25 | D36: =SurveySetup!$D$5 -> 240 | E36: =SurveySetup!$E$6 -> 10
A37: 34 | B37: =SurveySetup!$D$3 -> 100 | C37: =SurveySetup!$C$4 -> 0.25 | D37: =SurveySetup!$E$5 -> 600 | E37: =SurveySetup!$C$6 -> 1
A38: 35 | B38: =SurveySetup!$D$3 -> 100 | C38: =SurveySetup!$C$4 -> 0.25 | D38: =SurveySetup!$E$5 -> 600 | E38: =SurveySetup!$D$6 -> 5
A39: 36 | B39: =SurveySetup!$D$3 -> 100 | C39: =SurveySetup!$C$4 -> 0.25 | D39: =SurveySetup!$E$5 -> 600 | E39: =SurveySetup!$E$6 -> 10
A40: 37 | B40: =SurveySetup!$D$3 -> 100 | C40: =SurveySetup!$D$4 -> 1 | D40: =SurveySetup!$C$5 -> 120 | E40: =SurveySetup!$C$6 -> 1
A41: 38 | B41: =SurveySetup!$D$3 -> 100 | C41: =SurveySetup!$D$4 -> 1 | D41: =SurveySetup!$C$5 -> 120 | E41: =SurveySetup!$D$6 -> 5
A42: 39 | B42: =SurveySetup!$D$3 -> 100 | C42: =SurveySetup!$D$4 -> 1 | D42: =SurveySetup!$C$5 -> 120 | E42: =SurveySetup!$E$6 -> 10
A43: 40 | B43: =SurveySetup!$D$3 -> 100 | C43: =SurveySetup!$D$4 -> 1 | D43: =SurveySetup!$D$5 -> 240 | E43: =SurveySetup!$C$6 -> 1
A44: 41 | B44: =SurveySetup!$D$3 -> 100 | C44: =SurveySetup!$D$4 -> 1 | D44: =SurveySetup!$D$5 -> 240 | E44: =SurveySetup!$D$6 -> 5
A45: 42 | B45: =SurveySetup!$D$3 -> 100 | C45: =SurveySetup!$D$4 -> 1 | D45: =SurveySetup!$D$5 -> 240 | E45: =SurveySetup!$E$6 -> 10
A46: 43 | B46: =SurveySetup!$D$3 -> 100 | C46: =SurveySetup!$D$4 -> 1 | D46: =SurveySetup!$E$5 -> 600 | E46: =SurveySetup!$C$6 -> 1
A47: 44 | B47: =SurveySetup!$D$3 -> 100 | C47: =SurveySetup!$D$4 -> 1 | D47: =SurveySetup!$E$5 -> 600 | E47: =SurveySetup!$D$6 -> 5
A48: 45 | B48: =SurveySetup!$D$3 -> 100 | C48: =SurveySetup!$D$4 -> 1 | D48: =SurveySetup!$E$5 -> 600 | E48: =SurveySetup!$E$6 -> 10
A49: 46 | B49: =SurveySetup!$D$3 -> 100 | C49: =SurveySetup!$E$4 -> 2 | D49: =SurveySetup!$C$5 -> 120 | E49: =SurveySetup!$C$6 -> 1
A50: 47 | B50: =SurveySetup!$D$3 -> 100 | C50: =SurveySetup!$E$4 -> 2 | D50: =SurveySetup!$C$5 -> 120 | E50: =SurveySetup!$D$6 -> 5
A51: 48 | B51: =SurveySetup!$D$3 -> 100 | C51: =SurveySetup!$E$4 -> 2 | D51: =SurveySetup!$C$5 -> 120 | E51: =SurveySetup!$E$6 -> 10
A52: 49 | B52: =SurveySetup!$D$3 -> 100 | C52: =SurveySetup!$E$4 -> 2 | D52: =SurveySetup!$D$5 -> 240 | E52: =SurveySetup!$C$6 -> 1
A53: 50 | B53: =SurveySetup!$D$3 -> 100 | C53: =SurveySetup!$E$4 -> 2 | D53: =SurveySetup!$D$5 -> 240 | E53: =SurveySetup!$D$6 -> 5
A54: 51 | B54: =SurveySetup!$D$3 -> 100 | C54: =SurveySetup!$E$4 -> 2 | D54: =SurveySetup!$D$5 -> 240 | E54: =SurveySetup!$E$6 -> 10
A55: 52 | B55: =SurveySetup!$D$3 -> 100 | C55: =SurveySetup!$E$4 -> 2 | D55: =SurveySetup!$E$5 -> 600 | E55: =SurveySetup!$C$6 -> 1
A56: 53 | B56: =SurveySetup!$D$3 -> 100 | C56: =SurveySetup!$E$4 -> 2 | D56: =SurveySetup!$E$5 -> 600 | E56: =SurveySetup!$D$6 -> 5
A57: 54 | B57: =SurveySetup!$D$3 -> 100 | C57: =SurveySetup!$E$4 -> 2 | D57: =SurveySetup!$E$5 -> 600 | E57: =SurveySetup!$E$6 -> 10
A58: 55 | B58: =SurveySetup!$E$3 -> 200 | C58: =SurveySetup!$C$4 -> 0.25 | D58: =SurveySetup!$C$5 -> 120 | E58: =SurveySetup!$C$6 -> 1
A59: 56 | B59: =SurveySetup!$E$3 -> 200 | C59: =SurveySetup!$C$4 -> 0.25 | D59: =SurveySetup!$C$5 -> 120 | E59: =SurveySetup!$D$6 -> 5
A60: 57 | B60: =SurveySetup!$E$3 -> 200 | C60: =SurveySetup!$C$4 -> 0.25 | D60: =SurveySetup!$C$5 -> 120 | E60: =SurveySetup!$E$6 -> 10
A61: 58 | B61: =SurveySetup!$E$3 -> 200 | C61: =SurveySetup!$C$4 -> 0.25 | D61: =SurveySetup!$D$5 -> 240 | E61: =SurveySetup!$C$6 -> 1
A62: 59 | B62: =SurveySetup!$E$3 -> 200 | C62: =SurveySetup!$C$4 -> 0.25 | D62: =SurveySetup!$D$5 -> 240 | E62: =SurveySetup!$D$6 -> 5
A63: 60 | B63: =SurveySetup!$E$3 -> 200 | C63: =SurveySetup!$C$4 -> 0.25 | D63: =SurveySetup!$D$5 -> 240 | E63: =SurveySetup!$E$6 -> 10
A64: 61 | B64: =SurveySetup!$E$3 -> 200 | C64: =SurveySetup!$C$4 -> 0.25 | D64: =SurveySetup!$E$5 -> 600 | E64: =SurveySetup!$C$6 -> 1
A65: 62 | B65: =SurveySetup!$E$3 -> 200 | C65: =SurveySetup!$C$4 -> 0.25 | D65: =SurveySetup!$E$5 -> 600 | E65: =SurveySetup!$D$6 -> 5
A66: 63 | B66: =SurveySetup!$E$3 -> 200 | C66: =SurveySetup!$C$4 -> 0.25 | D66: =SurveySetup!$E$5 -> 600 | E66: =SurveySetup!$E$6 -> 10
A67: 64 | B67: =SurveySetup!$E$3 -> 200 | C67: =SurveySetup!$D$4 -> 1 | D67: =SurveySetup!$C$5 -> 120 | E67: =SurveySetup!$C$6 -> 1
A68: 65 | B68: =SurveySetup!$E$3 -> 200 | C68: =SurveySetup!$D$4 -> 1 | D68: =SurveySetup!$C$5 -> 120 | E68: =SurveySetup!$D$6 -> 5
A69: 66 | B69: =SurveySetup!$E$3 -> 200 | C69: =SurveySetup!$D$4 -> 1 | D69: =SurveySetup!$C$5 -> 120 | E69: =SurveySetup!$E$6 -> 10
A70: 67 | B70: =SurveySetup!$E$3 -> 200 | C70: =SurveySetup!$D$4 -> 1 | D70: =SurveySetup!$D$5 -> 240 | E70: =SurveySetup!$C$6 -> 1
A71: 68 | B71: =SurveySetup!$E$3 -> 200 | C71: =SurveySetup!$D$4 -> 1 | D71: =SurveySetup!$D$5 -> 240 | E71: =SurveySetup!$D$6 -> 5
A72: 69 | B72: =SurveySetup!$E$3 -> 200 | C72: =SurveySetup!$D$4 -> 1 | D72: =SurveySetup!$D$5 -> 240 | E72: =SurveySetup!$E$6 -> 10
A73: 70 | B73: =SurveySetup!$E$3 -> 200 | C73: =SurveySetup!$D$4 -> 1 | D73: =SurveySetup!$E$5 -> 600 | E73: =SurveySetup!$C$6 -> 1
A74: 71 | B74: =SurveySetup!$E$3 -> 200 | C74: =SurveySetup!$D$4 -> 1 | D74: =SurveySetup!$E$5 -> 600 | E74: =SurveySetup!$D$6 -> 5
A75: 72 | B75: =SurveySetup!$E$3 -> 200 | C75: =SurveySetup!$D$4 -> 1 | D75: =SurveySetup!$E$5 -> 600 | E75: =SurveySetup!$E$6 -> 10
A76: 73 | B76: =SurveySetup!$E$3 -> 200 | C76: =SurveySetup!$E$4 -> 2 | D76: =SurveySetup!$C$5 -> 120 | E76: =SurveySetup!$C$6 -> 1
A77: 74 | B77: =SurveySetup!$E$3 -> 200 | C77: =SurveySetup!$E$4 -> 2 | D77: =SurveySetup!$C$5 -> 120 | E77: =SurveySetup!$D$6 -> 5
A78: 75 | B78: =SurveySetup!$E$3 -> 200 | C78: =SurveySetup!$E$4 -> 2 | D78: =SurveySetup!$C$5 -> 120 | E78: =SurveySetup!$E$6 -> 10
A79: 76 | B79: =SurveySetup!$E$3 -> 200 | C79: =SurveySetup!$E$4 -> 2 | D79: =SurveySetup!$D$5 -> 240 | E79: =SurveySetup!$C$6 -> 1
A80: 77 | B80: =SurveySetup!$E$3 -> 200 | C80: =SurveySetup!$E$4 -> 2 | D80: =SurveySetup!$D$5 -> 240 | E80: =SurveySetup!$D$6 -> 5
A81: 78 | B81: =SurveySetup!$E$3 -> 200 | C81: =SurveySetup!$E$4 -> 2 | D81: =SurveySetup!$D$5 -> 240 | E81: =SurveySetup!$E$6 -> 10
A82: 79 | B82: =SurveySetup!$E$3 -> 200 | C82: =SurveySetup!$E$4 -> 2 | D82: =SurveySetup!$E$5 -> 600 | E82: =SurveySetup!$C$6 -> 1
A83: 80 | B83: =SurveySetup!$E$3 -> 200 | C83: =SurveySetup!$E$4 -> 2 | D83: =SurveySetup!$E$5 -> 600 | E83: =SurveySetup!$D$6 -> 5
A84: 81 | B84: =SurveySetup!$E$3 -> 200 | C84: =SurveySetup!$E$4 -> 2 | D84: =SurveySetup!$E$5 -> 600 | E84: =SurveySetup!$E$6 -> 10
A86: Transpose Version
A87: =SurveySetup!$C$3 -> 50 | B87: =SurveySetup!$C$3 -> 50 | C87: =SurveySetup!$C$3 -> 50 | D87: =SurveySetup!$C$3 -> 50 | E87: =SurveySetup!$C$3 -> 50 | F87: =SurveySetup!$C$3 -> 50 | G87: =SurveySetup!$C$3 -> 50 | H87: =SurveySetup!$C$3 -> 50 | ... AA87: =SurveySetup!$C$3 -> 50 | AB87: =SurveySetup!$D$3 -> 100 | AC87: =SurveySetup!$D$3 -> 100 | AD87: =SurveySetup!$D$3 -> 100 | AE87: =SurveySetup!$D$3 -> 100 | AF87: =SurveySetup!$D$3 -> 100 | AG87: =SurveySetup!$D$3 -> 100 | AH87: =SurveySetup!$D$3 -> 100 | AI87: =SurveySetup!$D$3 -> 100 | ... BB87: =SurveySetup!$D$3 -> 100 | BC87: =SurveySetup!$E$3 -> 200 | BD87: =SurveySetup!$E$3 -> 200 | BE87: =SurveySetup!$E$3 -> 200 | BF87: =SurveySetup!$E$3 -> 200 | BG87: =SurveySetup!$E$3 -> 200 | BH87: =SurveySetup!$E$3 -> 200 | BI87: =SurveySetup!$E$3 -> 200 | BJ87: =SurveySetup!$E$3 -> 200 | ... CC87: =SurveySetup!$E$3 -> 200
A88: =SurveySetup!$C$4 -> 0.25 | B88: =SurveySetup!$C$4 -> 0.25 | C88: =SurveySetup!$C$4 -> 0.25 | D88: =SurveySetup!$C$4 -> 0.25 | E88: =SurveySetup!$C$4 -> 0.25 | F88: =SurveySetup!$C$4 -> 0.25 | G88: =SurveySetup!$C$4 -> 0.25 | H88: =SurveySetup!$C$4 -> 0.25 | I88: =SurveySetup!$C$4 -> 0.25 | J88: =SurveySetup!$D$4 -> 1 | K88: =SurveySetup!$D$4 -> 1 | L88: =SurveySetup!$D$4 -> 1 | M88: =SurveySetup!$D$4 -> 1 | N88: =SurveySetup!$D$4 -> 1 | O88: =SurveySetup!$D$4 -> 1 | P88: =SurveySetup!$D$4 -> 1 | Q88: =SurveySetup!$D$4 -> 1 | R88: =SurveySetup!$D$4 -> 1 | S88: =SurveySetup!$E$4 -> 2 | T88: =SurveySetup!$E$4 -> 2 | U88: =SurveySetup!$E$4 -> 2 | V88: =SurveySetup!$E$4 -> 2 | W88: =SurveySetup!$E$4 -> 2 | X88: =SurveySetup!$E$4 -> 2 | Y88: =SurveySetup!$E$4 -> 2 | Z88: =SurveySetup!$E$4 -> 2 | AA88: =SurveySetup!$E$4 -> 2 | AB88: =SurveySetup!$C$4 -> 0.25 | AC88: =SurveySetup!$C$4 -> 0.25 | AD88: =SurveySetup!$C$4 -> 0.25 | AE88: =SurveySetup!$C$4 -> 0.25 | AF88: =SurveySetup!$C$4 -> 0.25 | AG88: =SurveySetup!$C$4 -> 0.25 | AH88: =SurveySetup!$C$4 -> 0.25 | AI88: =SurveySetup!$C$4 -> 0.25 | AJ88: =SurveySetup!$C$4 -> 0.25 | AK88: =SurveySetup!$D$4 -> 1 | AL88: =SurveySetup!$D$4 -> 1 | AM88: =SurveySetup!$D$4 -> 1 | AN88: =SurveySetup!$D$4 -> 1 | AO88: =SurveySetup!$D$4 -> 1 | AP88: =SurveySetup!$D$4 -> 1 | AQ88: =SurveySetup!$D$4 -> 1 | AR88: =SurveySetup!$D$4 -> 1 | AS88: =SurveySetup!$D$4 -> 1 | AT88: =SurveySetup!$E$4 -> 2 | AU88: =SurveySetup!$E$4 -> 2 | AV88: =SurveySetup!$E$4 -> 2 | AW88: =SurveySetup!$E$4 -> 2 | AX88: =SurveySetup!$E$4 -> 2 | AY88: =SurveySetup!$E$4 -> 2 | AZ88: =SurveySetup!$E$4 -> 2 | BA88: =SurveySetup!$E$4 -> 2 | BB88: =SurveySetup!$E$4 -> 2 | BC88: =SurveySetup!$C$4 -> 0.25 | BD88: =SurveySetup!$C$4 -> 0.25 | BE88: =SurveySetup!$C$4 -> 0.25 | BF88: =SurveySetup!$C$4 -> 0.25 | BG88: =SurveySetup!$C$4 -> 0.25 | BH88: =SurveySetup!$C$4 -> 0.25 | BI88: =SurveySetup!$C$4 -> 0.25 | BJ88: =SurveySetup!$C$4 -> 0.25 | BK88: =SurveySetup!$C$4 -> 0.25 | BL88: =SurveySetup!$D$4 -> 1 | BM88: =SurveySetup!$D$4 -> 1 | BN88: =SurveySetup!$D$4 -> 1 | BO88: =SurveySetup!$D$4 -> 1 | BP88: =SurveySetup!$D$4 -> 1 | BQ88: =SurveySetup!$D$4 -> 1 | BR88: =SurveySetup!$D$4 -> 1 | BS88: =SurveySetup!$D$4 -> 1 | BT88: =SurveySetup!$D$4 -> 1 | BU88: =SurveySetup!$E$4 -> 2 | BV88: =SurveySetup!$E$4 -> 2 | BW88: =SurveySetup!$E$4 -> 2 | BX88: =SurveySetup!$E$4 -> 2 | BY88: =SurveySetup!$E$4 -> 2 | BZ88: =SurveySetup!$E$4 -> 2 | CA88: =SurveySetup!$E$4 -> 2 | CB88: =SurveySetup!$E$4 -> 2 | CC88: =SurveySetup!$E$4 -> 2
A89: =SurveySetup!$C$5 -> 120 | B89: =SurveySetup!$C$5 -> 120 | C89: =SurveySetup!$C$5 -> 120 | D89: =SurveySetup!$D$5 -> 240 | E89: =SurveySetup!$D$5 -> 240 | F89: =SurveySetup!$D$5 -> 240 | G89: =SurveySetup!$E$5 -> 600 | H89: =SurveySetup!$E$5 -> 600 | I89: =SurveySetup!$E$5 -> 600 | J89: =SurveySetup!$C$5 -> 120 | K89: =SurveySetup!$C$5 -> 120 | L89: =SurveySetup!$C$5 -> 120 | M89: =SurveySetup!$D$5 -> 240 | N89: =SurveySetup!$D$5 -> 240 | O89: =SurveySetup!$D$5 -> 240 | P89: =SurveySetup!$E$5 -> 600 | Q89: =SurveySetup!$E$5 -> 600 | R89: =SurveySetup!$E$5 -> 600 | S89: =SurveySetup!$C$5 -> 120 | T89: =SurveySetup!$C$5 -> 120 | U89: =SurveySetup!$C$5 -> 120 | V89: =SurveySetup!$D$5 -> 240 | W89: =SurveySetup!$D$5 -> 240 | X89: =SurveySetup!$D$5 -> 240 | Y89: =SurveySetup!$E$5 -> 600 | Z89: =SurveySetup!$E$5 -> 600 | AA89: =SurveySetup!$E$5 -> 600 | AB89: =SurveySetup!$C$5 -> 120 | AC89: =SurveySetup!$C$5 -> 120 | AD89: =SurveySetup!$C$5 -> 120 | AE89: =SurveySetup!$D$5 -> 240 | AF89: =SurveySetup!$D$5 -> 240 | AG89: =SurveySetup!$D$5 -> 240 | AH89: =SurveySetup!$E$5 -> 600 | AI89: =SurveySetup!$E$5 -> 600 | AJ89: =SurveySetup!$E$5 -> 600 | AK89: =SurveySetup!$C$5 -> 120 | AL89: =SurveySetup!$C$5 -> 120 | AM89: =SurveySetup!$C$5 -> 120 | AN89: =SurveySetup!$D$5 -> 240 | AO89: =SurveySetup!$D$5 -> 240 | AP89: =SurveySetup!$D$5 -> 240 | AQ89: =SurveySetup!$E$5 -> 600 | AR89: =SurveySetup!$E$5 -> 600 | AS89: =SurveySetup!$E$5 -> 600 | AT89: =SurveySetup!$C$5 -> 120 | AU89: =SurveySetup!$C$5 -> 120 | AV89: =SurveySetup!$C$5 -> 120 | AW89: =SurveySetup!$D$5 -> 240 | AX89: =SurveySetup!$D$5 -> 240 | AY89: =SurveySetup!$D$5 -> 240 | AZ89: =SurveySetup!$E$5 -> 600 | BA89: =SurveySetup!$E$5 -> 600 | BB89: =SurveySetup!$E$5 -> 600 | BC89: =SurveySetup!$C$5 -> 120 | BD89: =SurveySetup!$C$5 -> 120 | BE89: =SurveySetup!$C$5 -> 120 | BF89: =SurveySetup!$D$5 -> 240 | BG89: =SurveySetup!$D$5 -> 240 | BH89: =SurveySetup!$D$5 -> 240 | BI89: =SurveySetup!$E$5 -> 600 | BJ89: =SurveySetup!$E$5 -> 600 | BK89: =SurveySetup!$E$5 -> 600 | BL89: =SurveySetup!$C$5 -> 120 | BM89: =SurveySetup!$C$5 -> 120 | BN89: =SurveySetup!$C$5 -> 120 | BO89: =SurveySetup!$D$5 -> 240 | BP89: =SurveySetup!$D$5 -> 240 | BQ89: =SurveySetup!$D$5 -> 240 | BR89: =SurveySetup!$E$5 -> 600 | BS89: =SurveySetup!$E$5 -> 600 | BT89: =SurveySetup!$E$5 -> 600 | BU89: =SurveySetup!$C$5 -> 120 | BV89: =SurveySetup!$C$5 -> 120 | BW89: =SurveySetup!$C$5 -> 120 | BX89: =SurveySetup!$D$5 -> 240 | BY89: =SurveySetup!$D$5 -> 240 | BZ89: =SurveySetup!$D$5 -> 240 | CA89: =SurveySetup!$E$5 -> 600 | CB89: =SurveySetup!$E$5 -> 600 | CC89: =SurveySetup!$E$5 -> 600
A90: =SurveySetup!$C$6 -> 1 | B90: =SurveySetup!$D$6 -> 5 | C90: =SurveySetup!$E$6 -> 10 | D90: =SurveySetup!$C$6 -> 1 | E90: =SurveySetup!$D$6 -> 5 | F90: =SurveySetup!$E$6 -> 10 | G90: =SurveySetup!$C$6 -> 1 | H90: =SurveySetup!$D$6 -> 5 | I90: =SurveySetup!$E$6 -> 10 | J90: =SurveySetup!$C$6 -> 1 | K90: =SurveySetup!$D$6 -> 5 | L90: =SurveySetup!$E$6 -> 10 | M90: =SurveySetup!$C$6 -> 1 | N90: =SurveySetup!$D$6 -> 5 | O90: =SurveySetup!$E$6 -> 10 | P90: =SurveySetup!$C$6 -> 1 | Q90: =SurveySetup!$D$6 -> 5 | R90: =SurveySetup!$E$6 -> 10 | S90: =SurveySetup!$C$6 -> 1 | T90: =SurveySetup!$D$6 -> 5 | U90: =SurveySetup!$E$6 -> 10 | V90: =SurveySetup!$C$6 -> 1 | W90: =SurveySetup!$D$6 -> 5 | X90: =SurveySetup!$E$6 -> 10 | Y90: =SurveySetup!$C$6 -> 1 | Z90: =SurveySetup!$D$6 -> 5 | AA90: =SurveySetup!$E$6 -> 10 | AB90: =SurveySetup!$C$6 -> 1 | AC90: =SurveySetup!$D$6 -> 5 | AD90: =SurveySetup!$E$6 -> 10 | AE90: =SurveySetup!$C$6 -> 1 | AF90: =SurveySetup!$D$6 -> 5 | AG90: =SurveySetup!$E$6 -> 10 | AH90: =SurveySetup!$C$6 -> 1 | AI90: =SurveySetup!$D$6 -> 5 | AJ90: =SurveySetup!$E$6 -> 10 | AK90: =SurveySetup!$C$6 -> 1 | AL90: =SurveySetup!$D$6 -> 5 | AM90: =SurveySetup!$E$6 -> 10 | AN90: =SurveySetup!$C$6 -> 1 | AO90: =SurveySetup!$D$6 -> 5 | AP90: =SurveySetup!$E$6 -> 10 | AQ90: =SurveySetup!$C$6 -> 1 | AR90: =SurveySetup!$D$6 -> 5 | AS90: =SurveySetup!$E$6 -> 10 | AT90: =SurveySetup!$C$6 -> 1 | AU90: =SurveySetup!$D$6 -> 5 | AV90: =SurveySetup!$E$6 -> 10 | AW90: =SurveySetup!$C$6 -> 1 | AX90: =SurveySetup!$D$6 -> 5 | AY90: =SurveySetup!$E$6 -> 10 | AZ90: =SurveySetup!$C$6 -> 1 | BA90: =SurveySetup!$D$6 -> 5 | BB90: =SurveySetup!$E$6 -> 10 | BC90: =SurveySetup!$C$6 -> 1 | BD90: =SurveySetup!$D$6 -> 5 | BE90: =SurveySetup!$E$6 -> 10 | BF90: =SurveySetup!$C$6 -> 1 | BG90: =SurveySetup!$D$6 -> 5 | BH90: =SurveySetup!$E$6 -> 10 | BI90: =SurveySetup!$C$6 -> 1 | BJ90: =SurveySetup!$D$6 -> 5 | BK90: =SurveySetup!$E$6 -> 10 | BL90: =SurveySetup!$C$6 -> 1 | BM90: =SurveySetup!$D$6 -> 5 | BN90: =SurveySetup!$E$6 -> 10 | BO90: =SurveySetup!$C$6 -> 1 | BP90: =SurveySetup!$D$6 -> 5 | BQ90: =SurveySetup!$E$6 -> 10 | BR90: =SurveySetup!$C$6 -> 1 | BS90: =SurveySetup!$D$6 -> 5 | BT90: =SurveySetup!$E$6 -> 10 | BU90: =SurveySetup!$C$6 -> 1 | BV90: =SurveySetup!$D$6 -> 5 | BW90: =SurveySetup!$E$6 -> 10 | BX90: =SurveySetup!$C$6 -> 1 | BY90: =SurveySetup!$D$6 -> 5 | BZ90: =SurveySetup!$E$6 -> 10 | CA90: =SurveySetup!$C$6 -> 1 | CB90: =SurveySetup!$D$6 -> 5 | CC90: =SurveySetup!$E$6 -> 10

Sheet MaxLikelihoodSolver
A1: Normalized Inputs -- The survey results
A2: index | B2: 1 | C2: 2 | D2: 3 | E2: 4 | F2: 5 | G2: 6 | H2: 7 | I2: 8 | J2: 9 | K2: 10 | L2: 11 | M2: 12 | N2: 13 | O2: 14 | P2: 15 | Q2: 16 | R2: 17 | S2: 18 | T2: 19 | U2: 20 | V2: 21 | W2: 22 | X2: 23 | Y2: 24 | Z2: 25 | AA2: 26 | AB2: 27 | AC2: 28 | AD2: 29 | AE2: 30 | AF2: 31 | AG2: 32 | AH2: 33 | AI2: 34 | AJ2: 35 | AK2: 36 | AL2: 37 | AM2: 38 | AN2: 39 | AO2: 40 | AP2: 41 | AQ2: 42 | AR2: 43 | AS2: 44 | AT2: 45 | AU2: 46 | AV2: 47 | AW2: 48 | AX2: 49 | AY2: 50 | AZ2: 51 | BA2: 52 | BB2: 53 | BC2: 54 | BD2: 55 | BE2: 56 | BF2: 57 | BG2: 58 | BH2: 59 | BI2: 60 | BJ2: 61 | BK2: 62 | BL2: 63 | BM2: 64 | BN2: 65 | BO2: 66 | BP2: 67 | BQ2: 68 | BR2: 69 | BS2: 70 | BT2: 71 | BU2: 72 | BV2: 73 | BW2: 74 | BX2: 75 | BY2: 76 | BZ2: 77 | CA2: 78 | CB2: 79 | CC2: 80 | CD2: 81 | CE2: Totals | CH2: Max | CI2: Min | CJ2: Scaling | CK2: Offset
A3: pj | B3: =(DOE!A87-$CK3)/$CJ3 -> -1 | C3: =(DOE!B87-$CK3)/$CJ3 -> -1 | D3: =(DOE!C87-$CK3)/$CJ3 -> -1 | E3: =(DOE!D87-$CK3)/$CJ3 -> -1 | F3: =(DOE!E87-$CK3)/$CJ3 -> -1 | G3: =(DOE!F87-$CK3)/$CJ3 -> -1 | H3: =(DOE!G87-$CK3)/$CJ3 -> -1 | I3: =(DOE!H87-$CK3)/$CJ3 -> -1 | ... CD3: =(DOE!CC87-$CK3)/$CJ3 -> 1 | CE3: =SUMPRODUCT(MaxLikelihoodSolver!$B3:$CD3,$B$7:$CD$7) -> -60.666667 | CF3: SumProduct with n_j | CH3: =MAX(SurveySetup!C3:E3) -> 200 | CI3: =MIN(SurveySetup!C3:E3) -> 50 | CJ3: =(CH3-CI3)/2 -> 75 | CK3: =CJ3+CI3 -> 125
A4: x1j | B4: =(DOE!A88-$CK4)/$CJ4 -> -1 | C4: =(DOE!B88-$CK4)/$CJ4 -> -1 | D4: =(DOE!C88-$CK4)/$CJ4 -> -1 | E4: =(DOE!D88-$CK4)/$CJ4 -> -1 | F4: =(DOE!E88-$CK4)/$CJ4 -> -1 | G4: =(DOE!F88-$CK4)/$CJ4 -> -1 | H4: =(DOE!G88-$CK4)/$CJ4 -> -1 | I4: =(DOE!H88-$CK4)/$CJ4 -> -1 | ... CD4: =(DOE!CC88-$CK4)/$CJ4 -> 1 | CE4: =SUMPRODUCT(MaxLikelihoodSolver!$B4:$CD4,$B$7:$CD$7) -> 43.714286 | CF4: SumProduct with n_j | CH4: =MAX(SurveySetup!C4:E4) -> 2 | CI4: =MIN(SurveySetup!C4:E4) -> 0.25 | CJ4: =(CH4-CI4)/2 -> 0.875 | CK4: =CJ4+CI4 -> 1.125
A5: x2j | B5: =(DOE!A89-$CK5)/$CJ5 -> -1 | C5: =(DOE!B89-$CK5)/$CJ5 -> -1 | D5: =(DOE!C89-$CK5)/$CJ5 -> -1 | E5: =(DOE!D89-$CK5)/$CJ5 -> -0.5 | F5: =(DOE!E89-$CK5)/$CJ5 -> -0.5 | G5: =(DOE!F89-$CK5)/$CJ5 -> -0.5 | H5: =(DOE!G89-$CK5)/$CJ5 -> 1 | I5: =(DOE!H89-$CK5)/$CJ5 -> 1 | ... CD5: =(DOE!CC89-$CK5)/$CJ5 -> 1 | CE5: =SUMPRODUCT(MaxLikelihoodSolver!$B5:$CD5,$B$7:$CD$7) -> -47.5 | CF5: SumProduct with n_j | CH5: =MAX(SurveySetup!C5:E5) -> 600 | CI5: =MIN(SurveySetup!C5:E5) -> 120 | CJ5: =(CH5-CI5)/2 -> 240 | CK5: =CJ5+CI5 -> 360
A6: x3j | B6: =(DOE!A90-$CK6)/$CJ6 -> -1 | C6: =(DOE!B90-$CK6)/$CJ6 -> -0.11111111 | D6: =(DOE!C90-$CK6)/$CJ6 -> 1 | E6: =(DOE!D90-$CK6)/$CJ6 -> -1 | F6: =(DOE!E90-$CK6)/$CJ6 -> -0.11111111 | G6: =(DOE!F90-$CK6)/$CJ6 -> 1 | H6: =(DOE!G90-$CK6)/$CJ6 -> -1 | I6: =(DOE!H90-$CK6)/$CJ6 -> -0.11111111 | ... CD6: =(DOE!CC90-$CK6)/$CJ6 -> 1 | CE6: =SUMPRODUCT(MaxLikelihoodSolver!$B6:$CD6,$B$7:$CD$7) -> 24.666667 | CF6: SumProduct with n_j | CH6: =MAX(SurveySetup!C6:E6) -> 10 | CI6: =MIN(SurveySetup!C6:E6) -> 1 | CJ6: =(CH6-CI6)/2 -> 4.5 | CK6: =CJ6+CI6 -> 5.5
A7: nj | B7: {=TRANSPOSE(SurveyResultAggregation!$C$3:$C$83)} -> 1 | C7: 1 | D7: 0 | E7: 2 | F7: 1 | G7: 2 | H7: 0 | I7: 0 | J7: 0 | K7: 4 | L7: 5 | M7: 2 | N7: 0 | O7: 5 | P7: 4 | Q7: 1 | R7: 3 | S7: 3 | T7: 4 | U7: 3 | V7: 6 | W7: 2 | X7: 4 | Y7: 4 | Z7: 0 | AA7: 4 | AB7: 2 | AC7: 0 | AD7: 0 | AE7: 0 | AF7: 0 | AG7: 0 | AH7: 2 | AI7: 0 | AJ7: 0 | AK7: 0 | AL7: 1 | AM7: 3 | AN7: 1 | AO7: 3 | AP7: 1 | AQ7: 3 | AR7: 0 | AS7: 1 | AT7: 2 | AU7: 0 | AV7: 3 | AW7: 6 | AX7: 2 | AY7: 5 | AZ7: 2 | BA7: 1 | BB7: 2 | BC7: 3 | BD7: 0 | BE7: 0 | BF7: 0 | BG7: 0 | BH7: 0 | BI7: 0 | BJ7: 0 | BK7: 0 | BL7: 0 | BM7: 0 | BN7: 1 | BO7: 3 | BP7: 0 | BQ7: 2 | BR7: 2 | BS7: 0 | BT7: 1 | BU7: 0 | BV7: 0 | BW7: 0 | BX7: 3 | BY7: 0 | BZ7: 2 | CA7: 1 | CB7: 0 | CC7: 1 | CD7: 0 | CE7: =SUM(MaxLikelihoodSolver!$B7:$CD7) -> 120 | CF7: Sum
A8: POBS | B8: =B7/$CE$7 -> 0.0083333333 | C8: =C7/$CE$7 -> 0.0083333333 | D8: =D7/$CE$7 -> 0 | E8: =E7/$CE$7 -> 0.016666667 | F8: =F7/$CE$7 -> 0.0083333333 | G8: =G7/$CE$7 -> 0.016666667 | H8: =H7/$CE$7 -> 0 | I8: =I7/$CE$7 -> 0 | ... CD8: =CD7/$CE$7 -> 0 | CE8: =SUM(MaxLikelihoodSolver!$B8:$CD8) -> 1 | CF8: Sum
A10: Optimization Iterations -- for debugging | K10: Optimization Results -- after rescaling | O10: Hessian -- scaled
A11: iteration | B11: beta0 | C11: beta1 | D11: beta2 | E11: beta3 | F11: lnL | G11: alpha | H11: NormGradient | K11: beta | L11: gradient | M11: sigma | O11: =B915 -> -53.057894 | P11: =C915 -> 0.45685547 | Q11: =D915 -> 0.45685547 | R11: =E915 -> 0.45685547
A12: 1 | B12: =INDEX(B:B,ROW($B$34)+(MaxLikelihoodSolver!$A12-1)*(94-36)) -> 0 | C12: =INDEX(B:B,ROW($B$35)+(MaxLikelihoodSolver!$A12-1)*(94-36)) -> 0 | D12: =INDEX(B:B,ROW($B$36)+(MaxLikelihoodSolver!$A12-1)*(94-36)) -> 0 | E12: =INDEX(B:B,ROW($B$37)+(MaxLikelihoodSolver!$A12-1)*(94-36)) -> 0 | F12: =INDEX(F:F,ROW($F$36)+(MaxLikelihoodSolver!$A12-1)*(94-36)) -> -527.3339 | G12: =INDEX(H:H,ROW($H$85)+(MaxLikelihoodSolver!$A12-1)*(94-36)) -> 0.65234375 | H12: =INDEX(F:F,ROW($F$34)+(MaxLikelihoodSolver!$A12-1)*(94-36)) -> 6287.3349 | K12: =K897/$CJ3 -> -0.0090891018 | L12: =L897*$CJ3 -> 4.2632564e-12 | M12: =SQRT(O17)/$CJ3 -> 0.0018304608 | O12: =B916 -> -0.32919413 | P12: =C916 -> -72.056326 | Q12: =D916 -> -0.32919413 | R12: =E916 -> -0.32919413
A13: 2 | B13: =INDEX(B:B,ROW($B$34)+(MaxLikelihoodSolver!$A13-1)*(94-36)) -> -0.62469141 | C13: =INDEX(B:B,ROW($B$35)+(MaxLikelihoodSolver!$A13-1)*(94-36)) -> 0.65234375 | D13: =INDEX(B:B,ROW($B$36)+(MaxLikelihoodSolver!$A13-1)*(94-36)) -> -0.36293691 | E13: =INDEX(B:B,ROW($B$37)+(MaxLikelihoodSolver!$A13-1)*(94-36)) -> 0.38419988 | F13: =INDEX(F:F,ROW($F$36)+(MaxLikelihoodSolver!$A13-1)*(94-36)) -> -487.36901 | G13: =INDEX(H:H,ROW($H$85)+(MaxLikelihoodSolver!$A13-1)*(94-36)) -> 0.053512573 | H13: =INDEX(F:F,ROW($F$34)+(MaxLikelihoodSolver!$A13-1)*(94-36)) -> 16.04702 | K13: =K898/$CJ4 -> 0.71797282 | L13: =L898*$CJ4 -> 0 | M13: =SQRT(P18)/$CJ4 -> 0.13463082 | O13: =B917 -> 0.35770278 | P13: =C917 -> 0.35770278 | Q13: =D917 -> -68.494824 | R13: =E917 -> 0.35770278
A14: 3 | B14: =INDEX(B:B,ROW($B$34)+(MaxLikelihoodSolver!$A14-1)*(94-36)) -> -0.67820399 | C14: =INDEX(B:B,ROW($B$35)+(MaxLikelihoodSolver!$A14-1)*(94-36)) -> 0.62734158 | D14: =INDEX(B:B,ROW($B$36)+(MaxLikelihoodSolver!$A14-1)*(94-36)) -> -0.35144284 | E14: =INDEX(B:B,ROW($B$37)+(MaxLikelihoodSolver!$A14-1)*(94-36)) -> 0.35947798 | F14: =INDEX(F:F,ROW($F$36)+(MaxLikelihoodSolver!$A14-1)*(94-36)) -> -487.23896 | G14: =INDEX(H:H,ROW($H$85)+(MaxLikelihoodSolver!$A14-1)*(94-36)) -> 0.0027174354 | H14: =INDEX(F:F,ROW($F$34)+(MaxLikelihoodSolver!$A14-1)*(94-36)) -> 0.12825834 | K14: =K899/$CJ5 -> -0.001463119 | L14: =L899*$CJ5 -> 0 | M14: =SQRT(Q19)/$CJ5 -> 0.00050345617 | O14: =B918 -> -0.18575442 | P14: =C918 -> -0.18575442 | Q14: =D918 -> -0.18575442 | R14: =E918 -> -78.323497
A15: 4 | B15: =INDEX(B:B,ROW($B$34)+(MaxLikelihoodSolver!$A15-1)*(94-36)) -> -0.67875783 | C15: =INDEX(B:B,ROW($B$35)+(MaxLikelihoodSolver!$A15-1)*(94-36)) -> 0.62598953 | D15: =INDEX(B:B,ROW($B$36)+(MaxLikelihoodSolver!$A15-1)*(94-36)) -> -0.34994318 | E15: =INDEX(B:B,ROW($B$37)+(MaxLikelihoodSolver!$A15-1)*(94-36)) -> 0.36219542 | F15: =INDEX(F:F,ROW($F$36)+(MaxLikelihoodSolver!$A15-1)*(94-36)) -> -487.23854 | G15: =INDEX(H:H,ROW($H$85)+(MaxLikelihoodSolver!$A15-1)*(94-36)) -> 0.0014330226 | H15: =INDEX(F:F,ROW($F$34)+(MaxLikelihoodSolver!$A15-1)*(94-36)) -> 0.064612432 | K15: =K900/$CJ6 -> 0.080732285 | L15: =L900*$CJ6 -> 0 | M15: =SQRT(R20)/$CJ6 -> 0.025109421
A16: 5 | B16: =INDEX(B:B,ROW($B$34)+(MaxLikelihoodSolver!$A16-1)*(94-36)) -> -0.67929939 | C16: =INDEX(B:B,ROW($B$35)+(MaxLikelihoodSolver!$A16-1)*(94-36)) -> 0.62562364 | D16: =INDEX(B:B,ROW($B$36)+(MaxLikelihoodSolver!$A16-1)*(94-36)) -> -0.35137621 | E16: =INDEX(B:B,ROW($B$37)+(MaxLikelihoodSolver!$A16-1)*(94-36)) -> 0.36262692 | F16: =INDEX(F:F,ROW($F$36)+(MaxLikelihoodSolver!$A16-1)*(94-36)) -> -487.23845 | G16: =INDEX(H:H,ROW($H$85)+(MaxLikelihoodSolver!$A16-1)*(94-36)) -> 0.0026085489 | H16: =INDEX(F:F,ROW($F$34)+(MaxLikelihoodSolver!$A16-1)*(94-36)) -> 0.054167332 | O16: Sigma -- scaled
A17: 6 | B17: =INDEX(B:B,ROW($B$34)+(MaxLikelihoodSolver!$A17-1)*(94-36)) -> -0.68166306 | C17: =INDEX(B:B,ROW($B$35)+(MaxLikelihoodSolver!$A17-1)*(94-36)) -> 0.62823218 | D17: =INDEX(B:B,ROW($B$36)+(MaxLikelihoodSolver!$A17-1)*(94-36)) -> -0.35115026 | E17: =INDEX(B:B,ROW($B$37)+(MaxLikelihoodSolver!$A17-1)*(94-36)) -> 0.36328263 | F17: =INDEX(F:F,ROW($F$36)+(MaxLikelihoodSolver!$A17-1)*(94-36)) -> -487.23803 | G17: =INDEX(H:H,ROW($H$85)+(MaxLikelihoodSolver!$A17-1)*(94-36)) -> 1.0189644e-05 | H17: =INDEX(F:F,ROW($F$34)+(MaxLikelihoodSolver!$A17-1)*(94-36)) -> 2.2707399e-06 | O17: {=-MINVERSE(O11:R14)} -> 0.01884705 | P17: 0.00011983124 | Q17: 0.00012483421 | R17: 0.00010999999
A18: 7 | B18: =INDEX(B:B,ROW($B$34)+(MaxLikelihoodSolver!$A18-1)*(94-36)) -> -0.68167325 | C18: =INDEX(B:B,ROW($B$35)+(MaxLikelihoodSolver!$A18-1)*(94-36)) -> 0.62822909 | D18: =INDEX(B:B,ROW($B$36)+(MaxLikelihoodSolver!$A18-1)*(94-36)) -> -0.35114938 | E18: =INDEX(B:B,ROW($B$37)+(MaxLikelihoodSolver!$A18-1)*(94-36)) -> 0.36328929 | F18: =INDEX(F:F,ROW($F$36)+(MaxLikelihoodSolver!$A18-1)*(94-36)) -> -487.23803 | G18: =INDEX(H:H,ROW($H$85)+(MaxLikelihoodSolver!$A18-1)*(94-36)) -> 9.3537748e-06 | H18: =INDEX(F:F,ROW($F$34)+(MaxLikelihoodSolver!$A18-1)*(94-36)) -> 5.173549e-07 | O18: -8.6346212e-05 | P18: 0.013877304 | Q18: -6.7111493e-05 | R18: -5.9136542e-05
A19: 8 | B19: =INDEX(B:B,ROW($B$34)+(MaxLikelihoodSolver!$A19-1)*(94-36)) -> -0.68168261 | C19: =INDEX(B:B,ROW($B$35)+(MaxLikelihoodSolver!$A19-1)*(94-36)) -> 0.62822622 | D19: =INDEX(B:B,ROW($B$36)+(MaxLikelihoodSolver!$A19-1)*(94-36)) -> -0.35114856 | E19: =INDEX(B:B,ROW($B$37)+(MaxLikelihoodSolver!$A19-1)*(94-36)) -> 0.36329527 | F19: =INDEX(F:F,ROW($F$36)+(MaxLikelihoodSolver!$A19-1)*(94-36)) -> -487.23803 | G19: =INDEX(H:H,ROW($H$85)+(MaxLikelihoodSolver!$A19-1)*(94-36)) -> 3.6538183e-08 | H19: =INDEX(F:F,ROW($F$34)+(MaxLikelihoodSolver!$A19-1)*(94-36)) -> 3.4149542e-12 | O19: 9.7741071e-05 | P19: 7.2923436e-05 | Q19: 0.014599763 | R19: 6.694062e-05
A20: 9 | B20: =INDEX(B:B,ROW($B$34)+(MaxLikelihoodSolver!$A20-1)*(94-36)) -> -0.68168264 | C20: =INDEX(B:B,ROW($B$35)+(MaxLikelihoodSolver!$A20-1)*(94-36)) -> 0.62822621 | D20: =INDEX(B:B,ROW($B$36)+(MaxLikelihoodSolver!$A20-1)*(94-36)) -> -0.35114855 | E20: =INDEX(B:B,ROW($B$37)+(MaxLikelihoodSolver!$A20-1)*(94-36)) -> 0.36329529 | F20: =INDEX(F:F,ROW($F$36)+(MaxLikelihoodSolver!$A20-1)*(94-36)) -> -487.23803 | G20: =INDEX(H:H,ROW($H$85)+(MaxLikelihoodSolver!$A20-1)*(94-36)) -> 1.1560909e-08 | H20: =INDEX(F:F,ROW($F$34)+(MaxLikelihoodSolver!$A20-1)*(94-36)) -> 7.5132214e-13 | O20: -4.472527e-05 | P20: -3.3368985e-05 | Q20: -3.4762146e-05 | R20: 0.012767281
A21: 10 | B21: =INDEX(B:B,ROW($B$34)+(MaxLikelihoodSolver!$A21-1)*(94-36)) -> -0.68168263 | C21: =INDEX(B:B,ROW($B$35)+(MaxLikelihoodSolver!$A21-1)*(94-36)) -> 0.62822621 | D21: =INDEX(B:B,ROW($B$36)+(MaxLikelihoodSolver!$A21-1)*(94-36)) -> -0.35114856 | E21: =INDEX(B:B,ROW($B$37)+(MaxLikelihoodSolver!$A21-1)*(94-36)) -> 0.36329528 | F21: =INDEX(F:F,ROW($F$36)+(MaxLikelihoodSolver!$A21-1)*(94-36)) -> -487.23803 | G21: =INDEX(H:H,ROW($H$85)+(MaxLikelihoodSolver!$A21-1)*(94-36)) -> 1.3547941e-10 | H21: =INDEX(F:F,ROW($F$34)+(MaxLikelihoodSolver!$A21-1)*(94-36)) -> 5.2544169e-17
A22: 11 | B22: =INDEX(B:B,ROW($B$34)+(MaxLikelihoodSolver!$A22-1)*(94-36)) -> -0.68168263 | C22: =INDEX(B:B,ROW($B$35)+(MaxLikelihoodSolver!$A22-1)*(94-36)) -> 0.62822621 | D22: =INDEX(B:B,ROW($B$36)+(MaxLikelihoodSolver!$A22-1)*(94-36)) -> -0.35114856 | E22: =INDEX(B:B,ROW($B$37)+(MaxLikelihoodSolver!$A22-1)*(94-36)) -> 0.36329528 | F22: =INDEX(F:F,ROW($F$36)+(MaxLikelihoodSolver!$A22-1)*(94-36)) -> -487.23803 | G22: =INDEX(H:H,ROW($H$85)+(MaxLikelihoodSolver!$A22-1)*(94-36)) -> 3.7574367e-11 | H22: =INDEX(F:F,ROW($F$34)+(MaxLikelihoodSolver!$A22-1)*(94-36)) -> 8.0227551e-18
A23: 12 | B23: =INDEX(B:B,ROW($B$34)+(MaxLikelihoodSolver!$A23-1)*(94-36)) -> -0.68168263 | C23: =INDEX(B:B,ROW($B$35)+(MaxLikelihoodSolver!$A23-1)*(94-36)) -> 0.62822621 | D23: =INDEX(B:B,ROW($B$36)+(MaxLikelihoodSolver!$A23-1)*(94-36)) -> -0.35114856 | E23: =INDEX(B:B,ROW($B$37)+(MaxLikelihoodSolver!$A23-1)*(94-36)) -> 0.36329528 | F23: =INDEX(F:F,ROW($F$36)+(MaxLikelihoodSolver!$A23-1)*(94-36)) -> -487.23803 | G23: =INDEX(H:H,ROW($H$85)+(MaxLikelihoodSolver!$A23-1)*(94-36)) -> 4.4032461e-13 | H23: =INDEX(F:F,ROW($F$34)+(MaxLikelihoodSolver!$A23-1)*(94-36)) -> 1.3412024e-21
A24: 13 | B24: =INDEX(B:B,ROW($B$34)+(MaxLikelihoodSolver!$A24-1)*(94-36)) -> -0.68168263 | C24: =INDEX(B:B,ROW($B$35)+(MaxLikelihoodSolver!$A24-1)*(94-36)) -> 0.62822621 | D24: =INDEX(B:B,ROW($B$36)+(MaxLikelihoodSolver!$A24-1)*(94-36)) -> -0.35114856 | E24: =INDEX(B:B,ROW($B$37)+(MaxLikelihoodSolver!$A24-1)*(94-36)) -> 0.36329528 | F24: =INDEX(F:F,ROW($F$36)+(MaxLikelihoodSolver!$A24-1)*(94-36)) -> -487.23803 | G24: =INDEX(H:H,ROW($H$85)+(MaxLikelihoodSolver!$A24-1)*(94-36)) -> 5.3320558e-14 | H24: =INDEX(F:F,ROW($F$34)+(MaxLikelihoodSolver!$A24-1)*(94-36)) -> 1.506193e-23
A25: 14 | B25: =INDEX(B:B,ROW($B$34)+(MaxLikelihoodSolver!$A25-1)*(94-36)) -> -0.68168263 | C25: =INDEX(B:B,ROW($B$35)+(MaxLikelihoodSolver!$A25-1)*(94-36)) -> 0.62822621 | D25: =INDEX(B:B,ROW($B$36)+(MaxLikelihoodSolver!$A25-1)*(94-36)) -> -0.35114856 | E25: =INDEX(B:B,ROW($B$37)+(MaxLikelihoodSolver!$A25-1)*(94-36)) -> 0.36329528 | F25: =INDEX(F:F,ROW($F$36)+(MaxLikelihoodSolver!$A25-1)*(94-36)) -> -487.23803 | G25: =INDEX(H:H,ROW($H$85)+(MaxLikelihoodSolver!$A25-1)*(94-36)) -> 3.5408183e-15 | H25: =INDEX(F:F,ROW($F$34)+(MaxLikelihoodSolver!$A25-1)*(94-36)) -> 3.3977817e-26
A26: 15 | B26: =INDEX(B:B,ROW($B$34)+(MaxLikelihoodSolver!$A26-1)*(94-36)) -> -0.68168263 | C26: =INDEX(B:B,ROW($B$35)+(MaxLikelihoodSolver!$A26-1)*(94-36)) -> 0.62822621 | D26: =INDEX(B:B,ROW($B$36)+(MaxLikelihoodSolver!$A26-1)*(94-36)) -> -0.35114856 | E26: =INDEX(B:B,ROW($B$37)+(MaxLikelihoodSolver!$A26-1)*(94-36)) -> 0.36329528 | F26: =INDEX(F:F,ROW($F$36)+(MaxLikelihoodSolver!$A26-1)*(94-36)) -> -487.23803 | G26: =INDEX(H:H,ROW($H$85)+(MaxLikelihoodSolver!$A26-1)*(94-36)) -> 2.0608669e-15 | H26: =INDEX(F:F,ROW($F$34)+(MaxLikelihoodSolver!$A26-1)*(94-36)) -> 1.0160528e-26
A30: BFGS Optimization of Maximum Likelihood using Analytical Gradients and Bisection Line Search
A32: BFGS Iteration | C32: 1
B33: beta | D33: gradient | F33: NormGradient | H33: inv(B_k) | M33: p_k_unnorm | N33: p_k | P33: grad_k+1 | R33: s_k | T33: y_k | V33: Binv*y | X33: Inv(B_k+1) | AC33: Sum
B34: 0 | D34: =$CE$3-$CE$7*SUMPRODUCT($B$3:$CD$3,AE36:DG36) -> -47.333333 | F34: =SUMPRODUCT(D34:D37,D34:D37) -> 6287.3349 | H34: 1 | I34: 0 | J34: 0 | K34: 0 | M34: {=MMULT(H34:K37,D34:D37)} -> -47.333333 | N34: =IFERROR(M34/(MAX(ABS(M34),ABS(M35),ABS(M36),ABS(M37))),0) -> -0.95761079 | P34: =L85 -> -3.1281693 | R34: =H85*J85 -> -0.62469141 | T34: =P34-D34 -> 44.205164 | V34: {=MMULT(H34:K37,T34:T37)} -> 44.205164 | X34: {=H34:K37+MMULT(R34:R37,TRANSPOSE(R34:R37))*((SUMPRODUCT(R34:R37,T34:T37)+SUMPRODUCT(V34:V37,T34:T37))/SUMPRODUCT(R34:R37,T34:T37)^2)-(MMULT(V34:V37,TRANSPOSE(R34:R37))+MMULT(R34:R37,TRANSPOSE(V34:V37)))/SUMPRODUCT(R34:R37,T34:T37)} -> 0.68765892 | Y34: 0.36366429 | Z34: -0.20120758 | AA34: 0.21881568 | AC34: =SUM(AE34:DG34) -> 0 | AD34: v_j | AE34: =SUMPRODUCT(B$3:B$6,$B34:$B37) -> 0 | AF34: =SUMPRODUCT(C$3:C$6,$B34:$B37) -> 0 | AG34: =SUMPRODUCT(D$3:D$6,$B34:$B37) -> 0 | AH34: =SUMPRODUCT(E$3:E$6,$B34:$B37) -> 0 | AI34: =SUMPRODUCT(F$3:F$6,$B34:$B37) -> 0 | AJ34: =SUMPRODUCT(G$3:G$6,$B34:$B37) -> 0 | AK34: =SUMPRODUCT(H$3:H$6,$B34:$B37) -> 0 | AL34: =SUMPRODUCT(I$3:I$6,$B34:$B37) -> 0 | ... DG34: =SUMPRODUCT(CD$3:CD$6,$B34:$B37) -> 0
B35: 0 | D35: =$CE$4-$CE$7*SUMPRODUCT($B$4:$CD$4,AE36:DG36) -> 49.428571 | F35: LogLikelihood | H35: 0 | I35: 1 | J35: 0 | K35: 0 | M35: 49.428571 | N35: =IFERROR(M35/(MAX(ABS(M34),ABS(M35),ABS(M36),ABS(M37))),0) -> 1 | P35: =L86 -> -1.7193428 | R35: =H86*J86 -> 0.65234375 | T35: =P35-D35 -> -51.147914 | V35: -51.147914 | X35: 0.36366429 | Y35: 0.58108082 | Z35: 0.23189952 | AA35: -0.25156337 | AC35: =SUM(AE35:DG35) -> 81 | AD35: exp(v_j) | AE35: =EXP(AE34) -> 1 | AF35: =EXP(AF34) -> 1 | AG35: =EXP(AG34) -> 1 | AH35: =EXP(AH34) -> 1 | AI35: =EXP(AI34) -> 1 | AJ35: =EXP(AJ34) -> 1 | AK35: =EXP(AK34) -> 1 | AL35: =EXP(AL34) -> 1 | ... DG35: =EXP(DG34) -> 1
B36: 0 | D36: =$CE$5-$CE$7*SUMPRODUCT($B$5:$CD$5,AE36:DG36) -> -27.5 | F36: =SUMPRODUCT($B$7:$CD$7, LN(AE36:DG36)) -> -527.3339 | H36: 0 | I36: 0 | J36: 1 | K36: 0 | M36: -27.5 | N36: =IFERROR(M36/(MAX(ABS(M34),ABS(M35),ABS(M36),ABS(M37))),0) -> -0.55635838 | P36: =L87 -> 0.80763277 | R36: =H87*J87 -> -0.36293691 | T36: =P36-D36 -> 28.307633 | V36: 28.307633 | X36: -0.20120758 | Y36: 0.23189952 | Z36: 0.87163151 | AA36: 0.13927051 | AC36: =SUM(AE36:DG36) -> 1 | AD36: P_j | AE36: =AE35/$AC35 -> 0.012345679 | AF36: =AF35/$AC35 -> 0.012345679 | AG36: =AG35/$AC35 -> 0.012345679 | AH36: =AH35/$AC35 -> 0.012345679 | AI36: =AI35/$AC35 -> 0.012345679 | AJ36: =AJ35/$AC35 -> 0.012345679 | AK36: =AK35/$AC35 -> 0.012345679 | AL36: =AL35/$AC35 -> 0.012345679 | ... DG36: =DG35/$AC35 -> 0.012345679
B37: 0 | D37: =$CE$6-$CE$7*SUMPRODUCT($B$6:$CD$6,AE36:DG36) -> 29.111111 | H37: 0 | I37: 0 | J37: 0 | K37: 1 | M37: 29.111111 | N37: =IFERROR(M37/(MAX(ABS(M34),ABS(M35),ABS(M36),ABS(M37))),0) -> 0.58895311 | P37: =L88 -> -1.6288544 | R37: =H88*J88 -> 0.38419988 | T37: =P37-D37 -> -30.739965 | V37: -30.739965 | X37: 0.21881568 | Y37: -0.25156337 | Z37: 0.13927051 | AA37: 0.84899066
B39: LineSearch Iteration | D39: low | E39: high | F39: bracket? | H39: alpha | I39: beta_iter | J39: p_k_iter | K39: beta | L39: gradient | M39: derivative
B40: 1 | D40: 0 | F40: FALSE | H40: 0 | I40: =B34 -> 0 | J40: =IF(SUMPRODUCT(L40:L43,N34:N37)>0,N34,-N34) -> -0.95761079 | K40: =I40+J40*H40 -> 0 | L40: =D34 -> -47.333333 | M40: =SUMPRODUCT(L40:L43,J40:J43) -> 127.20042
H41: =H40 -> 0 | I41: =B35 -> 0 | J41: =IF(SUMPRODUCT(L40:L43,N34:N37)>0,N35,-N35) -> 1 | K41: =I41+J41*H41 -> 0 | L41: =D35 -> 49.428571 | M41: ln(likelihood)
H42: =H41 -> 0 | I42: =B36 -> 0 | J42: =IF(SUMPRODUCT(L40:L43,N34:N37)>0,N36,-N36) -> -0.55635838 | K42: =I42+J42*H42 -> 0 | L42: =D36 -> -27.5 | M42: =F36 -> -527.3339
H43: =H42 -> 0 | I43: =B37 -> 0 | J43: =IF(SUMPRODUCT(L40:L43,N34:N37)>0,N37,-N37) -> 0.58895311 | K43: =I43+J43*H43 -> 0 | L43: =D37 -> 29.111111
B44: LineSearch Iteration | D44: low | E44: high | F44: bracket? | H44: alpha | I44: beta_iter | J44: p_k_iter | K44: beta | L44: gradient | M44: derivative | O44: Sum
B45: =1+B40 -> 2 | D45: 0 | E45: =H45 -> 1 | F45: =OR(F40,M45*M40<=0) -> TRUE | H45: 1 | I45: =I40 -> 0 | J45: =J40 -> -0.95761079 | K45: =I45+J45*H45 -> -0.95761079 | L45: =$CE$3-$CE$7*SUMPRODUCT($B$3:$CD$3,Q47:CS47) -> 13.014311 | M45: =SUMPRODUCT(L45:L48,J45:J48) -> -53.518572 | O45: =SUM(Q45:CS45) -> 10.505333 | P45: v_j | Q45: =SUMPRODUCT(B$3:B$6,$K45:$K48) -> -0.074983943 | R45: =SUMPRODUCT(C$3:C$6,$K45:$K48) -> 0.44852994 | S45: =SUMPRODUCT(D$3:D$6,$K45:$K48) -> 1.1029223 | T45: =SUMPRODUCT(E$3:E$6,$K45:$K48) -> -0.35316313 | U45: =SUMPRODUCT(F$3:F$6,$K45:$K48) -> 0.17035075 | V45: =SUMPRODUCT(G$3:G$6,$K45:$K48) -> 0.8247431 | W45: =SUMPRODUCT(H$3:H$6,$K45:$K48) -> -1.1877007 | X45: =SUMPRODUCT(I$3:I$6,$K45:$K48) -> -0.66418683 | ... CS45: =SUMPRODUCT(CD$3:CD$6,$K45:$K48) -> 0.074983943
H46: =H45 -> 1 | I46: =I41 -> 0 | J46: =J41 -> 1 | K46: =I46+J46*H46 -> 1 | L46: =$CE$4-$CE$7*SUMPRODUCT($B$4:$CD$4,Q47:CS47) -> -23.87612 | M46: ln(likelihood) | O46: =SUM(Q46:CS46) -> 206.78854 | P46: exp(v_j) | Q46: =EXP(Q45) -> 0.92775838 | R46: =EXP(R45) -> 1.5660084 | S46: =EXP(S45) -> 3.0129579 | T46: =EXP(T45) -> 0.70246259 | U46: =EXP(U45) -> 1.1857207 | V46: =EXP(V45) -> 2.2812946 | W46: =EXP(W45) -> 0.30492156 | X46: =EXP(X45) -> 0.51469189 | ... CS46: =EXP(CS45) -> 1.0778668
H47: =H46 -> 1 | I47: =I42 -> 0 | J47: =J42 -> -0.55635838 | K47: =I47+J47*H47 -> -0.55635838 | L47: =$CE$5-$CE$7*SUMPRODUCT($B$5:$CD$5,Q47:CS47) -> 12.902876 | M47: =SUMPRODUCT($B$7:$CD$7, LN(Q47:CS47)) -> -497.03973 | O47: =SUM(Q47:CS47) -> 1 | P47: P_j | Q47: =Q46/$O46 -> 0.0044865077 | R47: =R46/$O46 -> 0.0075729939 | S47: =S46/$O46 -> 0.014570236 | T47: =T46/$O46 -> 0.0033970092 | U47: =U46/$O46 -> 0.0057339766 | V47: =V46/$O46 -> 0.011032017 | W47: =W46/$O46 -> 0.0014745573 | X47: =X46/$O46 -> 0.0024889768 | ... CS47: =CS46/$O46 -> 0.0052124109
H48: =H47 -> 1 | I48: =I43 -> 0 | J48: =J43 -> 0.58895311 | K48: =I48+J48*H48 -> 0.58895311 | L48: =$CE$6-$CE$7*SUMPRODUCT($B$6:$CD$6,Q47:CS47) -> -16.98129
B49: LineSearch Iteration | D49: low | E49: high | F49: bracket? | H49: alpha | I49: beta_iter | J49: p_k_iter | K49: beta | L49: gradient | M49: derivative | O49: Sum
B50: =1+B45 -> 3 | D50: =IF(F45,IF(M50<0,D45,H50),E45) -> 0.5 | E50: =IF(F45,IF(M50<0,H50,E45),H50) -> 1 | F50: =OR(F45,M50*M45<=0) -> TRUE | H50: =IF(F45,(D45+E45)/2,2*H45) -> 0.5 | I50: =I45 -> 0 | J50: =J45 -> -0.95761079 | K50: =I50+J50*H50 -> -0.47880539 | L50: =$CE$3-$CE$7*SUMPRODUCT($B$3:$CD$3,Q52:CS52) -> -11.858198 | M50: =SUMPRODUCT(L50:L53,J50:J53) -> 26.902515 | O50: =SUM(Q50:CS50) -> 5.2526665 | P50: v_j | Q50: =SUMPRODUCT(B$3:B$6,$K50:$K53) -> -0.037491972 | R50: =SUMPRODUCT(C$3:C$6,$K50:$K53) -> 0.22426497 | S50: =SUMPRODUCT(D$3:D$6,$K50:$K53) -> 0.55146114 | T50: =SUMPRODUCT(E$3:E$6,$K50:$K53) -> -0.17658157 | U50: =SUMPRODUCT(F$3:F$6,$K50:$K53) -> 0.085175373 | V50: =SUMPRODUCT(G$3:G$6,$K50:$K53) -> 0.41237155 | W50: =SUMPRODUCT(H$3:H$6,$K50:$K53) -> -0.59385035 | X50: =SUMPRODUCT(I$3:I$6,$K50:$K53) -> -0.33209341 | ... CS50: =SUMPRODUCT(CD$3:CD$6,$K50:$K53) -> 0.037491972
H51: =H50 -> 0.5 | I51: =I46 -> 0 | J51: =J46 -> 1 | K51: =I51+J51*H51 -> 0.5 | L51: =$CE$4-$CE$7*SUMPRODUCT($B$4:$CD$4,Q52:CS52) -> 9.4735383 | M51: ln(likelihood) | O51: =SUM(Q51:CS51) -> 107.02153 | P51: exp(v_j) | Q51: =EXP(Q50) -> 0.96320215 | R51: =EXP(R50) -> 1.2514026 | S51: =EXP(S50) -> 1.7357874 | T51: =EXP(T50) -> 0.83813041 | U51: =EXP(U50) -> 1.088908 | V51: =EXP(V50) -> 1.5103955 | W51: =EXP(W50) -> 0.55219703 | X51: =EXP(X50) -> 0.7174203 | ... CS51: =EXP(CS50) -> 1.0382037
H52: =H51 -> 0.5 | I52: =I47 -> 0 | J52: =J47 -> -0.55635838 | K52: =I52+J52*H52 -> -0.27817919 | L52: =$CE$5-$CE$7*SUMPRODUCT($B$5:$CD$5,Q52:CS52) -> -5.1769975 | M52: =SUMPRODUCT($B$7:$CD$7, LN(Q52:CS52)) -> -489.38167 | O52: =SUM(Q52:CS52) -> 1 | P52: P_j | Q52: =Q51/$O51 -> 0.0090000779 | R52: =R51/$O51 -> 0.011692998 | S52: =S51/$O51 -> 0.016219048 | T52: =T51/$O51 -> 0.0078314184 | U52: =U51/$O51 -> 0.010174663 | V52: =V51/$O51 -> 0.014113006 | W52: =W51/$O51 -> 0.0051596815 | X52: =X51/$O51 -> 0.0067035135 | ... CS52: =CS51/$O51 -> 0.0097008856
H53: =H52 -> 0.5 | I53: =I48 -> 0 | J53: =J48 -> 0.58895311 | K53: =I53+J53*H53 -> 0.29447656 | L53: =$CE$6-$CE$7*SUMPRODUCT($B$6:$CD$6,Q52:CS52) -> 5.4217764
B54: LineSearch Iteration | D54: low | E54: high | F54: bracket? | H54: alpha | I54: beta_iter | J54: p_k_iter | K54: beta | L54: gradient | M54: derivative | O54: Sum
B55: =1+B50 -> 4 | D55: =IF(F50,IF(M55<0,D50,H55),E50) -> 0.5 | E55: =IF(F50,IF(M55<0,H55,E50),H55) -> 0.75 | F55: =OR(F50,M55*M50<=0) -> TRUE | H55: =IF(F50,(D50+E50)/2,2*H50) -> 0.75 | I55: =I50 -> 0 | J55: =J50 -> -0.95761079 | K55: =I55+J55*H55 -> -0.71820809 | L55: =$CE$3-$CE$7*SUMPRODUCT($B$3:$CD$3,Q57:CS57) -> 1.9228051 | M55: =SUMPRODUCT(L55:L58,J55:J58) -> -16.327035 | O55: =SUM(Q55:CS55) -> 7.8789998 | P55: v_j | Q55: =SUMPRODUCT(B$3:B$6,$K55:$K58) -> -0.056237958 | R55: =SUMPRODUCT(C$3:C$6,$K55:$K58) -> 0.33639745 | S55: =SUMPRODUCT(D$3:D$6,$K55:$K58) -> 0.82719171 | T55: =SUMPRODUCT(E$3:E$6,$K55:$K58) -> -0.26487235 | U55: =SUMPRODUCT(F$3:F$6,$K55:$K58) -> 0.12776306 | V55: =SUMPRODUCT(G$3:G$6,$K55:$K58) -> 0.61855732 | W55: =SUMPRODUCT(H$3:H$6,$K55:$K58) -> -0.89077553 | X55: =SUMPRODUCT(I$3:I$6,$K55:$K58) -> -0.49814012 | ... CS55: =SUMPRODUCT(CD$3:CD$6,$K55:$K58) -> 0.056237958
H56: =H55 -> 0.75 | I56: =I51 -> 0 | J56: =J51 -> 1 | K56: =I56+J56*H56 -> 0.75 | L56: =$CE$4-$CE$7*SUMPRODUCT($B$4:$CD$4,Q57:CS57) -> -8.4552201 | M56: ln(likelihood) | O56: =SUM(Q56:CS56) -> 142.65687 | P56: exp(v_j) | Q56: =EXP(Q55) -> 0.94531416 | R56: =EXP(R55) -> 1.3998953 | S56: =EXP(S55) -> 2.2868875 | T56: =EXP(T55) -> 0.76730389 | U56: =EXP(U55) -> 1.1362837 | V56: =EXP(V55) -> 1.8562481 | W56: =EXP(W55) -> 0.4103374 | X56: =EXP(X55) -> 0.60765978 | ... CS56: =EXP(CS55) -> 1.0578494
H57: =H56 -> 0.75 | I57: =I52 -> 0 | J57: =J52 -> -0.55635838 | K57: =I57+J57*H57 -> -0.41726879 | L57: =$CE$5-$CE$7*SUMPRODUCT($B$5:$CD$5,Q57:CS57) -> 4.4254631 | M57: =SUMPRODUCT($B$7:$CD$7, LN(Q57:CS57)) -> -488.18016 | O57: =SUM(Q57:CS57) -> 1 | P57: P_j | Q57: =Q56/$O56 -> 0.006626489 | R57: =R56/$O56 -> 0.0098130242 | S57: =S56/$O56 -> 0.016030686 | T57: =T56/$O56 -> 0.0053786677 | U57: =U56/$O56 -> 0.0079651527 | V57: =V56/$O56 -> 0.013011979 | W57: =W56/$O56 -> 0.0028763943 | X57: =X56/$O56 -> 0.0042595901 | ... CS57: =CS56/$O56 -> 0.0074153414
H58: =H57 -> 0.75 | I58: =I53 -> 0 | J58: =J53 -> 0.58895311 | K58: =I58+J58*H58 -> 0.44171484 | L58: =$CE$6-$CE$7*SUMPRODUCT($B$6:$CD$6,Q57:CS57) -> -6.0588403
B59: LineSearch Iteration | D59: low | E59: high | F59: bracket? | H59: alpha | I59: beta_iter | J59: p_k_iter | K59: beta | L59: gradient | M59: derivative | O59: Sum
B60: =1+B55 -> 5 | D60: =IF(F55,IF(M60<0,D55,H60),E55) -> 0.625 | E60: =IF(F55,IF(M60<0,H60,E55),H60) -> 0.75 | F60: =OR(F55,M60*M55<=0) -> TRUE | H60: =IF(F55,(D55+E55)/2,2*H55) -> 0.625 | I60: =I55 -> 0 | J60: =J55 -> -0.95761079 | K60: =I60+J60*H60 -> -0.59850674 | L60: =$CE$3-$CE$7*SUMPRODUCT($B$3:$CD$3,Q62:CS62) -> -4.6182837 | M60: =SUMPRODUCT(L60:L63,J60:J63) -> 4.5647115 | O60: =SUM(Q60:CS60) -> 6.5658332 | P60: v_j | Q60: =SUMPRODUCT(B$3:B$6,$K60:$K63) -> -0.046864965 | R60: =SUMPRODUCT(C$3:C$6,$K60:$K63) -> 0.28033121 | S60: =SUMPRODUCT(D$3:D$6,$K60:$K63) -> 0.68932643 | T60: =SUMPRODUCT(E$3:E$6,$K60:$K63) -> -0.22072696 | U60: =SUMPRODUCT(F$3:F$6,$K60:$K63) -> 0.10646922 | V60: =SUMPRODUCT(G$3:G$6,$K60:$K63) -> 0.51546443 | W60: =SUMPRODUCT(H$3:H$6,$K60:$K63) -> -0.74231294 | X60: =SUMPRODUCT(I$3:I$6,$K60:$K63) -> -0.41511677 | ... CS60: =SUMPRODUCT(CD$3:CD$6,$K60:$K63) -> 0.046864965
H61: =H60 -> 0.625 | I61: =I56 -> 0 | J61: =J56 -> 1 | K61: =I61+J61*H61 -> 0.625 | L61: =$CE$4-$CE$7*SUMPRODUCT($B$4:$CD$4,Q62:CS62) -> 0.23159338 | M61: ln(likelihood) | O61: =SUM(Q61:CS61) -> 122.17738 | P61: exp(v_j) | Q61: =EXP(Q60) -> 0.95421624 | R61: =EXP(R60) -> 1.3235681 | S61: =EXP(S60) -> 1.9923731 | T61: =EXP(T60) -> 0.80193561 | U61: =EXP(U60) -> 1.1123437 | V61: =EXP(V60) -> 1.674416 | W61: =EXP(W60) -> 0.47601165 | X61: =EXP(X60) -> 0.66026318 | ... CS61: =EXP(CS60) -> 1.0479805
H62: =H61 -> 0.625 | I62: =I57 -> 0 | J62: =J57 -> -0.55635838 | K62: =I62+J62*H62 -> -0.34772399 | L62: =$CE$5-$CE$7*SUMPRODUCT($B$5:$CD$5,Q62:CS62) -> -0.23612938 | M62: =SUMPRODUCT($B$7:$CD$7, LN(Q62:CS62)) -> -487.42945 | O62: =SUM(Q62:CS62) -> 1 | P62: P_j | Q62: =Q61/$O61 -> 0.0078100892 | R62: =R61/$O61 -> 0.010833168 | S62: =S61/$O61 -> 0.016307217 | T62: =T61/$O61 -> 0.0065636995 | U62: =U61/$O61 -> 0.009104334 | V62: =V61/$O61 -> 0.013704795 | W62: =W61/$O61 -> 0.0038960702 | X62: =X61/$O61 -> 0.005404136 | ... CS62: =CS61/$O61 -> 0.0085775327
H63: =H62 -> 0.625 | I63: =I58 -> 0 | J63: =J58 -> 0.58895311 | K63: =I63+J63*H63 -> 0.3680957 | L63: =$CE$6-$CE$7*SUMPRODUCT($B$6:$CD$6,Q62:CS62) -> -0.37485623
B64: LineSearch Iteration | D64: low | E64: high | F64: bracket? | H64: alpha | I64: beta_iter | J64: p_k_iter | K64: beta | L64: gradient | M64: derivative | O64: Sum
B65: =1+B60 -> 6 | D65: =IF(F60,IF(M65<0,D60,H65),E60) -> 0.625 | E65: =IF(F60,IF(M65<0,H65,E60),H65) -> 0.6875 | F65: =OR(F60,M65*M60<=0) -> TRUE | H65: =IF(F60,(D60+E60)/2,2*H60) -> 0.6875 | I65: =I60 -> 0 | J65: =J60 -> -0.95761079 | K65: =I65+J65*H65 -> -0.65835742 | L65: =$CE$3-$CE$7*SUMPRODUCT($B$3:$CD$3,Q67:CS67) -> -1.2613165 | M65: =SUMPRODUCT(L65:L68,J65:J68) -> -6.0679773 | O65: =SUM(Q65:CS65) -> 7.2224165 | P65: v_j | Q65: =SUMPRODUCT(B$3:B$6,$K65:$K68) -> -0.051551461 | R65: =SUMPRODUCT(C$3:C$6,$K65:$K68) -> 0.30836433 | S65: =SUMPRODUCT(D$3:D$6,$K65:$K68) -> 0.75825907 | T65: =SUMPRODUCT(E$3:E$6,$K65:$K68) -> -0.24279965 | U65: =SUMPRODUCT(F$3:F$6,$K65:$K68) -> 0.11711614 | V65: =SUMPRODUCT(G$3:G$6,$K65:$K68) -> 0.56701088 | W65: =SUMPRODUCT(H$3:H$6,$K65:$K68) -> -0.81654424 | X65: =SUMPRODUCT(I$3:I$6,$K65:$K68) -> -0.45662844 | ... CS65: =SUMPRODUCT(CD$3:CD$6,$K65:$K68) -> 0.051551461
H66: =H65 -> 0.6875 | I66: =I61 -> 0 | J66: =J61 -> 1 | K66: =I66+J66*H66 -> 0.6875 | L66: =$CE$4-$CE$7*SUMPRODUCT($B$4:$CD$4,Q67:CS67) -> -4.1869355 | M66: ln(likelihood) | O66: =SUM(Q66:CS66) -> 131.66194 | P66: exp(v_j) | Q66: =EXP(Q65) -> 0.94975477 | R66: =EXP(R65) -> 1.3611968 | S66: =EXP(S65) -> 2.1345569 | T66: =EXP(T65) -> 0.78442865 | U66: =EXP(U65) -> 1.12425 | V66: =EXP(V65) -> 1.7629894 | W66: =EXP(W65) -> 0.44195632 | X66: =EXP(X65) -> 0.63341565 | ... CS66: =EXP(CS65) -> 1.0529034
H67: =H66 -> 0.6875 | I67: =I62 -> 0 | J67: =J62 -> -0.55635838 | K67: =I67+J67*H67 -> -0.38249639 | L67: =$CE$5-$CE$7*SUMPRODUCT($B$5:$CD$5,Q67:CS67) -> 2.1298708 | M67: =SUMPRODUCT($B$7:$CD$7, LN(Q67:CS67)) -> -487.47835 | O67: =SUM(Q67:CS67) -> 1 | P67: P_j | Q67: =Q66/$O66 -> 0.0072135862 | R67: =R66/$O66 -> 0.010338575 | S67: =S66/$O66 -> 0.016212406 | T67: =T66/$O66 -> 0.0059578998 | U67: =U66/$O66 -> 0.0085389139 | V67: =V66/$O66 -> 0.013390273 | W67: =W66/$O66 -> 0.0033567507 | X67: =X66/$O66 -> 0.0048109244 | ... CS67: =CS66/$O66 -> 0.0079970214
H68: =H67 -> 0.6875 | I68: =I63 -> 0 | J68: =J63 -> 0.58895311 | K68: =I68+J68*H68 -> 0.40490527 | L68: =$CE$6-$CE$7*SUMPRODUCT($B$6:$CD$6,Q67:CS67) -> -3.2327203
B69: LineSearch Iteration | D69: low | E69: high | F69: bracket? | H69: alpha | I69: beta_iter | J69: p_k_iter | K69: beta | L69: gradient | M69: derivative | O69: Sum
B70: =1+B65 -> 7 | D70: =IF(F65,IF(M70<0,D65,H70),E65) -> 0.625 | E70: =IF(F65,IF(M70<0,H70,E65),H70) -> 0.65625 | F70: =OR(F65,M70*M65<=0) -> TRUE | H70: =IF(F65,(D65+E65)/2,2*H65) -> 0.65625 | I70: =I65 -> 0 | J70: =J65 -> -0.95761079 | K70: =I70+J70*H70 -> -0.62843208 | L70: =$CE$3-$CE$7*SUMPRODUCT($B$3:$CD$3,Q72:CS72) -> -2.9180243 | M70: =SUMPRODUCT(L70:L73,J70:J73) -> -0.79771827 | O70: =SUM(Q70:CS70) -> 6.8941248 | P70: v_j | Q70: =SUMPRODUCT(B$3:B$6,$K70:$K73) -> -0.049208213 | R70: =SUMPRODUCT(C$3:C$6,$K70:$K73) -> 0.29434777 | S70: =SUMPRODUCT(D$3:D$6,$K70:$K73) -> 0.72379275 | T70: =SUMPRODUCT(E$3:E$6,$K70:$K73) -> -0.23176331 | U70: =SUMPRODUCT(F$3:F$6,$K70:$K73) -> 0.11179268 | V70: =SUMPRODUCT(G$3:G$6,$K70:$K73) -> 0.54123766 | W70: =SUMPRODUCT(H$3:H$6,$K70:$K73) -> -0.77942859 | X70: =SUMPRODUCT(I$3:I$6,$K70:$K73) -> -0.4358726 | ... CS70: =SUMPRODUCT(CD$3:CD$6,$K70:$K73) -> 0.049208213
H71: =H70 -> 0.65625 | I71: =I66 -> 0 | J71: =J66 -> 1 | K71: =I71+J71*H71 -> 0.65625 | L71: =$CE$4-$CE$7*SUMPRODUCT($B$4:$CD$4,Q72:CS72) -> -1.9958125 | M71: ln(likelihood) | O71: =SUM(Q71:CS71) -> 126.74327 | P71: exp(v_j) | Q71: =EXP(Q70) -> 0.95198289 | R71: =EXP(R70) -> 1.3422506 | S71: =EXP(S70) -> 2.06224 | T71: =EXP(T70) -> 0.79313383 | U71: =EXP(U70) -> 1.118281 | V71: =EXP(V70) -> 1.718132 | W71: =EXP(W70) -> 0.45866802 | X71: =EXP(X70) -> 0.64670011 | ... CS71: =EXP(CS70) -> 1.050439
H72: =H71 -> 0.65625 | I72: =I67 -> 0 | J72: =J67 -> -0.55635838 | K72: =I72+J72*H72 -> -0.36511019 | L72: =$CE$5-$CE$7*SUMPRODUCT($B$5:$CD$5,Q72:CS72) -> 0.95564623 | M72: =SUMPRODUCT($B$7:$CD$7, LN(Q72:CS72)) -> -487.37083 | O72: =SUM(Q72:CS72) -> 1 | P72: P_j | Q72: =Q71/$O71 -> 0.0075111122 | R72: =R71/$O71 -> 0.010590311 | S72: =S71/$O71 -> 0.016271002 | T72: =T71/$O71 -> 0.0062577986 | U72: =U71/$O71 -> 0.0088231984 | V72: =V71/$O71 -> 0.013556002 | W72: =W71/$O71 -> 0.0036188749 | X72: =X71/$O71 -> 0.0051024415 | ... CS72: =CS71/$O71 -> 0.0082879278
H73: =H72 -> 0.65625 | I73: =I68 -> 0 | J73: =J68 -> 0.58895311 | K73: =I73+J73*H73 -> 0.38650048 | L73: =$CE$6-$CE$7*SUMPRODUCT($B$6:$CD$6,Q72:CS72) -> -1.8075386
B74: LineSearch Iteration | D74: low | E74: high | F74: bracket? | H74: alpha | I74: beta_iter | J74: p_k_iter | K74: beta | L74: gradient | M74: derivative | O74: Sum
B75: =1+B70 -> 8 | D75: =IF(F70,IF(M75<0,D70,H75),E70) -> 0.640625 | E75: =IF(F70,IF(M75<0,H75,E70),H75) -> 0.65625 | F75: =OR(F70,M75*M70<=0) -> TRUE | H75: =IF(F70,(D70+E70)/2,2*H70) -> 0.640625 | I75: =I70 -> 0 | J75: =J70 -> -0.95761079 | K75: =I75+J75*H75 -> -0.61346941 | L75: =$CE$3-$CE$7*SUMPRODUCT($B$3:$CD$3,Q77:CS77) -> -3.7626932 | M75: =SUMPRODUCT(L75:L78,J75:J78) -> 1.8720645 | O75: =SUM(Q75:CS75) -> 6.729979 | P75: v_j | Q75: =SUMPRODUCT(B$3:B$6,$K75:$K78) -> -0.048036589 | R75: =SUMPRODUCT(C$3:C$6,$K75:$K78) -> 0.28733949 | S75: =SUMPRODUCT(D$3:D$6,$K75:$K78) -> 0.70655959 | T75: =SUMPRODUCT(E$3:E$6,$K75:$K78) -> -0.22624513 | U75: =SUMPRODUCT(F$3:F$6,$K75:$K78) -> 0.10913095 | V75: =SUMPRODUCT(G$3:G$6,$K75:$K78) -> 0.52835105 | W75: =SUMPRODUCT(H$3:H$6,$K75:$K78) -> -0.76087077 | X75: =SUMPRODUCT(I$3:I$6,$K75:$K78) -> -0.42549469 | ... CS75: =SUMPRODUCT(CD$3:CD$6,$K75:$K78) -> 0.048036589
H76: =H75 -> 0.640625 | I76: =I71 -> 0 | J76: =J71 -> 1 | K76: =I76+J76*H76 -> 0.640625 | L76: =$CE$4-$CE$7*SUMPRODUCT($B$4:$CD$4,Q77:CS77) -> -0.88655821 | M76: ln(likelihood) | O76: =SUM(Q76:CS76) -> 124.41766 | P76: exp(v_j) | Q76: =EXP(Q75) -> 0.95309891 | R76: =EXP(R75) -> 1.3328766 | S76: =EXP(S75) -> 2.0270055 | T76: =EXP(T75) -> 0.79752258 | U76: =EXP(U75) -> 1.1153084 | V76: =EXP(V75) -> 1.6961332 | W76: =EXP(W75) -> 0.46725938 | X76: =EXP(X75) -> 0.65344645 | ... CS76: =EXP(CS75) -> 1.049209
H77: =H76 -> 0.640625 | I77: =I72 -> 0 | J77: =J72 -> -0.55635838 | K77: =I77+J77*H77 -> -0.35641709 | L77: =$CE$5-$CE$7*SUMPRODUCT($B$5:$CD$5,Q77:CS77) -> 0.36194815 | M77: =SUMPRODUCT($B$7:$CD$7, LN(Q77:CS77)) -> -487.37919 | O77: =SUM(Q77:CS77) -> 1 | P77: P_j | Q77: =Q76/$O76 -> 0.0076604791 | R77: =R76/$O76 -> 0.010712921 | S77: =S76/$O76 -> 0.016291943 | T77: =T76/$O76 -> 0.006410043 | U77: =U76/$O76 -> 0.0089642286 | V77: =V76/$O76 -> 0.013632575 | W77: =W76/$O76 -> 0.003755571 | X77: =X76/$O76 -> 0.0052520392 | ... CS77: =CS76/$O76 -> 0.0084329588
H78: =H77 -> 0.640625 | I78: =I73 -> 0 | J78: =J73 -> 0.58895311 | K78: =I78+J78*H78 -> 0.37729809 | L78: =$CE$6-$CE$7*SUMPRODUCT($B$6:$CD$6,Q77:CS77) -> -1.0921072
B79: LineSearch Iteration | D79: low | E79: high | F79: bracket? | H79: alpha | I79: beta_iter | J79: p_k_iter | K79: beta | L79: gradient | M79: derivative | O79: Sum
B80: =1+B75 -> 9 | D80: =IF(F75,IF(M80<0,D75,H80),E75) -> 0.6484375 | E80: =IF(F75,IF(M80<0,H80,E75),H80) -> 0.65625 | F80: =OR(F75,M80*M75<=0) -> TRUE | H80: =IF(F75,(D75+E75)/2,2*H75) -> 0.6484375 | I80: =I75 -> 0 | J80: =J75 -> -0.95761079 | K80: =I80+J80*H80 -> -0.62095075 | L80: =$CE$3-$CE$7*SUMPRODUCT($B$3:$CD$3,Q82:CS82) -> -3.3389954 | M80: =SUMPRODUCT(L80:L83,J80:J83) -> 0.53430341 | O80: =SUM(Q80:CS80) -> 6.8120519 | P80: v_j | Q80: =SUMPRODUCT(B$3:B$6,$K80:$K83) -> -0.048622401 | R80: =SUMPRODUCT(C$3:C$6,$K80:$K83) -> 0.29084363 | S80: =SUMPRODUCT(D$3:D$6,$K80:$K83) -> 0.71517617 | T80: =SUMPRODUCT(E$3:E$6,$K80:$K83) -> -0.22900422 | U80: =SUMPRODUCT(F$3:F$6,$K80:$K83) -> 0.11046181 | V80: =SUMPRODUCT(G$3:G$6,$K80:$K83) -> 0.53479435 | W80: =SUMPRODUCT(H$3:H$6,$K80:$K83) -> -0.77014968 | X80: =SUMPRODUCT(I$3:I$6,$K80:$K83) -> -0.43068365 | ... CS80: =SUMPRODUCT(CD$3:CD$6,$K80:$K83) -> 0.048622401
H81: =H80 -> 0.6484375 | I81: =I76 -> 0 | J81: =J76 -> 1 | K81: =I81+J81*H81 -> 0.6484375 | L81: =$CE$4-$CE$7*SUMPRODUCT($B$4:$CD$4,Q82:CS82) -> -1.4423087 | M81: ln(likelihood) | O81: =SUM(Q81:CS81) -> 125.56963 | P81: exp(v_j) | Q81: =EXP(Q80) -> 0.95254074 | R81: =EXP(R80) -> 1.3375554 | S81: =EXP(S80) -> 2.0445468 | T81: =EXP(T80) -> 0.79532518 | U81: =EXP(U80) -> 1.1167937 | V81: =EXP(V80) -> 1.7070971 | W81: =EXP(W80) -> 0.46294377 | X81: =EXP(X80) -> 0.65006453 | ... CS81: =EXP(CS80) -> 1.0498239
H82: =H81 -> 0.6484375 | I82: =I77 -> 0 | J82: =J77 -> -0.55635838 | K82: =I82+J82*H82 -> -0.36076364 | L82: =$CE$5-$CE$7*SUMPRODUCT($B$5:$CD$5,Q82:CS82) -> 0.65934519 | M82: =SUMPRODUCT($B$7:$CD$7, LN(Q82:CS82)) -> -487.3698 | O82: =SUM(Q82:CS82) -> 1 | P82: P_j | Q82: =Q81/$O81 -> 0.0075857576 | R82: =R81/$O81 -> 0.010651903 | S82: =S81/$O81 -> 0.016282177 | T82: =T81/$O81 -> 0.0063337386 | U82: =U81/$O81 -> 0.0088938204 | V82: =V81/$O81 -> 0.013594825 | W82: =W81/$O81 -> 0.0036867496 | X82: =X81/$O81 -> 0.005176925 | ... CS82: =CS81/$O81 -> 0.0083604921
H83: =H82 -> 0.6484375 | I83: =I78 -> 0 | J83: =J78 -> 0.58895311 | K83: =I83+J83*H83 -> 0.38189929 | L83: =$CE$6-$CE$7*SUMPRODUCT($B$6:$CD$6,Q82:CS82) -> -1.4500538
B84: LineSearch Iteration | D84: low | E84: high | F84: bracket? | H84: alpha | I84: beta_iter | J84: p_k_iter | K84: beta | L84: gradient | M84: derivative | O84: Sum
B85: =1+B80 -> 10 | D85: =IF(F80,IF(M85<0,D80,H85),E80) -> 0.6484375 | E85: =IF(F80,IF(M85<0,H85,E80),H85) -> 0.65234375 | F85: =OR(F80,M85*M80<=0) -> TRUE | H85: =IF(F80,(D80+E80)/2,2*H80) -> 0.65234375 | I85: =I80 -> 0 | J85: =J80 -> -0.95761079 | K85: =I85+J85*H85 -> -0.62469141 | L85: =$CE$3-$CE$7*SUMPRODUCT($B$3:$CD$3,Q87:CS87) -> -3.1281693 | M85: =SUMPRODUCT(L85:L88,J85:J88) -> -0.13242627 | O85: =SUM(Q85:CS85) -> 6.8530884 | P85: v_j | Q85: =SUMPRODUCT(B$3:B$6,$K85:$K88) -> -0.048915307 | R85: =SUMPRODUCT(C$3:C$6,$K85:$K88) -> 0.2925957 | S85: =SUMPRODUCT(D$3:D$6,$K85:$K88) -> 0.71948446 | T85: =SUMPRODUCT(E$3:E$6,$K85:$K88) -> -0.23038376 | U85: =SUMPRODUCT(F$3:F$6,$K85:$K88) -> 0.11112724 | V85: =SUMPRODUCT(G$3:G$6,$K85:$K88) -> 0.538016 | W85: =SUMPRODUCT(H$3:H$6,$K85:$K88) -> -0.77478913 | X85: =SUMPRODUCT(I$3:I$6,$K85:$K88) -> -0.43327813 | ... CS85: =SUMPRODUCT(CD$3:CD$6,$K85:$K88) -> 0.048915307
H86: =H85 -> 0.65234375 | I86: =I81 -> 0 | J86: =J81 -> 1 | K86: =I86+J86*H86 -> 0.65234375 | L86: =$CE$4-$CE$7*SUMPRODUCT($B$4:$CD$4,Q87:CS87) -> -1.7193428 | M86: ln(likelihood) | O86: =SUM(Q86:CS86) -> 126.15371 | P86: exp(v_j) | Q86: =EXP(Q85) -> 0.95226178 | R86: =EXP(R85) -> 1.339901 | S86: =EXP(S85) -> 2.0533743 | T86: =EXP(T85) -> 0.79422875 | U86: =EXP(U85) -> 1.1175371 | V86: =EXP(V85) -> 1.7126057 | W86: =EXP(W85) -> 0.46080094 | X86: =EXP(X85) -> 0.64838014 | ... CS86: =EXP(CS85) -> 1.0501314
H87: =H86 -> 0.65234375 | I87: =I82 -> 0 | J87: =J82 -> -0.55635838 | K87: =I87+J87*H87 -> -0.36293691 | L87: =$CE$5-$CE$7*SUMPRODUCT($B$5:$CD$5,Q87:CS87) -> 0.80763277 | M87: =SUMPRODUCT($B$7:$CD$7, LN(Q87:CS87)) -> -487.36901 | O87: =SUM(Q87:CS87) -> 1 | P87: P_j | Q87: =Q86/$O86 -> 0.0075484244 | R87: =R86/$O86 -> 0.010621177 | S87: =S86/$O86 -> 0.016276765 | T87: =T86/$O86 -> 0.0062957223 | U87: =U86/$O86 -> 0.0088585351 | V87: =V86/$O86 -> 0.013575547 | W87: =W86/$O86 -> 0.0036526942 | X87: =X86/$O86 -> 0.005139604 | ... CS87: =CS86/$O86 -> 0.0083242211
H88: =H87 -> 0.65234375 | I88: =I83 -> 0 | J88: =J83 -> 0.58895311 | K88: =I88+J88*H88 -> 0.38419988 | L88: =$CE$6-$CE$7*SUMPRODUCT($B$6:$CD$6,Q87:CS87) -> -1.6288544
A90: BFGS Iteration | C90: =1+C32 -> 2
B91: beta | D91: gradient | F91: NormGradient | H91: inv(B_k) | M91: p_k_unnorm | N91: p_k | P91: grad_k+1 | R91: s_k | T91: y_k | V91: Binv*y | X91: Inv(B_k+1) | AC91: Sum
B92: =K85 -> -0.62469141 | D92: =$CE$3-$CE$7*SUMPRODUCT($B$3:$CD$3,AE94:DG94) -> -3.1281693 | F92: =SUMPRODUCT(D92:D95,D92:D95) -> 16.04702 | H92: =X34 -> 0.68765892 | I92: =Y34 -> 0.36366429 | J92: =Z34 -> -0.20120758 | K92: =AA34 -> 0.21881568 | M92: {=MMULT(H92:K95,D92:D95)} -> -3.2952978 | N92: =IFERROR(M92/(MAX(ABS(M92),ABS(M93),ABS(M94),ABS(M95))),0) -> -1 | P92: =L143 -> -0.18644899 | R92: =H143*J143 -> -0.053512573 | T92: =P92-D92 -> 2.9417203 | V92: {=MMULT(H92:K95,T92:T95)} -> 3.2513883 | X92: {=H92:K95+MMULT(R92:R95,TRANSPOSE(R92:R95))*((SUMPRODUCT(R92:R95,T92:T95)+SUMPRODUCT(V92:V95,T92:T95))/SUMPRODUCT(R92:R95,T92:T95)^2)-(MMULT(V92:V95,TRANSPOSE(R92:R95))+MMULT(R92:R95,TRANSPOSE(V92:V95)))/SUMPRODUCT(R92:R95,T92:T95)} -> 0.012524212 | Y92: 0.064938591 | Z92: -0.077298457 | AA92: -0.13853275 | AC92: =SUM(AE92:DG92) -> 6.8530884 | AD92: v_j | AE92: =SUMPRODUCT(B$3:B$6,$B92:$B95) -> -0.048915307 | AF92: =SUMPRODUCT(C$3:C$6,$B92:$B95) -> 0.2925957 | AG92: =SUMPRODUCT(D$3:D$6,$B92:$B95) -> 0.71948446 | AH92: =SUMPRODUCT(E$3:E$6,$B92:$B95) -> -0.23038376 | AI92: =SUMPRODUCT(F$3:F$6,$B92:$B95) -> 0.11112724 | AJ92: =SUMPRODUCT(G$3:G$6,$B92:$B95) -> 0.538016 | AK92: =SUMPRODUCT(H$3:H$6,$B92:$B95) -> -0.77478913 | AL92: =SUMPRODUCT(I$3:I$6,$B92:$B95) -> -0.43327813 | ... DG92: =SUMPRODUCT(CD$3:CD$6,$B92:$B95) -> 0.048915307
B93: =K86 -> 0.65234375 | D93: =$CE$4-$CE$7*SUMPRODUCT($B$4:$CD$4,AE94:DG94) -> -1.7193428 | F93: LogLikelihood | H93: =X35 -> 0.36366429 | I93: =Y35 -> 0.58108082 | J93: =Z35 -> 0.23189952 | K93: =AA35 -> -0.25156337 | M93: -1.5396308 | N93: =IFERROR(M93/(MAX(ABS(M92),ABS(M93),ABS(M94),ABS(M95))),0) -> -0.46722054 | P93: =L144 -> 0.063466499 | R93: =H144*J144 -> -0.025002173 | T93: =P93-D93 -> 1.7828093 | V93: 1.438331 | X93: 0.064938591 | Y93: 0.44931781 | Z93: 0.286203 | AA93: -0.41080366 | AC93: =SUM(AE93:DG93) -> 126.15371 | AD93: exp(v_j) | AE93: =EXP(AE92) -> 0.95226178 | AF93: =EXP(AF92) -> 1.339901 | AG93: =EXP(AG92) -> 2.0533743 | AH93: =EXP(AH92) -> 0.79422875 | AI93: =EXP(AI92) -> 1.1175371 | AJ93: =EXP(AJ92) -> 1.7126057 | AK93: =EXP(AK92) -> 0.46080094 | AL93: =EXP(AL92) -> 0.64838014 | ... DG93: =EXP(DG92) -> 1.0501314
B94: =K87 -> -0.36293691 | D94: =$CE$5-$CE$7*SUMPRODUCT($B$5:$CD$5,AE94:DG94) -> 0.80763277 | F94: =SUMPRODUCT($B$7:$CD$7, LN(AE94:DG94)) -> -487.36901 | H94: =X36 -> -0.20120758 | I94: =Y36 -> 0.23189952 | J94: =Z36 -> 0.87163151 | K94: =AA36 -> 0.13927051 | M94: 0.7078034 | N94: =IFERROR(M94/(MAX(ABS(M92),ABS(M93),ABS(M94),ABS(M95))),0) -> 0.21479194 | P94: =L145 -> 0.020259973 | R94: =H145*J145 -> 0.011494069 | T94: =P94-D94 -> -0.7873728 | V94: -0.59634976 | X94: -0.077298457 | Y94: 0.286203 | Z94: 0.84954988 | AA94: 0.20627621 | AC94: =SUM(AE94:DG94) -> 1 | AD94: P_j | AE94: =AE93/$AC93 -> 0.0075484244 | AF94: =AF93/$AC93 -> 0.010621177 | AG94: =AG93/$AC93 -> 0.016276765 | AH94: =AH93/$AC93 -> 0.0062957223 | AI94: =AI93/$AC93 -> 0.0088585351 | AJ94: =AJ93/$AC93 -> 0.013575547 | AK94: =AK93/$AC93 -> 0.0036526942 | AL94: =AL93/$AC93 -> 0.005139604 | ... DG94: =DG93/$AC93 -> 0.0083242211
B95: =K88 -> 0.38419988 | D95: =$CE$6-$CE$7*SUMPRODUCT($B$6:$CD$6,AE94:DG94) -> -1.6288544 | H95: =X37 -> 0.21881568 | I95: =Y37 -> -0.25156337 | J95: =Z37 -> 0.13927051 | K95: =AA37 -> 0.84899066 | M95: -1.5223716 | N95: =IFERROR(M95/(MAX(ABS(M92),ABS(M93),ABS(M94),ABS(M95))),0) -> -0.461983 | P95: =L146 -> 0.29842361 | R95: =H146*J146 -> -0.024721899 | T95: =P95-D95 -> 1.927278 | V95: 1.7217882 | X95: -0.13853275 | Y95: -0.41080366 | Z95: 0.20627621 | AA95: 0.6629057
B97: LineSearch Iteration | D97: low | E97: high | F97: bracket? | H97: alpha | I97: beta_iter | J97: p_k_iter | K97: beta | L97: gradient | M97: derivative
B98: 1 | D98: 0 | F98: FALSE | H98: 0 | I98: =B92 -> -0.62469141 | J98: =IF(SUMPRODUCT(L98:L101,N92:N95)>0,N92,-N92) -> -1 | K98: =I98+J98*H98 -> -0.62469141 | L98: =D92 -> -3.1281693 | M98: =SUMPRODUCT(L98:L101,J98:J101) -> 4.8574576
H99: =H98 -> 0 | I99: =B93 -> 0.65234375 | J99: =IF(SUMPRODUCT(L98:L101,N92:N95)>0,N93,-N93) -> -0.46722054 | K99: =I99+J99*H99 -> 0.65234375 | L99: =D93 -> -1.7193428 | M99: ln(likelihood)
H100: =H99 -> 0 | I100: =B94 -> -0.36293691 | J100: =IF(SUMPRODUCT(L98:L101,N92:N95)>0,N94,-N94) -> 0.21479194 | K100: =I100+J100*H100 -> -0.36293691 | L100: =D94 -> 0.80763277 | M100: =F94 -> -487.36901
H101: =H100 -> 0 | I101: =B95 -> 0.38419988 | J101: =IF(SUMPRODUCT(L98:L101,N92:N95)>0,N95,-N95) -> -0.461983 | K101: =I101+J101*H101 -> 0.38419988 | L101: =D95 -> -1.6288544
B102: LineSearch Iteration | D102: low | E102: high | F102: bracket? | H102: alpha | I102: beta_iter | J102: p_k_iter | K102: beta | L102: gradient | M102: derivative | O102: Sum
B103: =1+B98 -> 2 | D103: 0 | E103: =H103 -> 0.65234375 | F103: =OR(F98,M103*M98<=0) -> TRUE | H103: =ABS(H85) -> 0.65234375 | I103: =I98 -> -0.62469141 | J103: =J98 -> -1 | K103: =I103+J103*H103 -> -1.2770352 | L103: =$CE$3-$CE$7*SUMPRODUCT($B$3:$CD$3,Q105:CS105) -> 24.234094 | M103: =SUMPRODUCT(L103:L106,J103:J106) -> -46.564473 | O103: =SUM(Q103:CS103) -> 12.912314 | P103: v_j | Q103: =SUMPRODUCT(B$3:B$6,$K103:$K106) -> 1.0694704 | R103: =SUMPRODUCT(C$3:C$6,$K103:$K106) -> 1.1430954 | S103: =SUMPRODUCT(D$3:D$6,$K103:$K106) -> 1.2351267 | T103: =SUMPRODUCT(E$3:E$6,$K103:$K106) -> 0.95806102 | U103: =SUMPRODUCT(F$3:F$6,$K103:$K106) -> 1.031686 | V103: =SUMPRODUCT(G$3:G$6,$K103:$K106) -> 1.1237173 | W103: =SUMPRODUCT(H$3:H$6,$K103:$K106) -> 0.62383291 | X103: =SUMPRODUCT(I$3:I$6,$K103:$K106) -> 0.69745795 | ... CS103: =SUMPRODUCT(CD$3:CD$6,$K103:$K106) -> -1.0694704
H104: =H103 -> 0.65234375 | I104: =I99 -> 0.65234375 | J104: =J99 -> -0.46722054 | K104: =I104+J104*H104 -> 0.34755535 | L104: =$CE$4-$CE$7*SUMPRODUCT($B$4:$CD$4,Q105:CS105) -> 21.333106 | M104: ln(likelihood) | O104: =SUM(Q104:CS104) -> 157.47372 | P104: exp(v_j) | Q104: =EXP(Q103) -> 2.9138359 | R104: =EXP(R103) -> 3.136462 | S104: =EXP(S103) -> 3.4388142 | T104: =EXP(T103) -> 2.6066373 | U104: =EXP(U103) -> 2.8057926 | V104: =EXP(V103) -> 3.0762685 | W104: =EXP(W103) -> 1.8660668 | X104: =EXP(X103) -> 2.0086401 | ... CS104: =EXP(CS103) -> 0.34319023
H105: =H104 -> 0.65234375 | I105: =I100 -> -0.36293691 | J105: =J100 -> 0.21479194 | K105: =I105+J105*H105 -> -0.22281874 | L105: =$CE$5-$CE$7*SUMPRODUCT($B$5:$CD$5,Q105:CS105) -> -9.3047793 | M105: =SUMPRODUCT($B$7:$CD$7, LN(Q105:CS105)) -> -501.81745 | O105: =SUM(Q105:CS105) -> 1 | P105: P_j | Q105: =Q104/$O104 -> 0.018503633 | R105: =R104/$O104 -> 0.019917368 | S105: =S104/$O104 -> 0.021837385 | T105: =T104/$O104 -> 0.01655284 | U105: =U104/$O104 -> 0.017817529 | V105: =V104/$O104 -> 0.019535123 | W105: =W104/$O104 -> 0.011850021 | X105: =X104/$O104 -> 0.012755399 | ... CS105: =CS104/$O104 -> 0.0021793492
H106: =H105 -> 0.65234375 | I106: =I101 -> 0.38419988 | J106: =J101 -> -0.461983 | K106: =I106+J106*H106 -> 0.082828161 | L106: =$CE$6-$CE$7*SUMPRODUCT($B$6:$CD$6,Q105:CS105) -> 22.434855
B107: LineSearch Iteration | D107: low | E107: high | F107: bracket? | H107: alpha | I107: beta_iter | J107: p_k_iter | K107: beta | L107: gradient | M107: derivative | O107: Sum
B108: =1+B103 -> 3 | D108: =IF(F103,IF(M108<0,D103,H108),E103) -> 0 | E108: =IF(F103,IF(M108<0,H108,E103),H108) -> 0.32617188 | F108: =OR(F103,M108*M103<=0) -> TRUE | H108: =IF(F103,(D103+E103)/2,2*H103) -> 0.32617188 | I108: =I103 -> -0.62469141 | J108: =J103 -> -1 | K108: =I108+J108*H108 -> -0.95086329 | L108: =$CE$3-$CE$7*SUMPRODUCT($B$3:$CD$3,Q110:CS110) -> 12.73581 | M108: =SUMPRODUCT(L108:L111,J108:J111) -> -22.798402 | O108: =SUM(Q108:CS108) -> 9.8827013 | P108: v_j | Q108: =SUMPRODUCT(B$3:B$6,$K108:$K111) -> 0.51027754 | R108: =SUMPRODUCT(C$3:C$6,$K108:$K111) -> 0.71784556 | S108: =SUMPRODUCT(D$3:D$6,$K108:$K111) -> 0.97730558 | T108: =SUMPRODUCT(E$3:E$6,$K108:$K111) -> 0.36383863 | U108: =SUMPRODUCT(F$3:F$6,$K108:$K111) -> 0.57140665 | V108: =SUMPRODUCT(G$3:G$6,$K108:$K111) -> 0.83086667 | W108: =SUMPRODUCT(H$3:H$6,$K108:$K111) -> -0.075478109 | X108: =SUMPRODUCT(I$3:I$6,$K108:$K111) -> 0.13208991 | ... CS108: =SUMPRODUCT(CD$3:CD$6,$K108:$K111) -> -0.51027754
...

Sheet PredictionSolver
A1: exp(v) competition
A2: competitor 1 | B2: competitor 2 | C2: competitor 3 | D2: competitor 4 | E2: Total exp_vc
A3: =IF(ISBLANK(DemandPredictionModel!C12),0,EXP(SUMPRODUCT(DemandPredictionModel!C12:C15,MaxLikelihoodSolver!$K$12:$K$15))) -> 0.38960146 | B3: =IF(ISBLANK(DemandPredictionModel!D12),0,EXP(SUMPRODUCT(DemandPredictionModel!D12:D15,MaxLikelihoodSolver!$K$12:$K$15))) -> 0.37106846 | C3: =IF(ISBLANK(DemandPredictionModel!E12),0,EXP(SUMPRODUCT(DemandPredictionModel!E12:E15,MaxLikelihoodSolver!$K$12:$K$15))) -> 0.9970298 | D3: =IF(ISBLANK(DemandPredictionModel!F12),0,EXP(SUMPRODUCT(DemandPredictionModel!F12:F15,MaxLikelihoodSolver!$K$12:$K$15))) -> 0.6216273 | E3: =SUM(A3:D3) -> 2.379327
A6: Solving for max profit using Haley's algorithm and the Lambeth function
A7: =SUMPRODUCT(DemandPredictionModel!$C$6:$C$8,DemandPredictionModel!$C$24:$C$26) -> 0.86221078 | C7: beta1*xin1+..+beta3+xin3
A8: =EXP($A$7+marginalCost*DemandPredictionModel!$C$5-1)/PredictionSolver!$E$3 -> 0.28650117 | C8: argument for Lambeth function
A9: 1 | C9: initial guess for W_1
A10: =A9 - (A9*EXP(A9)-$A$8)/((EXP(A9)*(A9+1) - (A9+2)*(A9*EXP(A9)-$A$8)/(2*A9+2))) -> 0.32688524 | C10: guess 1
A11: =A10 - (A10*EXP(A10)-$A$8)/((EXP(A10)*(A10+1) - (A10+2)*(A10*EXP(A10)-$A$8)/(2*A10+2))) -> 0.2284185 | C11: guess 2
A12: =A11 - (A11*EXP(A11)-$A$8)/((EXP(A11)*(A11+1) - (A11+2)*(A11*EXP(A11)-$A$8)/(2*A11+2))) -> 0.22807372 | C12: guess 3
A13: =A12 - (A12*EXP(A12)-$A$8)/((EXP(A12)*(A12+1) - (A12+2)*(A12*EXP(A12)-$A$8)/(2*A12+2))) -> 0.22807372 | C13: guess 4
A14: =A13 - (A13*EXP(A13)-$A$8)/((EXP(A13)*(A13+1) - (A13+2)*(A13*EXP(A13)-$A$8)/(2*A13+2))) -> 0.22807372 | C14: guess 5
A15: =A14 - (A14*EXP(A14)-$A$8)/((EXP(A14)*(A14+1) - (A14+2)*(A14*EXP(A14)-$A$8)/(2*A14+2))) -> 0.22807372 | C15: guess 6
A16: =A15 - (A15*EXP(A15)-$A$8)/((EXP(A15)*(A15+1) - (A15+2)*(A15*EXP(A15)-$A$8)/(2*A15+2))) -> 0.22807372 | C16: guess 7
A17: =A16 - (A16*EXP(A16)-$A$8)/((EXP(A16)*(A16+1) - (A16+2)*(A16*EXP(A16)-$A$8)/(2*A16+2))) -> 0.22807372 | C17: guess 8
A18: =A17 - (A17*EXP(A17)-$A$8)/((EXP(A17)*(A17+1) - (A17+2)*(A17*EXP(A17)-$A$8)/(2*A17+2))) -> 0.22807372 | C18: guess 9
A19: =A18 - (A18*EXP(A18)-$A$8)/((EXP(A18)*(A18+1) - (A18+2)*(A18*EXP(A18)-$A$8)/(2*A18+2))) -> 0.22807372 | C19: guess 10
A20: =A19 - (A19*EXP(A19)-$A$8)/((EXP(A19)*(A19+1) - (A19+2)*(A19*EXP(A19)-$A$8)/(2*A19+2))) -> 0.22807372 | C20: guess 11
A21: =A20 - (A20*EXP(A20)-$A$8)/((EXP(A20)*(A20+1) - (A20+2)*(A20*EXP(A20)-$A$8)/(2*A20+2))) -> 0.22807372 | C21: guess 12
... A131: =A130 - (A130*EXP(A130)-$A$8)/((EXP(A130)*(A130+1) - (A130+2)*(A130*EXP(A130)-$A$8)/(2*A130+2))) -> 0.22807372 | C131: guess 122 — should have definitely converged at this point
A132: =-(A131-DemandPredictionModel!$C$5*marginalCost+1)/DemandPredictionModel!$C$5 -> 162.11497 | C132: price assuming capacity constraint is NOT active
A133: =EXP($A$7+$A$132*DemandPredictionModel!$C$5)/(EXP($A$7+$A$132*DemandPredictionModel!$C$5)+PredictionSolver!$E$3)*marketSize -> 3714.3327 | C133: demand
A134: =($A$132-marginalCost)*$A$133 -> 501861.95 | C134: profit
A136: Solving for price to meet capacity constraint
A137: =IFERROR(MAX((-$A$7+LN($E$3*capacity/(marketSize-capacity)))/DemandPredictionModel!$C$5,0),0) -> 0 | C137: price assuming capacity constraint is active (cap at min of zero)
A138: =EXP($A$7+A137*DemandPredictionModel!$C$5)/(EXP($A$7+$A$137*DemandPredictionModel!C5)+$E$3)*marketSize -> 9976.9655 | C138: demand
A139: =($A$137-marginalCost)*$A$138 -> -269378.07 | C139: profit

Sheet StaticRandomNumbers
A1: Random numbers (These numbers are static -- to replace them, paste here by value from the table on the next tab "RandomNumbersToCopyFrom")
B2: Student ID
A3: Option | B3: 1 | C3: 2 | D3: 3 | E3: 4 | F3: 5 | G3: 6 | H3: 7 | I3: 8 | J3: 9 | K3: 10 | L3: 11 | M3: 12 | N3: 13 | O3: 14 | P3: 15 | Q3: 16 | R3: 17 | S3: 18 | T3: 19 | U3: 20 | V3: 21 | W3: 22 | X3: 23 | Y3: 24 | Z3: 25 | AA3: 26 | AB3: 27 | AC3: 28 | AD3: 29 | AE3: 30 | AF3: 31 | AG3: 32 | AH3: 33 | AI3: 34 | AJ3: 35 | AK3: 36 | AL3: 37 | AM3: 38 | AN3: 39 | AO3: 40 | AP3: 41 | AQ3: 42 | AR3: 43 | AS3: 44 | AT3: 45 | AU3: 46 | AV3: 47 | AW3: 48 | AX3: 49 | AY3: 50 | AZ3: 51 | BA3: 52 | BB3: 53 | BC3: 54 | BD3: 55 | BE3: 56 | BF3: 57 | BG3: 58 | BH3: 59 | BI3: 60 | BJ3: Validity test
A4: 1 | B4: 11 | C4: 81 | D4: 37 | E4: 73 | F4: 46 | G4: 45 | H4: 69 | I4: 74 | J4: 55 | K4: 63 | L4: 6 | M4: 44 | N4: 71 | O4: 19 | P4: 72 | Q4: 73 | R4: 58 | S4: 3 | T4: 41 | U4: 7 | V4: 19 | W4: 73 | X4: 35 | Y4: 73 | Z4: 18 | AA4: 48 | AB4: 19 | AC4: 16 | AD4: 55 | AE4: 64 | AF4: 21 | AG4: 29 | AH4: 56 | AI4: 30 | AJ4: 7 | AK4: 36 | AL4: 23 | AM4: 66 | AN4: 41 | AO4: 56 | AP4: 24 | AQ4: 79 | AR4: 3 | AS4: 81 | AT4: 46 | AU4: 48 | AV4: 52 | AW4: 53 | AX4: 13 | AY4: 2 | AZ4: 65 | BA4: 58 | BB4: 62 | BC4: 75 | BD4: 63 | BE4: 13 | BF4: 60 | BG4: 17 | BH4: 18 | BI4: 1 | BJ4: =OR(B96:BI96) -> FALSE
A5: 2 | B5: 36 | C5: 50 | D5: 49 | E5: 26 | F5: 67 | G5: 10 | H5: 37 | I5: 45 | J5: 7 | K5: 62 | L5: 59 | M5: 24 | N5: 61 | O5: 20 | P5: 43 | Q5: 56 | R5: 8 | S5: 64 | T5: 27 | U5: 33 | V5: 38 | W5: 31 | X5: 49 | Y5: 60 | Z5: 53 | AA5: 65 | AB5: 41 | AC5: 29 | AD5: 81 | AE5: 10 | AF5: 73 | AG5: 36 | AH5: 2 | AI5: 18 | AJ5: 17 | AK5: 44 | AL5: 53 | AM5: 18 | AN5: 46 | AO5: 49 | AP5: 41 | AQ5: 52 | AR5: 70 | AS5: 19 | AT5: 59 | AU5: 14 | AV5: 40 | AW5: 29 | AX5: 52 | AY5: 29 | AZ5: 64 | BA5: 12 | BB5: 57 | BC5: 71 | BD5: 78 | BE5: 57 | BF5: 67 | BG5: 32 | BH5: 71 | BI5: 16 | BJ5: =OR(B96:BI96) -> FALSE
A6: 3 | B6: 7 | C6: 21 | D6: 75 | E6: 60 | F6: 11 | G6: 58 | H6: 51 | I6: 38 | J6: 21 | K6: 7 | L6: 71 | M6: 73 | N6: 75 | O6: 39 | P6: 39 | Q6: 15 | R6: 29 | S6: 13 | T6: 20 | U6: 18 | V6: 20 | W6: 11 | X6: 13 | Y6: 44 | Z6: 16 | AA6: 66 | AB6: 81 | AC6: 19 | AD6: 21 | AE6: 5 | AF6: 19 | AG6: 2 | AH6: 36 | AI6: 17 | AJ6: 61 | AK6: 52 | AL6: 18 | AM6: 75 | AN6: 66 | AO6: 30 | AP6: 65 | AQ6: 13 | AR6: 54 | AS6: 79 | AT6: 78 | AU6: 24 | AV6: 61 | AW6: 76 | AX6: 16 | AY6: 74 | AZ6: 6 | BA6: 43 | BB6: 27 | BC6: 10 | BD6: 75 | BE6: 38 | BF6: 71 | BG6: 68 | BH6: 43 | BI6: 20 | BJ6: =OR(B96:BI96) -> FALSE
A7: 4 | B7: 5 | C7: 21 | D7: 8 | E7: 5 | F7: 52 | G7: 80 | H7: 12 | I7: 48 | J7: 66 | K7: 29 | L7: 12 | M7: 15 | N7: 64 | O7: 53 | P7: 75 | Q7: 70 | R7: 30 | S7: 50 | T7: 36 | U7: 74 | V7: 39 | W7: 8 | X7: 57 | Y7: 62 | Z7: 80 | AA7: 45 | AB7: 3 | AC7: 35 | AD7: 77 | AE7: 67 | AF7: 15 | AG7: 14 | AH7: 65 | AI7: 26 | AJ7: 18 | AK7: 67 | AL7: 31 | AM7: 47 | AN7: 33 | AO7: 78 | AP7: 19 | AQ7: 1 | AR7: 81 | AS7: 6 | AT7: 6 | AU7: 6 | AV7: 27 | AW7: 4 | AX7: 21 | AY7: 60 | AZ7: 9 | BA7: 71 | BB7: 21 | BC7: 58 | BD7: 63 | BE7: 65 | BF7: 78 | BG7: 52 | BH7: 12 | BI7: 68 | BJ7: =OR(B99:BI99) -> FALSE
A8: 5 | B8: 1 | C8: 14 | D8: 60 | E8: 70 | F8: 39 | G8: 61 | H8: 8 | I8: 60 | J8: 8 | K8: 45 | L8: 17 | M8: 19 | N8: 1 | O8: 10 | P8: 70 | Q8: 2 | R8: 81 | S8: 28 | T8: 24 | U8: 6 | V8: 52 | W8: 45 | X8: 10 | Y8: 65 | Z8: 43 | AA8: 6 | AB8: 23 | AC8: 67 | AD8: 35 | AE8: 45 | AF8: 39 | AG8: 70 | AH8: 66 | AI8: 73 | AJ8: 10 | AK8: 61 | AL8: 41 | AM8: 1 | AN8: 78 | AO8: 10 | AP8: 34 | AQ8: 62 | AR8: 28 | AS8: 68 | AT8: 27 | AU8: 67 | AV8: 78 | AW8: 3 | AX8: 26 | AY8: 13 | AZ8: 33 | BA8: 46 | BB8: 49 | BC8: 6 | BD8: 45 | BE8: 43 | BF8: 19 | BG8: 80 | BH8: 28 | BI8: 7 | BJ8: =OR(B99:BI99) -> FALSE
A9: 6 | B9: 25 | C9: 64 | D9: 14 | E9: 59 | F9: 47 | G9: 78 | H9: 63 | I9: 35 | J9: 71 | K9: 68 | L9: 53 | M9: 3 | N9: 69 | O9: 73 | P9: 57 | Q9: 39 | R9: 44 | S9: 51 | T9: 10 | U9: 9 | V9: 28 | W9: 50 | X9: 22 | Y9: 69 | Z9: 73 | AA9: 33 | AB9: 22 | AC9: 76 | AD9: 15 | AE9: 13 | AF9: 40 | AG9: 24 | AH9: 61 | AI9: 3 | AJ9: 40 | AK9: 13 | AL9: 6 | AM9: 70 | AN9: 11 | AO9: 22 | AP9: 3 | AQ9: 76 | AR9: 7 | AS9: 42 | AT9: 49 | AU9: 68 | AV9: 64 | AW9: 36 | AX9: 8 | AY9: 28 | AZ9: 67 | BA9: 30 | BB9: 58 | BC9: 44 | BD9: 77 | BE9: 16 | BF9: 76 | BG9: 43 | BH9: 72 | BI9: 36 | BJ9: =OR(B99:BI99) -> FALSE
A10: 7 | B10: 11 | C10: 42 | D10: 65 | E10: 3 | F10: 77 | G10: 19 | H10: 58 | I10: 54 | J10: 1 | K10: 76 | L10: 11 | M10: 48 | N10: 40 | O10: 32 | P10: 17 | Q10: 46 | R10: 45 | S10: 61 | T10: 27 | U10: 44 | V10: 68 | W10: 34 | X10: 75 | Y10: 38 | Z10: 80 | AA10: 19 | AB10: 30 | AC10: 69 | AD10: 72 | AE10: 43 | AF10: 68 | AG10: 31 | AH10: 56 | AI10: 22 | AJ10: 15 | AK10: 60 | AL10: 44 | AM10: 80 | AN10: 9 | AO10: 3 | AP10: 18 | AQ10: 28 | AR10: 41 | AS10: 61 | AT10: 70 | AU10: 23 | AV10: 21 | AW10: 55 | AX10: 41 | AY10: 6 | AZ10: 80 | BA10: 35 | BB10: 26 | BC10: 74 | BD10: 21 | BE10: 70 | BF10: 5 | BG10: 41 | BH10: 23 | BI10: 37 | BJ10: =OR(B102:BI102) -> FALSE
A11: 8 | B11: 79 | C11: 50 | D11: 53 | E11: 30 | F11: 1 | G11: 62 | H11: 32 | I11: 65 | J11: 17 | K11: 64 | L11: 53 | M11: 61 | N11: 14 | O11: 76 | P11: 8 | Q11: 66 | R11: 19 | S11: 77 | T11: 53 | U11: 37 | V11: 55 | W11: 67 | X11: 25 | Y11: 51 | Z11: 72 | AA11: 23 | AB11: 50 | AC11: 2 | AD11: 14 | AE11: 41 | AF11: 22 | AG11: 69 | AH11: 58 | AI11: 37 | AJ11: 42 | AK11: 10 | AL11: 37 | AM11: 15 | AN11: 29 | AO11: 17 | AP11: 43 | AQ11: 29 | AR11: 57 | AS11: 76 | AT11: 40 | AU11: 15 | AV11: 5 | AW11: 12 | AX11: 53 | AY11: 70 | AZ11: 78 | BA11: 40 | BB11: 66 | BC11: 66 | BD11: 58 | BE11: 39 | BF11: 52 | BG11: 44 | BH11: 74 | BI11: 69 | BJ11: =OR(B102:BI102) -> FALSE
A12: 9 | B12: 54 | C12: 39 | D12: 64 | E12: 54 | F12: 62 | G12: 51 | H12: 15 | I12: 17 | J12: 26 | K12: 21 | L12: 71 | M12: 29 | N12: 53 | O12: 33 | P12: 16 | Q12: 27 | R12: 70 | S12: 73 | T12: 73 | U12: 66 | V12: 69 | W12: 32 | X12: 18 | Y12: 32 | Z12: 14 | AA12: 72 | AB12: 75 | AC12: 73 | AD12: 45 | AE12: 25 | AF12: 43 | AG12: 41 | AH12: 66 | AI12: 32 | AJ12: 21 | AK12: 54 | AL12: 36 | AM12: 62 | AN12: 25 | AO12: 28 | AP12: 7 | AQ12: 54 | AR12: 4 | AS12: 78 | AT12: 41 | AU12: 58 | AV12: 48 | AW12: 66 | AX12: 5 | AY12: 8 | AZ12: 27 | BA12: 75 | BB12: 53 | BC12: 78 | BD12: 78 | BE12: 26 | BF12: 80 | BG12: 55 | BH12: 64 | BI12: 79 | BJ12: =OR(B102:BI102) -> FALSE
A13: 10 | B13: 54 | C13: 29 | D13: 40 | E13: 73 | F13: 45 | G13: 42 | H13: 55 | I13: 60 | J13: 26 | K13: 55 | L13: 64 | M13: 80 | N13: 60 | O13: 15 | P13: 1 | Q13: 28 | R13: 29 | S13: 23 | T13: 17 | U13: 12 | V13: 79 | W13: 49 | X13: 7 | Y13: 80 | Z13: 45 | AA13: 17 | AB13: 58 | AC13: 43 | AD13: 9 | AE13: 51 | AF13: 63 | AG13: 61 | AH13: 59 | AI13: 3 | AJ13: 60 | AK13: 10 | AL13: 62 | AM13: 21 | AN13: 63 | AO13: 4 | AP13: 28 | AQ13: 13 | AR13: 77 | AS13: 1 | AT13: 33 | AU13: 7 | AV13: 16 | AW13: 65 | AX13: 1 | AY13: 58 | AZ13: 28 | BA13: 81 | BB13: 59 | BC13: 23 | BD13: 42 | BE13: 49 | BF13: 76 | BG13: 71 | BH13: 29 | BI13: 81 | BJ13: =OR(B105:BI105) -> FALSE
A14: 11 | B14: 53 | C14: 32 | D14: 72 | E14: 21 | F14: 43 | G14: 70 | H14: 71 | I14: 55 | J14: 37 | K14: 9 | L14: 65 | M14: 2 | N14: 23 | O14: 36 | P14: 15 | Q14: 43 | R14: 38 | S14: 78 | T14: 63 | U14: 81 | V14: 3 | W14: 74 | X14: 53 | Y14: 46 | Z14: 27 | AA14: 4 | AB14: 36 | AC14: 47 | AD14: 26 | AE14: 27 | AF14: 65 | AG14: 1 | AH14: 43 | AI14: 19 | AJ14: 55 | AK14: 63 | AL14: 59 | AM14: 61 | AN14: 8 | AO14: 66 | AP14: 80 | AQ14: 46 | AR14: 13 | AS14: 12 | AT14: 52 | AU14: 4 | AV14: 23 | AW14: 54 | AX14: 8 | AY14: 59 | AZ14: 54 | BA14: 50 | BB14: 81 | BC14: 31 | BD14: 26 | BE14: 78 | BF14: 40 | BG14: 3 | BH14: 45 | BI14: 52 | BJ14: =OR(B105:BI105) -> FALSE
A15: 12 | B15: 13 | C15: 2 | D15: 58 | E15: 9 | F15: 2 | G15: 65 | H15: 62 | I15: 66 | J15: 5 | K15: 44 | L15: 8 | M15: 16 | N15: 34 | O15: 73 | P15: 3 | Q15: 12 | R15: 11 | S15: 18 | T15: 14 | U15: 42 | V15: 17 | W15: 18 | X15: 46 | Y15: 74 | Z15: 8 | AA15: 72 | AB15: 27 | AC15: 8 | AD15: 54 | AE15: 46 | AF15: 9 | AG15: 42 | AH15: 74 | AI15: 64 | AJ15: 51 | AK15: 38 | AL15: 11 | AM15: 30 | AN15: 14 | AO15: 30 | AP15: 66 | AQ15: 28 | AR15: 50 | AS15: 2 | AT15: 54 | AU15: 57 | AV15: 29 | AW15: 20 | AX15: 21 | AY15: 76 | AZ15: 76 | BA15: 28 | BB15: 56 | BC15: 37 | BD15: 41 | BE15: 67 | BF15: 26 | BG15: 16 | BH15: 34 | BI15: 4 | BJ15: =OR(B105:BI105) -> FALSE
A16: 13 | B16: 49 | C16: 22 | D16: 3 | E16: 68 | F16: 13 | G16: 67 | H16: 76 | I16: 9 | J16: 39 | K16: 76 | L16: 80 | M16: 22 | N16: 61 | O16: 5 | P16: 24 | Q16: 19 | R16: 65 | S16: 78 | T16: 3 | U16: 76 | V16: 35 | W16: 79 | X16: 22 | Y16: 8 | Z16: 45 | AA16: 62 | AB16: 59 | AC16: 52 | AD16: 43 | AE16: 26 | AF16: 75 | AG16: 8 | AH16: 2 | AI16: 46 | AJ16: 12 | AK16: 6 | AL16: 60 | AM16: 75 | AN16: 22 | AO16: 32 | AP16: 70 | AQ16: 6 | AR16: 60 | AS16: 22 | AT16: 10 | AU16: 42 | AV16: 38 | AW16: 18 | AX16: 80 | AY16: 58 | AZ16: 36 | BA16: 45 | BB16: 63 | BC16: 43 | BD16: 56 | BE16: 51 | BF16: 74 | BG16: 75 | BH16: 7 | BI16: 80 | BJ16: =OR(B108:BI108) -> FALSE
A17: 14 | B17: 1 | C17: 14 | D17: 9 | E17: 27 | F17: 73 | G17: 55 | H17: 40 | I17: 41 | J17: 20 | K17: 73 | L17: 42 | M17: 66 | N17: 59 | O17: 21 | P17: 74 | Q17: 73 | R17: 11 | S17: 50 | T17: 57 | U17: 71 | V17: 30 | W17: 42 | X17: 77 | Y17: 70 | Z17: 52 | AA17: 50 | AB17: 13 | AC17: 70 | AD17: 26 | AE17: 9 | AF17: 74 | AG17: 69 | AH17: 15 | AI17: 69 | AJ17: 45 | AK17: 75 | AL17: 69 | AM17: 45 | AN17: 29 | AO17: 36 | AP17: 7 | AQ17: 72 | AR17: 45 | AS17: 4 | AT17: 69 | AU17: 17 | AV17: 26 | AW17: 15 | AX17: 37 | AY17: 29 | AZ17: 17 | BA17: 15 | BB17: 49 | BC17: 21 | BD17: 37 | BE17: 76 | BF17: 68 | BG17: 4 | BH17: 58 | BI17: 63 | BJ17: =OR(B108:BI108) -> FALSE
A18: 15 | B18: 71 | C18: 25 | D18: 80 | E18: 81 | F18: 2 | G18: 40 | H18: 57 | I18: 56 | J18: 8 | K18: 77 | L18: 43 | M18: 20 | N18: 21 | O18: 59 | P18: 59 | Q18: 34 | R18: 34 | S18: 27 | T18: 31 | U18: 42 | V18: 74 | W18: 59 | X18: 64 | Y18: 5 | Z18: 31 | AA18: 71 | AB18: 54 | AC18: 81 | AD18: 7 | AE18: 49 | AF18: 38 | AG18: 36 | AH18: 78 | AI18: 67 | AJ18: 16 | AK18: 14 | AL18: 46 | AM18: 60 | AN18: 73 | AO18: 28 | AP18: 76 | AQ18: 54 | AR18: 34 | AS18: 77 | AT18: 42 | AU18: 18 | AV18: 42 | AW18: 34 | AX18: 3 | AY18: 50 | AZ18: 42 | BA18: 71 | BB18: 55 | BC18: 35 | BD18: 50 | BE18: 54 | BF18: 77 | BG18: 62 | BH18: 34 | BI18: 24 | BJ18: =OR(B108:BI108) -> FALSE
A19: 16 | B19: 34 | C19: 70 | D19: 51 | E19: 36 | F19: 75 | G19: 39 | H19: 2 | I19: 72 | J19: 50 | K19: 49 | L19: 78 | M19: 42 | N19: 63 | O19: 31 | P19: 81 | Q19: 74 | R19: 41 | S19: 42 | T19: 72 | U19: 11 | V19: 45 | W19: 42 | X19: 66 | Y19: 81 | Z19: 60 | AA19: 50 | AB19: 37 | AC19: 52 | AD19: 33 | AE19: 77 | AF19: 3 | AG19: 35 | AH19: 45 | AI19: 51 | AJ19: 8 | AK19: 61 | AL19: 81 | AM19: 45 | AN19: 24 | AO19: 12 | AP19: 46 | AQ19: 67 | AR19: 28 | AS19: 13 | AT19: 39 | AU19: 18 | AV19: 27 | AW19: 70 | AX19: 21 | AY19: 61 | AZ19: 23 | BA19: 58 | BB19: 81 | BC19: 54 | BD19: 52 | BE19: 32 | BF19: 44 | BG19: 80 | BH19: 26 | BI19: 55 | BJ19: =OR(B111:BI111) -> FALSE
A20: 17 | B20: 46 | C20: 42 | D20: 44 | E20: 34 | F20: 17 | G20: 79 | H20: 70 | I20: 2 | J20: 15 | K20: 52 | L20: 8 | M20: 74 | N20: 49 | O20: 36 | P20: 13 | Q20: 78 | R20: 4 | S20: 75 | T20: 16 | U20: 41 | V20: 31 | W20: 2 | X20: 8 | Y20: 54 | Z20: 3 | AA20: 37 | AB20: 1 | AC20: 27 | AD20: 24 | AE20: 68 | AF20: 19 | AG20: 13 | AH20: 8 | AI20: 59 | AJ20: 41 | AK20: 6 | AL20: 1 | AM20: 70 | AN20: 40 | AO20: 32 | AP20: 23 | AQ20: 53 | AR20: 70 | AS20: 20 | AT20: 6 | AU20: 44 | AV20: 78 | AW20: 43 | AX20: 2 | AY20: 20 | AZ20: 20 | BA20: 56 | BB20: 24 | BC20: 40 | BD20: 72 | BE20: 79 | BF20: 17 | BG20: 44 | BH20: 43 | BI20: 59 | BJ20: =OR(B111:BI111) -> FALSE
A21: 18 | B21: 62 | C21: 3 | D21: 56 | E21: 53 | F21: 40 | G21: 14 | H21: 53 | I21: 47 | J21: 54 | K21: 26 | L21: 61 | M21: 17 | N21: 46 | O21: 53 | P21: 26 | Q21: 4 | R21: 78 | S21: 63 | T21: 58 | U21: 72 | V21: 42 | W21: 7 | X21: 19 | Y21: 34 | Z21: 26 | AA21: 61 | AB21: 17 | AC21: 74 | AD21: 52 | AE21: 74 | AF21: 46 | AG21: 63 | AH21: 68 | AI21: 33 | AJ21: 15 | AK21: 23 | AL21: 6 | AM21: 18 | AN21: 67 | AO21: 15 | AP21: 8 | AQ21: 33 | AR21: 78 | AS21: 63 | AT21: 13 | AU21: 3 | AV21: 3 | AW21: 4 | AX21: 36 | AY21: 53 | AZ21: 4 | BA21: 65 | BB21: 74 | BC21: 60 | BD21: 63 | BE21: 48 | BF21: 51 | BG21: 58 | BH21: 79 | BI21: 46 | BJ21: =OR(B111:BI111) -> FALSE
A22: 19 | B22: 58 | C22: 56 | D22: 25 | E22: 32 | F22: 39 | G22: 65 | H22: 64 | I22: 2 | J22: 34 | K22: 77 | L22: 27 | M22: 30 | N22: 38 | O22: 65 | P22: 9 | Q22: 64 | R22: 13 | S22: 5 | T22: 60 | U22: 73 | V22: 38 | W22: 46 | X22: 16 | Y22: 59 | Z22: 21 | AA22: 53 | AB22: 23 | AC22: 10 | AD22: 54 | AE22: 34 | AF22: 51 | AG22: 72 | AH22: 49 | AI22: 53 | AJ22: 50 | AK22: 71 | AL22: 48 | AM22: 28 | AN22: 14 | AO22: 53 | AP22: 63 | AQ22: 30 | AR22: 70 | AS22: 30 | AT22: 14 | AU22: 53 | AV22: 51 | AW22: 73 | AX22: 20 | AY22: 11 | AZ22: 4 | BA22: 46 | BB22: 39 | BC22: 46 | BD22: 26 | BE22: 16 | BF22: 40 | BG22: 18 | BH22: 6 | BI22: 5 | BJ22: =OR(B114:BI114) -> FALSE
A23: 20 | B23: 3 | C23: 13 | D23: 61 | E23: 41 | F23: 38 | G23: 75 | H23: 62 | I23: 76 | J23: 28 | K23: 13 | L23: 65 | M23: 67 | N23: 44 | O23: 3 | P23: 34 | Q23: 55 | R23: 68 | S23: 23 | T23: 17 | U23: 40 | V23: 5 | W23: 54 | X23: 24 | Y23: 71 | Z23: 25 | AA23: 47 | AB23: 69 | AC23: 77 | AD23: 30 | AE23: 24 | AF23: 61 | AG23: 35 | AH23: 28 | AI23: 78 | AJ23: 43 | AK23: 26 | AL23: 55 | AM23: 24 | AN23: 31 | AO23: 14 | AP23: 17 | AQ23: 10 | AR23: 72 | AS23: 34 | AT23: 71 | AU23: 66 | AV23: 34 | AW23: 69 | AX23: 81 | AY23: 14 | AZ23: 26 | BA23: 37 | BB23: 67 | BC23: 70 | BD23: 50 | BE23: 70 | BF23: 24 | BG23: 58 | BH23: 35 | BI23: 79 | BJ23: =OR(B114:BI114) -> FALSE
A24: 21 | B24: 43 | C24: 55 | D24: 50 | E24: 64 | F24: 5 | G24: 58 | H24: 49 | I24: 68 | J24: 52 | K24: 31 | L24: 18 | M24: 14 | N24: 37 | O24: 40 | P24: 53 | Q24: 17 | R24: 51 | S24: 52 | T24: 80 | U24: 28 | V24: 35 | W24: 65 | X24: 18 | Y24: 23 | Z24: 1 | AA24: 16 | AB24: 35 | AC24: 31 | AD24: 56 | AE24: 28 | AF24: 54 | AG24: 23 | AH24: 55 | AI24: 2 | AJ24: 59 | AK24: 39 | AL24: 30 | AM24: 43 | AN24: 57 | AO24: 7 | AP24: 12 | AQ24: 29 | AR24: 43 | AS24: 42 | AT24: 38 | AU24: 34 | AV24: 3 | AW24: 18 | AX24: 52 | AY24: 39 | AZ24: 62 | BA24: 81 | BB24: 76 | BC24: 6 | BD24: 23 | BE24: 63 | BF24: 72 | BG24: 32 | BH24: 37 | BI24: 15 | BJ24: =OR(B114:BI114) -> FALSE
A25: 22 | B25: 6 | C25: 46 | D25: 47 | E25: 70 | F25: 24 | G25: 19 | H25: 12 | I25: 67 | J25: 23 | K25: 44 | L25: 15 | M25: 17 | N25: 14 | O25: 21 | P25: 59 | Q25: 61 | R25: 33 | S25: 17 | T25: 45 | U25: 43 | V25: 3 | W25: 39 | X25: 66 | Y25: 39 | Z25: 35 | AA25: 31 | AB25: 27 | AC25: 37 | AD25: 77 | AE25: 29 | AF25: 6 | AG25: 28 | AH25: 68 | AI25: 15 | AJ25: 12 | AK25: 57 | AL25: 4 | AM25: 60 | AN25: 6 | AO25: 9 | AP25: 44 | AQ25: 63 | AR25: 25 | AS25: 23 | AT25: 17 | AU25: 62 | AV25: 72 | AW25: 6 | AX25: 79 | AY25: 20 | AZ25: 16 | BA25: 54 | BB25: 45 | BC25: 38 | BD25: 70 | BE25: 28 | BF25: 21 | BG25: 25 | BH25: 49 | BI25: 62 | BJ25: =OR(B117:BI117) -> FALSE
A26: 23 | B26: 64 | C26: 64 | D26: 75 | E26: 47 | F26: 28 | G26: 11 | H26: 8 | I26: 77 | J26: 58 | K26: 55 | L26: 8 | M26: 73 | N26: 43 | O26: 34 | P26: 55 | Q26: 35 | R26: 61 | S26: 23 | T26: 60 | U26: 18 | V26: 71 | W26: 2 | X26: 13 | Y26: 77 | Z26: 60 | AA26: 67 | AB26: 4 | AC26: 74 | AD26: 37 | AE26: 47 | AF26: 50 | AG26: 49 | AH26: 52 | AI26: 13 | AJ26: 18 | AK26: 43 | AL26: 27 | AM26: 12 | AN26: 66 | AO26: 15 | AP26: 33 | AQ26: 61 | AR26: 38 | AS26: 56 | AT26: 74 | AU26: 24 | AV26: 41 | AW26: 43 | AX26: 56 | AY26: 30 | AZ26: 9 | BA26: 34 | BB26: 81 | BC26: 70 | BD26: 13 | BE26: 22 | BF26: 8 | BG26: 80 | BH26: 15 | BI26: 61 | BJ26: =OR(B117:BI117) -> FALSE
A27: 24 | B27: 35 | C27: 32 | D27: 10 | E27: 24 | F27: 60 | G27: 78 | H27: 65 | I27: 4 | J27: 77 | K27: 28 | L27: 76 | M27: 11 | N27: 64 | O27: 47 | P27: 56 | Q27: 66 | R27: 32 | S27: 75 | T27: 1 | U27: 38 | V27: 1 | W27: 44 | X27: 41 | Y27: 19 | Z27: 41 | AA27: 54 | AB27: 80 | AC27: 62 | AD27: 48 | AE27: 46 | AF27: 43 | AG27: 75 | AH27: 15 | AI27: 5 | AJ27: 36 | AK27: 15 | AL27: 78 | AM27: 15 | AN27: 39 | AO27: 71 | AP27: 61 | AQ27: 6 | AR27: 16 | AS27: 33 | AT27: 54 | AU27: 38 | AV27: 44 | AW27: 75 | AX27: 69 | AY27: 76 | AZ27: 19 | BA27: 61 | BB27: 28 | BC27: 12 | BD27: 33 | BE27: 68 | BF27: 42 | BG27: 24 | BH27: 43 | BI27: 42 | BJ27: =OR(B117:BI117) -> FALSE
A28: 25 | B28: 27 | C28: 52 | D28: 43 | E28: 28 | F28: 20 | G28: 65 | H28: 3 | I28: 26 | J28: 69 | K28: 73 | L28: 44 | M28: 33 | N28: 39 | O28: 58 | P28: 14 | Q28: 45 | R28: 7 | S28: 31 | T28: 58 | U28: 12 | V28: 55 | W28: 9 | X28: 68 | Y28: 28 | Z28: 62 | AA28: 23 | AB28: 58 | AC28: 16 | AD28: 19 | AE28: 66 | AF28: 63 | AG28: 25 | AH28: 57 | AI28: 66 | AJ28: 69 | AK28: 33 | AL28: 38 | AM28: 22 | AN28: 67 | AO28: 53 | AP28: 18 | AQ28: 42 | AR28: 17 | AS28: 22 | AT28: 33 | AU28: 71 | AV28: 45 | AW28: 36 | AX28: 40 | AY28: 13 | AZ28: 15 | BA28: 56 | BB28: 61 | BC28: 70 | BD28: 28 | BE28: 45 | BF28: 4 | BG28: 72 | BH28: 2 | BI28: 80 | BJ28: =OR(B120:BI120) -> FALSE
A29: 26 | B29: 18 | C29: 43 | D29: 4 | E29: 68 | F29: 10 | G29: 15 | H29: 80 | I29: 62 | J29: 71 | K29: 61 | L29: 68 | M29: 5 | N29: 8 | O29: 45 | P29: 11 | Q29: 34 | R29: 80 | S29: 11 | T29: 81 | U29: 16 | V29: 8 | W29: 58 | X29: 64 | Y29: 68 | Z29: 45 | AA29: 38 | AB29: 79 | AC29: 10 | AD29: 8 | AE29: 72 | AF29: 5 | AG29: 13 | AH29: 7 | AI29: 79 | AJ29: 18 | AK29: 42 | AL29: 63 | AM29: 27 | AN29: 26 | AO29: 59 | AP29: 63 | AQ29: 6 | AR29: 70 | AS29: 18 | AT29: 56 | AU29: 57 | AV29: 64 | AW29: 61 | AX29: 22 | AY29: 62 | AZ29: 27 | BA29: 34 | BB29: 63 | BC29: 13 | BD29: 30 | BE29: 18 | BF29: 71 | BG29: 26 | BH29: 10 | BI29: 38 | BJ29: =OR(B120:BI120) -> FALSE
A30: 27 | B30: 64 | C30: 35 | D30: 19 | E30: 20 | F30: 33 | G30: 47 | H30: 20 | I30: 60 | J30: 10 | K30: 68 | L30: 55 | M30: 40 | N30: 19 | O30: 53 | P30: 3 | Q30: 56 | R30: 28 | S30: 50 | T30: 42 | U30: 39 | V30: 24 | W30: 36 | X30: 71 | Y30: 81 | Z30: 36 | AA30: 42 | AB30: 31 | AC30: 67 | AD30: 10 | AE30: 76 | AF30: 36 | AG30: 5 | AH30: 53 | AI30: 64 | AJ30: 53 | AK30: 74 | AL30: 69 | AM30: 55 | AN30: 20 | AO30: 60 | AP30: 7 | AQ30: 33 | AR30: 18 | AS30: 24 | AT30: 48 | AU30: 50 | AV30: 27 | AW30: 48 | AX30: 43 | AY30: 71 | AZ30: 78 | BA30: 68 | BB30: 49 | BC30: 81 | BD30: 59 | BE30: 47 | BF30: 37 | BG30: 48 | BH30: 80 | BI30: 49 | BJ30: =OR(B120:BI120) -> FALSE
A31: 28 | B31: 70 | C31: 48 | D31: 1 | E31: 13 | F31: 6 | G31: 73 | H31: 80 | I31: 3 | J31: 31 | K31: 56 | L31: 39 | M31: 42 | N31: 40 | O31: 4 | P31: 72 | Q31: 58 | R31: 68 | S31: 12 | T31: 31 | U31: 21 | V31: 69 | W31: 47 | X31: 40 | Y31: 52 | Z31: 28 | AA31: 72 | AB31: 70 | AC31: 41 | AD31: 53 | AE31: 65 | AF31: 52 | AG31: 80 | AH31: 30 | AI31: 57 | AJ31: 31 | AK31: 74 | AL31: 49 | AM31: 50 | AN31: 53 | AO31: 6 | AP31: 48 | AQ31: 27 | AR31: 7 | AS31: 4 | AT31: 40 | AU31: 36 | AV31: 59 | AW31: 27 | AX31: 37 | AY31: 65 | AZ31: 78 | BA31: 53 | BB31: 47 | BC31: 39 | BD31: 44 | BE31: 15 | BF31: 67 | BG31: 10 | BH31: 1 | BI31: 47 | BJ31: =OR(B123:BI123) -> FALSE
A32: 29 | B32: 29 | C32: 38 | D32: 22 | E32: 18 | F32: 41 | G32: 60 | H32: 57 | I32: 11 | J32: 17 | K32: 29 | L32: 58 | M32: 37 | N32: 77 | O32: 41 | P32: 81 | Q32: 75 | R32: 38 | S32: 74 | T32: 21 | U32: 10 | V32: 63 | W32: 62 | X32: 33 | Y32: 76 | Z32: 24 | AA32: 69 | AB32: 49 | AC32: 11 | AD32: 62 | AE32: 77 | AF32: 64 | AG32: 39 | AH32: 23 | AI32: 64 | AJ32: 26 | AK32: 36 | AL32: 29 | AM32: 39 | AN32: 70 | AO32: 4 | AP32: 7 | AQ32: 32 | AR32: 11 | AS32: 3 | AT32: 56 | AU32: 43 | AV32: 27 | AW32: 78 | AX32: 79 | AY32: 74 | AZ32: 61 | BA32: 67 | BB32: 70 | BC32: 47 | BD32: 43 | BE32: 57 | BF32: 75 | BG32: 21 | BH32: 40 | BI32: 52 | BJ32: =OR(B123:BI123) -> FALSE
A33: 30 | B33: 64 | C33: 21 | D33: 55 | E33: 52 | F33: 3 | G33: 45 | H33: 61 | I33: 48 | J33: 80 | K33: 22 | L33: 36 | M33: 47 | N33: 4 | O33: 14 | P33: 51 | Q33: 43 | R33: 16 | S33: 67 | T33: 29 | U33: 28 | V33: 76 | W33: 64 | X33: 12 | Y33: 7 | Z33: 70 | AA33: 49 | AB33: 7 | AC33: 30 | AD33: 1 | AE33: 24 | AF33: 65 | AG33: 67 | AH33: 61 | AI33: 51 | AJ33: 69 | AK33: 59 | AL33: 53 | AM33: 9 | AN33: 11 | AO33: 15 | AP33: 67 | AQ33: 17 | AR33: 50 | AS33: 25 | AT33: 57 | AU33: 10 | AV33: 18 | AW33: 66 | AX33: 22 | AY33: 35 | AZ33: 41 | BA33: 27 | BB33: 36 | BC33: 43 | BD33: 33 | BE33: 1 | BF33: 3 | BG33: 29 | BH33: 77 | BI33: 57 | BJ33: =OR(B123:BI123) -> FALSE
A34: 31 | B34: 42 | C34: 42 | D34: 11 | E34: 37 | F34: 9 | G34: 9 | H34: 9 | I34: 75 | J34: 22 | K34: 51 | L34: 22 | M34: 43 | N34: 72 | O34: 79 | P34: 13 | Q34: 6 | R34: 74 | S34: 78 | T34: 80 | U34: 60 | V34: 13 | W34: 8 | X34: 54 | Y34: 17 | Z34: 22 | AA34: 6 | AB34: 35 | AC34: 45 | AD34: 15 | AE34: 35 | AF34: 74 | AG34: 76 | AH34: 11 | AI34: 10 | AJ34: 26 | AK34: 71 | AL34: 31 | AM34: 30 | AN34: 32 | AO34: 65 | AP34: 48 | AQ34: 66 | AR34: 54 | AS34: 54 | AT34: 44 | AU34: 41 | AV34: 58 | AW34: 25 | AX34: 76 | AY34: 60 | AZ34: 61 | BA34: 9 | BB34: 18 | BC34: 59 | BD34: 41 | BE34: 12 | BF34: 73 | BG34: 18 | BH34: 63 | BI34: 38 | BJ34: =OR(B126:BI126) -> FALSE
A35: 32 | B35: 47 | C35: 31 | D35: 49 | E35: 41 | F35: 39 | G35: 43 | H35: 7 | I35: 30 | J35: 31 | K35: 59 | L35: 8 | M35: 10 | N35: 1 | O35: 34 | P35: 12 | Q35: 2 | R35: 1 | S35: 66 | T35: 10 | U35: 7 | V35: 24 | W35: 43 | X35: 71 | Y35: 24 | Z35: 32 | AA35: 56 | AB35: 54 | AC35: 61 | AD35: 77 | AE35: 69 | AF35: 17 | AG35: 25 | AH35: 47 | AI35: 61 | AJ35: 68 | AK35: 12 | AL35: 73 | AM35: 51 | AN35: 57 | AO35: 29 | AP35: 60 | AQ35: 41 | AR35: 44 | AS35: 33 | AT35: 29 | AU35: 13 | AV35: 73 | AW35: 63 | AX35: 32 | AY35: 23 | AZ35: 9 | BA35: 38 | BB35: 5 | BC35: 66 | BD35: 32 | BE35: 2 | BF35: 76 | BG35: 2 | BH35: 71 | BI35: 43 | BJ35: =OR(B126:BI126) -> FALSE
A36: 33 | B36: 32 | C36: 30 | D36: 30 | E36: 22 | F36: 31 | G36: 8 | H36: 33 | I36: 34 | J36: 79 | K36: 2 | L36: 45 | M36: 20 | N36: 75 | O36: 4 | P36: 72 | Q36: 59 | R36: 16 | S36: 74 | T36: 52 | U36: 9 | V36: 11 | W36: 35 | X36: 63 | Y36: 55 | Z36: 4 | AA36: 14 | AB36: 14 | AC36: 24 | AD36: 74 | AE36: 21 | AF36: 23 | AG36: 13 | AH36: 1 | AI36: 51 | AJ36: 51 | AK36: 19 | AL36: 13 | AM36: 24 | AN36: 5 | AO36: 60 | AP36: 6 | AQ36: 12 | AR36: 76 | AS36: 1 | AT36: 7 | AU36: 18 | AV36: 26 | AW36: 67 | AX36: 53 | AY36: 78 | AZ36: 60 | BA36: 10 | BB36: 53 | BC36: 22 | BD36: 69 | BE36: 43 | BF36: 13 | BG36: 77 | BH36: 18 | BI36: 57 | BJ36: =OR(B126:BI126) -> FALSE
A37: 34 | B37: 37 | C37: 19 | D37: 12 | E37: 21 | F37: 74 | G37: 62 | H37: 24 | I37: 28 | J37: 19 | K37: 51 | L37: 21 | M37: 69 | N37: 17 | O37: 18 | P37: 17 | Q37: 61 | R37: 28 | S37: 9 | T37: 30 | U37: 26 | V37: 68 | W37: 43 | X37: 41 | Y37: 22 | Z37: 34 | AA37: 18 | AB37: 29 | AC37: 81 | AD37: 1 | AE37: 2 | AF37: 51 | AG37: 70 | AH37: 15 | AI37: 19 | AJ37: 20 | AK37: 55 | AL37: 66 | AM37: 11 | AN37: 48 | AO37: 15 | AP37: 25 | AQ37: 73 | AR37: 55 | AS37: 52 | AT37: 47 | AU37: 50 | AV37: 15 | AW37: 26 | AX37: 60 | AY37: 49 | AZ37: 51 | BA37: 30 | BB37: 44 | BC37: 43 | BD37: 59 | BE37: 4 | BF37: 72 | BG37: 31 | BH37: 29 | BI37: 10 | BJ37: =OR(B129:BI129) -> FALSE
A38: 35 | B38: 56 | C38: 3 | D38: 28 | E38: 23 | F38: 67 | G38: 16 | H38: 30 | I38: 43 | J38: 80 | K38: 60 | L38: 26 | M38: 13 | N38: 79 | O38: 48 | P38: 3 | Q38: 51 | R38: 59 | S38: 51 | T38: 32 | U38: 1 | V38: 64 | W38: 27 | X38: 74 | Y38: 14 | Z38: 24 | AA38: 21 | AB38: 6 | AC38: 63 | AD38: 53 | AE38: 24 | AF38: 22 | AG38: 64 | AH38: 78 | AI38: 46 | AJ38: 25 | AK38: 49 | AL38: 5 | AM38: 50 | AN38: 25 | AO38: 20 | AP38: 40 | AQ38: 74 | AR38: 62 | AS38: 10 | AT38: 63 | AU38: 8 | AV38: 64 | AW38: 44 | AX38: 62 | AY38: 48 | AZ38: 77 | BA38: 60 | BB38: 54 | BC38: 50 | BD38: 50 | BE38: 45 | BF38: 6 | BG38: 65 | BH38: 3 | BI38: 42 | BJ38: =OR(B129:BI129) -> FALSE
A39: 36 | B39: 69 | C39: 21 | D39: 21 | E39: 76 | F39: 73 | G39: 8 | H39: 52 | I39: 71 | J39: 6 | K39: 34 | L39: 11 | M39: 80 | N39: 45 | O39: 5 | P39: 22 | Q39: 25 | R39: 13 | S39: 4 | T39: 41 | U39: 67 | V39: 61 | W39: 11 | X39: 31 | Y39: 65 | Z39: 38 | AA39: 4 | AB39: 39 | AC39: 15 | AD39: 23 | AE39: 13 | AF39: 8 | AG39: 72 | AH39: 30 | AI39: 55 | AJ39: 64 | AK39: 60 | AL39: 54 | AM39: 78 | AN39: 64 | AO39: 28 | AP39: 9 | AQ39: 29 | AR39: 25 | AS39: 32 | AT39: 60 | AU39: 2 | AV39: 2 | AW39: 9 | AX39: 13 | AY39: 75 | AZ39: 43 | BA39: 54 | BB39: 75 | BC39: 47 | BD39: 34 | BE39: 80 | BF39: 10 | BG39: 32 | BH39: 59 | BI39: 47 | BJ39: =OR(B129:BI129) -> FALSE
A40: 37 | B40: 74 | C40: 59 | D40: 12 | E40: 13 | F40: 10 | G40: 69 | H40: 42 | I40: 10 | J40: 14 | K40: 52 | L40: 68 | M40: 68 | N40: 41 | O40: 35 | P40: 72 | Q40: 67 | R40: 66 | S40: 70 | T40: 44 | U40: 34 | V40: 70 | W40: 15 | X40: 60 | Y40: 60 | Z40: 12 | AA40: 35 | AB40: 45 | AC40: 19 | AD40: 61 | AE40: 1 | AF40: 24 | AG40: 18 | AH40: 1 | AI40: 49 | AJ40: 58 | AK40: 26 | AL40: 19 | AM40: 78 | AN40: 62 | AO40: 31 | AP40: 73 | AQ40: 32 | AR40: 41 | AS40: 71 | AT40: 67 | AU40: 25 | AV40: 24 | AW40: 31 | AX40: 40 | AY40: 59 | AZ40: 2 | BA40: 21 | BB40: 36 | BC40: 25 | BD40: 36 | BE40: 58 | BF40: 34 | BG40: 36 | BH40: 22 | BI40: 37 | BJ40: =OR(B132:BI132) -> FALSE
A41: 38 | B41: 23 | C41: 43 | D41: 73 | E41: 39 | F41: 53 | G41: 31 | H41: 59 | I41: 22 | J41: 16 | K41: 57 | L41: 2 | M41: 70 | N41: 76 | O41: 79 | P41: 24 | Q41: 58 | R41: 65 | S41: 34 | T41: 81 | U41: 43 | V41: 18 | W41: 55 | X41: 42 | Y41: 56 | Z41: 64 | AA41: 18 | AB41: 17 | AC41: 79 | AD41: 41 | AE41: 71 | AF41: 15 | AG41: 45 | AH41: 9 | AI41: 68 | AJ41: 69 | AK41: 70 | AL41: 21 | AM41: 32 | AN41: 77 | AO41: 47 | AP41: 74 | AQ41: 74 | AR41: 47 | AS41: 72 | AT41: 3 | AU41: 18 | AV41: 11 | AW41: 76 | AX41: 12 | AY41: 2 | AZ41: 58 | BA41: 50 | BB41: 13 | BC41: 26 | BD41: 35 | BE41: 11 | BF41: 81 | BG41: 58 | BH41: 46 | BI41: 20 | BJ41: =OR(B132:BI132) -> FALSE
A42: 39 | B42: 64 | C42: 37 | D42: 29 | E42: 49 | F42: 61 | G42: 5 | H42: 41 | I42: 78 | J42: 56 | K42: 53 | L42: 17 | M42: 45 | N42: 22 | O42: 49 | P42: 12 | Q42: 23 | R42: 28 | S42: 17 | T42: 34 | U42: 32 | V42: 20 | W42: 78 | X42: 74 | Y42: 38 | Z42: 24 | AA42: 12 | AB42: 55 | AC42: 80 | AD42: 24 | AE42: 74 | AF42: 62 | AG42: 42 | AH42: 45 | AI42: 57 | AJ42: 45 | AK42: 67 | AL42: 27 | AM42: 2 | AN42: 8 | AO42: 57 | AP42: 60 | AQ42: 31 | AR42: 51 | AS42: 7 | AT42: 58 | AU42: 15 | AV42: 21 | AW42: 27 | AX42: 80 | AY42: 8 | AZ42: 59 | BA42: 17 | BB42: 49 | BC42: 49 | BD42: 4 | BE42: 5 | BF42: 78 | BG42: 43 | BH42: 57 | BI42: 53 | BJ42: =OR(B132:BI132) -> FALSE
A43: 40 | B43: 69 | C43: 32 | D43: 60 | E43: 41 | F43: 5 | G43: 2 | H43: 10 | I43: 62 | J43: 53 | K43: 1 | L43: 72 | M43: 70 | N43: 61 | O43: 16 | P43: 51 | Q43: 76 | R43: 28 | S43: 6 | T43: 18 | U43: 68 | V43: 62 | W43: 49 | X43: 80 | Y43: 74 | Z43: 74 | AA43: 8 | AB43: 24 | AC43: 23 | AD43: 63 | AE43: 39 | AF43: 65 | AG43: 10 | AH43: 10 | AI43: 42 | AJ43: 71 | AK43: 13 | AL43: 42 | AM43: 42 | AN43: 55 | AO43: 13 | AP43: 7 | AQ43: 43 | AR43: 8 | AS43: 44 | AT43: 77 | AU43: 66 | AV43: 16 | AW43: 52 | AX43: 52 | AY43: 69 | AZ43: 54 | BA43: 1 | BB43: 35 | BC43: 59 | BD43: 81 | BE43: 2 | BF43: 13 | BG43: 18 | BH43: 73 | BI43: 71 | BJ43: =OR(B135:BI135) -> FALSE
A44: 41 | B44: 21 | C44: 24 | D44: 52 | E44: 49 | F44: 4 | G44: 17 | H44: 28 | I44: 8 | J44: 69 | K44: 3 | L44: 63 | M44: 52 | N44: 68 | O44: 10 | P44: 74 | Q44: 44 | R44: 79 | S44: 50 | T44: 3 | U44: 23 | V44: 25 | W44: 48 | X44: 3 | Y44: 33 | Z44: 55 | AA44: 54 | AB44: 14 | AC44: 27 | AD44: 6 | AE44: 57 | AF44: 75 | AG44: 17 | AH44: 76 | AI44: 60 | AJ44: 21 | AK44: 25 | AL44: 68 | AM44: 65 | AN44: 77 | AO44: 54 | AP44: 30 | AQ44: 72 | AR44: 46 | AS44: 43 | AT44: 39 | AU44: 76 | AV44: 12 | AW44: 71 | AX44: 76 | AY44: 35 | AZ44: 15 | BA44: 4 | BB44: 16 | BC44: 49 | BD44: 12 | BE44: 10 | BF44: 36 | BG44: 37 | BH44: 58 | BI44: 66 | BJ44: =OR(B135:BI135) -> FALSE
A45: 42 | B45: 16 | C45: 6 | D45: 17 | E45: 47 | F45: 10 | G45: 20 | H45: 48 | I45: 11 | J45: 11 | K45: 26 | L45: 6 | M45: 21 | N45: 33 | O45: 42 | P45: 58 | Q45: 35 | R45: 29 | S45: 5 | T45: 78 | U45: 45 | V45: 57 | W45: 66 | X45: 58 | Y45: 54 | Z45: 68 | AA45: 33 | AB45: 16 | AC45: 51 | AD45: 55 | AE45: 24 | AF45: 51 | AG45: 65 | AH45: 65 | AI45: 37 | AJ45: 81 | AK45: 7 | AL45: 69 | AM45: 56 | AN45: 78 | AO45: 5 | AP45: 55 | AQ45: 41 | AR45: 56 | AS45: 70 | AT45: 55 | AU45: 1 | AV45: 6 | AW45: 58 | AX45: 29 | AY45: 40 | AZ45: 9 | BA45: 24 | BB45: 38 | BC45: 78 | BD45: 45 | BE45: 29 | BF45: 61 | BG45: 28 | BH45: 42 | BI45: 55 | BJ45: =OR(B135:BI135) -> FALSE
A46: 43 | B46: 18 | C46: 14 | D46: 6 | E46: 4 | F46: 9 | G46: 61 | H46: 36 | I46: 53 | J46: 60 | K46: 63 | L46: 80 | M46: 8 | N46: 2 | O46: 18 | P46: 19 | Q46: 80 | R46: 35 | S46: 8 | T46: 27 | U46: 13 | V46: 31 | W46: 1 | X46: 58 | Y46: 9 | Z46: 44 | AA46: 68 | AB46: 10 | AC46: 38 | AD46: 55 | AE46: 9 | AF46: 19 | AG46: 77 | AH46: 16 | AI46: 39 | AJ46: 72 | AK46: 37 | AL46: 28 | AM46: 42 | AN46: 18 | AO46: 12 | AP46: 59 | AQ46: 22 | AR46: 56 | AS46: 49 | AT46: 1 | AU46: 54 | AV46: 19 | AW46: 3 | AX46: 51 | AY46: 39 | AZ46: 54 | BA46: 39 | BB46: 1 | BC46: 79 | BD46: 76 | BE46: 60 | BF46: 80 | BG46: 74 | BH46: 44 | BI46: 14 | BJ46: =OR(B138:BI138) -> FALSE
A47: 44 | B47: 71 | C47: 75 | D47: 70 | E47: 5 | F47: 59 | G47: 49 | H47: 73 | I47: 4 | J47: 34 | K47: 32 | L47: 70 | M47: 75 | N47: 71 | O47: 1 | P47: 42 | Q47: 37 | R47: 4 | S47: 11 | T47: 43 | U47: 15 | V47: 51 | W47: 30 | X47: 33 | Y47: 69 | Z47: 37 | AA47: 51 | AB47: 17 | AC47: 69 | AD47: 25 | AE47: 69 | AF47: 72 | AG47: 57 | AH47: 51 | AI47: 27 | AJ47: 68 | AK47: 1 | AL47: 75 | AM47: 21 | AN47: 57 | AO47: 24 | AP47: 79 | AQ47: 57 | AR47: 77 | AS47: 33 | AT47: 65 | AU47: 70 | AV47: 81 | AW47: 7 | AX47: 66 | AY47: 54 | AZ47: 48 | BA47: 44 | BB47: 45 | BC47: 78 | BD47: 38 | BE47: 63 | BF47: 23 | BG47: 44 | BH47: 70 | BI47: 20 | BJ47: =OR(B138:BI138) -> FALSE
A48: 45 | B48: 13 | C48: 26 | D48: 5 | E48: 35 | F48: 68 | G48: 60 | H48: 37 | I48: 27 | J48: 24 | K48: 81 | L48: 75 | M48: 35 | N48: 12 | O48: 20 | P48: 32 | Q48: 12 | R48: 22 | S48: 10 | T48: 29 | U48: 1 | V48: 19 | W48: 56 | X48: 80 | Y48: 51 | Z48: 78 | AA48: 42 | AB48: 25 | AC48: 29 | AD48: 30 | AE48: 32 | AF48: 58 | AG48: 22 | AH48: 22 | AI48: 37 | AJ48: 46 | AK48: 74 | AL48: 39 | AM48: 44 | AN48: 79 | AO48: 56 | AP48: 78 | AQ48: 54 | AR48: 26 | AS48: 13 | AT48: 9 | AU48: 69 | AV48: 55 | AW48: 78 | AX48: 5 | AY48: 53 | AZ48: 25 | BA48: 18 | BB48: 18 | BC48: 42 | BD48: 64 | BE48: 27 | BF48: 45 | BG48: 23 | BH48: 43 | BI48: 40 | BJ48: =OR(B138:BI138) -> FALSE
A49: 46 | B49: 28 | C49: 78 | D49: 63 | E49: 19 | F49: 20 | G49: 69 | H49: 24 | I49: 37 | J49: 48 | K49: 78 | L49: 32 | M49: 76 | N49: 49 | O49: 6 | P49: 31 | Q49: 56 | R49: 61 | S49: 6 | T49: 16 | U49: 79 | V49: 33 | W49: 80 | X49: 19 | Y49: 8 | Z49: 3 | AA49: 53 | AB49: 55 | AC49: 45 | AD49: 69 | AE49: 17 | AF49: 76 | AG49: 66 | AH49: 78 | AI49: 27 | AJ49: 68 | AK49: 77 | AL49: 2 | AM49: 18 | AN49: 58 | AO49: 78 | AP49: 53 | AQ49: 58 | AR49: 3 | AS49: 6 | AT49: 56 | AU49: 55 | AV49: 67 | AW49: 47 | AX49: 66 | AY49: 56 | AZ49: 26 | BA49: 79 | BB49: 23 | BC49: 2 | BD49: 23 | BE49: 48 | BF49: 40 | BG49: 20 | BH49: 31 | BI49: 3 | BJ49: =OR(B141:BI141) -> FALSE
A50: 47 | B50: 17 | C50: 55 | D50: 50 | E50: 45 | F50: 18 | G50: 76 | H50: 13 | I50: 10 | J50: 34 | K50: 71 | L50: 62 | M50: 56 | N50: 60 | O50: 78 | P50: 13 | Q50: 14 | R50: 64 | S50: 63 | T50: 33 | U50: 21 | V50: 24 | W50: 8 | X50: 31 | Y50: 9 | Z50: 18 | AA50: 7 | AB50: 26 | AC50: 73 | AD50: 41 | AE50: 75 | AF50: 74 | AG50: 58 | AH50: 66 | AI50: 67 | AJ50: 37 | AK50: 59 | AL50: 68 | AM50: 73 | AN50: 31 | AO50: 34 | AP50: 4 | AQ50: 49 | AR50: 80 | AS50: 2 | AT50: 46 | AU50: 66 | AV50: 78 | AW50: 37 | AX50: 76 | AY50: 10 | AZ50: 13 | BA50: 71 | BB50: 17 | BC50: 30 | BD50: 36 | BE50: 11 | BF50: 72 | BG50: 65 | BH50: 33 | BI50: 39 | BJ50: =OR(B141:BI141) -> FALSE
A51: 48 | B51: 54 | C51: 37 | D51: 17 | E51: 66 | F51: 2 | G51: 63 | H51: 57 | I51: 44 | J51: 78 | K51: 30 | L51: 20 | M51: 26 | N51: 40 | O51: 66 | P51: 21 | Q51: 35 | R51: 52 | S51: 29 | T51: 49 | U51: 45 | V51: 55 | W51: 47 | X51: 17 | Y51: 71 | Z51: 33 | AA51: 77 | AB51: 22 | AC51: 12 | AD51: 30 | AE51: 71 | AF51: 57 | AG51: 56 | AH51: 52 | AI51: 58 | AJ51: 1 | AK51: 15 | AL51: 17 | AM51: 5 | AN51: 5 | AO51: 7 | AP51: 10 | AQ51: 73 | AR51: 67 | AS51: 1 | AT51: 7 | AU51: 22 | AV51: 23 | AW51: 20 | AX51: 55 | AY51: 13 | AZ51: 27 | BA51: 13 | BB51: 13 | BC51: 56 | BD51: 15 | BE51: 12 | BF51: 44 | BG51: 80 | BH51: 61 | BI51: 38 | BJ51: =OR(B141:BI141) -> FALSE
A52: 49 | B52: 53 | C52: 25 | D52: 32 | E52: 43 | F52: 70 | G52: 51 | H52: 25 | I52: 66 | J52: 39 | K52: 76 | L52: 17 | M52: 55 | N52: 17 | O52: 38 | P52: 35 | Q52: 29 | R52: 9 | S52: 15 | T52: 74 | U52: 41 | V52: 72 | W52: 1 | X52: 11 | Y52: 75 | Z52: 73 | AA52: 30 | AB52: 77 | AC52: 19 | AD52: 45 | AE52: 66 | AF52: 73 | AG52: 54 | AH52: 72 | AI52: 10 | AJ52: 43 | AK52: 81 | AL52: 46 | AM52: 40 | AN52: 67 | AO52: 41 | AP52: 60 | AQ52: 24 | AR52: 22 | AS52: 22 | AT52: 65 | AU52: 5 | AV52: 51 | AW52: 6 | AX52: 41 | AY52: 53 | AZ52: 54 | BA52: 44 | BB52: 38 | BC52: 50 | BD52: 75 | BE52: 69 | BF52: 4 | BG52: 70 | BH52: 70 | BI52: 70 | BJ52: =OR(B144:BI144) -> FALSE
A53: 50 | B53: 60 | C53: 40 | D53: 22 | E53: 33 | F53: 3 | G53: 2 | H53: 20 | I53: 21 | J53: 35 | K53: 58 | L53: 43 | M53: 38 | N53: 69 | O53: 23 | P53: 56 | Q53: 38 | R53: 45 | S53: 48 | T53: 80 | U53: 2 | V53: 2 | W53: 14 | X53: 21 | Y53: 45 | Z53: 45 | AA53: 43 | AB53: 39 | AC53: 50 | AD53: 33 | AE53: 8 | AF53: 51 | AG53: 31 | AH53: 17 | AI53: 80 | AJ53: 47 | AK53: 79 | AL53: 44 | AM53: 75 | AN53: 68 | AO53: 48 | AP53: 8 | AQ53: 18 | AR53: 66 | AS53: 75 | AT53: 78 | AU53: 50 | AV53: 50 | AW53: 17 | AX53: 72 | AY53: 77 | AZ53: 8 | BA53: 19 | BB53: 25 | BC53: 79 | BD53: 20 | BE53: 75 | BF53: 3 | BG53: 44 | BH53: 25 | BI53: 12 | BJ53: =OR(B144:BI144) -> FALSE
A54: 51 | B54: 75 | C54: 61 | D54: 51 | E54: 52 | F54: 54 | G54: 17 | H54: 27 | I54: 43 | J54: 47 | K54: 53 | L54: 59 | M54: 19 | N54: 13 | O54: 59 | P54: 20 | Q54: 37 | R54: 5 | S54: 68 | T54: 44 | U54: 1 | V54: 42 | W54: 51 | X54: 70 | Y54: 11 | Z54: 52 | AA54: 75 | AB54: 37 | AC54: 60 | AD54: 49 | AE54: 46 | AF54: 60 | AG54: 24 | AH54: 63 | AI54: 43 | AJ54: 79 | AK54: 62 | AL54: 62 | AM54: 31 | AN54: 48 | AO54: 3 | AP54: 44 | AQ54: 45 | AR54: 63 | AS54: 50 | AT54: 22 | AU54: 30 | AV54: 45 | AW54: 37 | AX54: 3 | AY54: 61 | AZ54: 46 | BA54: 66 | BB54: 30 | BC54: 26 | BD54: 39 | BE54: 78 | BF54: 1 | BG54: 29 | BH54: 74 | BI54: 75 | BJ54: =OR(B144:BI144) -> FALSE
A55: 52 | B55: 57 | C55: 10 | D55: 37 | E55: 65 | F55: 47 | G55: 67 | H55: 73 | I55: 46 | J55: 40 | K55: 38 | L55: 75 | M55: 50 | N55: 37 | O55: 31 | P55: 17 | Q55: 23 | R55: 62 | S55: 11 | T55: 74 | U55: 47 | V55: 79 | W55: 67 | X55: 35 | Y55: 11 | Z55: 18 | AA55: 12 | AB55: 75 | AC55: 2 | AD55: 21 | AE55: 56 | AF55: 60 | AG55: 3 | AH55: 54 | AI55: 58 | AJ55: 63 | AK55: 39 | AL55: 47 | AM55: 74 | AN55: 47 | AO55: 46 | AP55: 17 | AQ55: 38 | AR55: 33 | AS55: 29 | AT55: 50 | AU55: 57 | AV55: 56 | AW55: 63 | AX55: 41 | AY55: 42 | AZ55: 34 | BA55: 30 | BB55: 58 | BC55: 57 | BD55: 18 | BE55: 54 | BF55: 39 | BG55: 11 | BH55: 59 | BI55: 81 | BJ55: =OR(B147:BI147) -> FALSE
A56: 53 | B56: 76 | C56: 13 | D56: 38 | E56: 60 | F56: 43 | G56: 23 | H56: 35 | I56: 43 | J56: 33 | K56: 76 | L56: 41 | M56: 36 | N56: 48 | O56: 40 | P56: 78 | Q56: 54 | R56: 20 | S56: 70 | T56: 7 | U56: 58 | V56: 20 | W56: 69 | X56: 54 | Y56: 48 | Z56: 7 | AA56: 9 | AB56: 1 | AC56: 12 | AD56: 36 | AE56: 68 | AF56: 71 | AG56: 5 | AH56: 52 | AI56: 32 | AJ56: 16 | AK56: 35 | AL56: 19 | AM56: 27 | AN56: 25 | AO56: 42 | AP56: 15 | AQ56: 81 | AR56: 43 | AS56: 14 | AT56: 70 | AU56: 78 | AV56: 32 | AW56: 16 | AX56: 53 | AY56: 61 | AZ56: 17 | BA56: 67 | BB56: 16 | BC56: 11 | BD56: 39 | BE56: 43 | BF56: 27 | BG56: 25 | BH56: 27 | BI56: 59 | BJ56: =OR(B147:BI147) -> FALSE
A57: 54 | B57: 50 | C57: 58 | D57: 12 | E57: 70 | F57: 58 | G57: 3 | H57: 50 | I57: 19 | J57: 55 | K57: 44 | L57: 17 | M57: 59 | N57: 51 | O57: 16 | P57: 12 | Q57: 22 | R57: 47 | S57: 62 | T57: 70 | U57: 78 | V57: 80 | W57: 18 | X57: 16 | Y57: 63 | Z57: 16 | AA57: 63 | AB57: 3 | AC57: 47 | AD57: 56 | AE57: 78 | AF57: 66 | AG57: 11 | AH57: 42 | AI57: 53 | AJ57: 19 | AK57: 22 | AL57: 62 | AM57: 38 | AN57: 59 | AO57: 23 | AP57: 6 | AQ57: 13 | AR57: 22 | AS57: 71 | AT57: 29 | AU57: 27 | AV57: 28 | AW57: 7 | AX57: 69 | AY57: 79 | AZ57: 66 | BA57: 70 | BB57: 77 | BC57: 76 | BD57: 78 | BE57: 57 | BF57: 38 | BG57: 5 | BH57: 70 | BI57: 73 | BJ57: =OR(B147:BI147) -> FALSE
A58: 55 | B58: 1 | C58: 66 | D58: 10 | E58: 35 | F58: 18 | G58: 8 | H58: 59 | I58: 17 | J58: 10 | K58: 54 | L58: 8 | M58: 6 | N58: 22 | O58: 33 | P58: 31 | Q58: 6 | R58: 22 | S58: 42 | T58: 47 | U58: 75 | V58: 21 | W58: 28 | X58: 41 | Y58: 6 | Z58: 18 | AA58: 67 | AB58: 56 | AC58: 51 | AD58: 11 | AE58: 76 | AF58: 7 | AG58: 36 | AH58: 11 | AI58: 74 | AJ58: 12 | AK58: 4 | AL58: 52 | AM58: 46 | AN58: 72 | AO58: 16 | AP58: 5 | AQ58: 42 | AR58: 14 | AS58: 79 | AT58: 39 | AU58: 62 | AV58: 4 | AW58: 53 | AX58: 14 | AY58: 52 | AZ58: 6 | BA58: 5 | BB58: 78 | BC58: 4 | BD58: 28 | BE58: 15 | BF58: 29 | BG58: 7 | BH58: 72 | BI58: 37 | BJ58: =OR(B150:BI150) -> FALSE
A59: 56 | B59: 42 | C59: 60 | D59: 55 | E59: 74 | F59: 44 | G59: 3 | H59: 15 | I59: 77 | J59: 70 | K59: 71 | L59: 75 | M59: 19 | N59: 28 | O59: 23 | P59: 15 | Q59: 45 | R59: 45 | S59: 60 | T59: 7 | U59: 61 | V59: 53 | W59: 18 | X59: 20 | Y59: 30 | Z59: 70 | AA59: 11 | AB59: 37 | AC59: 42 | AD59: 71 | AE59: 2 | AF59: 3 | AG59: 25 | AH59: 79 | AI59: 22 | AJ59: 47 | AK59: 16 | AL59: 49 | AM59: 5 | AN59: 54 | AO59: 29 | AP59: 75 | AQ59: 28 | AR59: 17 | AS59: 45 | AT59: 53 | AU59: 44 | AV59: 21 | AW59: 33 | AX59: 46 | AY59: 77 | AZ59: 1 | BA59: 79 | BB59: 15 | BC59: 57 | BD59: 5 | BE59: 29 | BF59: 15 | BG59: 10 | BH59: 21 | BI59: 35 | BJ59: =OR(B150:BI150) -> FALSE
A60: 57 | B60: 48 | C60: 63 | D60: 4 | E60: 4 | F60: 26 | G60: 23 | H60: 18 | I60: 63 | J60: 31 | K60: 6 | L60: 6 | M60: 17 | N60: 25 | O60: 32 | P60: 25 | Q60: 17 | R60: 21 | S60: 63 | T60: 40 | U60: 6 | V60: 17 | W60: 38 | X60: 18 | Y60: 26 | Z60: 13 | AA60: 70 | AB60: 31 | AC60: 56 | AD60: 9 | AE60: 30 | AF60: 26 | AG60: 81 | AH60: 67 | AI60: 2 | AJ60: 22 | AK60: 43 | AL60: 63 | AM60: 20 | AN60: 73 | AO60: 45 | AP60: 64 | AQ60: 67 | AR60: 33 | AS60: 77 | AT60: 56 | AU60: 54 | AV60: 37 | AW60: 43 | AX60: 16 | AY60: 49 | AZ60: 56 | BA60: 40 | BB60: 38 | BC60: 22 | BD60: 9 | BE60: 34 | BF60: 67 | BG60: 21 | BH60: 56 | BI60: 29 | BJ60: =OR(B150:BI150) -> FALSE
A61: 58 | B61: 36 | C61: 62 | D61: 29 | E61: 50 | F61: 22 | G61: 18 | H61: 14 | I61: 69 | J61: 51 | K61: 69 | L61: 18 | M61: 62 | N61: 63 | O61: 66 | P61: 29 | Q61: 75 | R61: 18 | S61: 78 | T61: 39 | U61: 81 | V61: 15 | W61: 30 | X61: 71 | Y61: 52 | Z61: 70 | AA61: 31 | AB61: 54 | AC61: 9 | AD61: 75 | AE61: 78 | AF61: 28 | AG61: 14 | AH61: 26 | AI61: 60 | AJ61: 75 | AK61: 47 | AL61: 4 | AM61: 56 | AN61: 33 | AO61: 63 | AP61: 74 | AQ61: 74 | AR61: 51 | AS61: 18 | AT61: 32 | AU61: 80 | AV61: 77 | AW61: 63 | AX61: 55 | AY61: 26 | AZ61: 24 | BA61: 75 | BB61: 31 | BC61: 59 | BD61: 57 | BE61: 16 | BF61: 60 | BG61: 9 | BH61: 53 | BI61: 34 | BJ61: =OR(B153:BI153) -> FALSE
A62: 59 | B62: 43 | C62: 38 | D62: 13 | E62: 7 | F62: 3 | G62: 15 | H62: 11 | I62: 35 | J62: 57 | K62: 53 | L62: 11 | M62: 10 | N62: 79 | O62: 67 | P62: 62 | Q62: 13 | R62: 61 | S62: 13 | T62: 40 | U62: 35 | V62: 57 | W62: 27 | X62: 4 | Y62: 46 | Z62: 10 | AA62: 8 | AB62: 55 | AC62: 35 | AD62: 14 | AE62: 48 | AF62: 14 | AG62: 9 | AH62: 11 | AI62: 73 | AJ62: 4 | AK62: 81 | AL62: 75 | AM62: 19 | AN62: 81 | AO62: 80 | AP62: 35 | AQ62: 49 | AR62: 72 | AS62: 54 | AT62: 30 | AU62: 73 | AV62: 39 | AW62: 61 | AX62: 64 | AY62: 60 | AZ62: 65 | BA62: 15 | BB62: 32 | BC62: 66 | BD62: 33 | BE62: 38 | BF62: 59 | BG62: 75 | BH62: 54 | BI62: 51 | BJ62: =OR(B153:BI153) -> FALSE
A63: 60 | B63: 5 | C63: 10 | D63: 16 | E63: 34 | F63: 58 | G63: 68 | H63: 28 | I63: 73 | J63: 11 | K63: 27 | L63: 23 | M63: 14 | N63: 68 | O63: 19 | P63: 46 | Q63: 29 | R63: 19 | S63: 53 | T63: 12 | U63: 67 | V63: 14 | W63: 49 | X63: 7 | Y63: 81 | Z63: 53 | AA63: 51 | AB63: 41 | AC63: 28 | AD63: 16 | AE63: 66 | AF63: 74 | AG63: 62 | AH63: 1 | AI63: 65 | AJ63: 49 | AK63: 3 | AL63: 60 | AM63: 11 | AN63: 27 | AO63: 51 | AP63: 59 | AQ63: 46 | AR63: 52 | AS63: 47 | AT63: 64 | AU63: 26 | AV63: 43 | AW63: 50 | AX63: 63 | AY63: 1 | AZ63: 76 | BA63: 49 | BB63: 4 | BC63: 5 | BD63: 26 | BE63: 74 | BF63: 5 | BG63: 11 | BH63: 12 | BI63: 20 | BJ63: =OR(B153:BI153) -> FALSE
A64: 61 | B64: 39 | C64: 19 | D64: 3 | E64: 81 | F64: 10 | G64: 79 | H64: 69 | I64: 64 | J64: 55 | K64: 48 | L64: 20 | M64: 36 | N64: 60 | O64: 42 | P64: 70 | Q64: 44 | R64: 66 | S64: 1 | T64: 59 | U64: 70 | V64: 74 | W64: 4 | X64: 64 | Y64: 20 | Z64: 49 | AA64: 11 | AB64: 46 | AC64: 45 | AD64: 68 | AE64: 71 | AF64: 72 | AG64: 7 | AH64: 55 | AI64: 26 | AJ64: 10 | AK64: 70 | AL64: 9 | AM64: 44 | AN64: 79 | AO64: 4 | AP64: 62 | AQ64: 7 | AR64: 34 | AS64: 76 | AT64: 67 | AU64: 42 | AV64: 50 | AW64: 58 | AX64: 50 | AY64: 63 | AZ64: 77 | BA64: 46 | BB64: 14 | BC64: 33 | BD64: 67 | BE64: 37 | BF64: 68 | BG64: 70 | BH64: 56 | BI64: 18 | BJ64: =OR(B156:BI156) -> FALSE
A65: 62 | B65: 68 | C65: 7 | D65: 30 | E65: 24 | F65: 22 | G65: 72 | H65: 29 | I65: 33 | J65: 25 | K65: 67 | L65: 36 | M65: 26 | N65: 32 | O65: 21 | P65: 5 | Q65: 62 | R65: 8 | S65: 53 | T65: 80 | U65: 25 | V65: 76 | W65: 2 | X65: 69 | Y65: 3 | Z65: 45 | AA65: 76 | AB65: 70 | AC65: 62 | AD65: 26 | AE65: 14 | AF65: 73 | AG65: 45 | AH65: 60 | AI65: 18 | AJ65: 63 | AK65: 2 | AL65: 34 | AM65: 63 | AN65: 59 | AO65: 28 | AP65: 33 | AQ65: 33 | AR65: 14 | AS65: 34 | AT65: 13 | AU65: 41 | AV65: 70 | AW65: 43 | AX65: 51 | AY65: 53 | AZ65: 21 | BA65: 10 | BB65: 8 | BC65: 52 | BD65: 13 | BE65: 77 | BF65: 28 | BG65: 9 | BH65: 58 | BI65: 47 | BJ65: =OR(B156:BI156) -> FALSE
A66: 63 | B66: 42 | C66: 43 | D66: 56 | E66: 50 | F66: 25 | G66: 62 | H66: 8 | I66: 4 | J66: 57 | K66: 5 | L66: 10 | M66: 44 | N66: 47 | O66: 79 | P66: 17 | Q66: 30 | R66: 3 | S66: 59 | T66: 12 | U66: 67 | V66: 58 | W66: 64 | X66: 12 | Y66: 40 | Z66: 42 | AA66: 27 | AB66: 36 | AC66: 64 | AD66: 13 | AE66: 75 | AF66: 76 | AG66: 41 | AH66: 45 | AI66: 29 | AJ66: 32 | AK66: 47 | AL66: 21 | AM66: 25 | AN66: 31 | AO66: 64 | AP66: 45 | AQ66: 14 | AR66: 76 | AS66: 80 | AT66: 43 | AU66: 38 | AV66: 39 | AW66: 28 | AX66: 46 | AY66: 33 | AZ66: 6 | BA66: 39 | BB66: 25 | BC66: 72 | BD66: 57 | BE66: 76 | BF66: 61 | BG66: 28 | BH66: 49 | BI66: 12 | BJ66: =OR(B156:BI156) -> FALSE
A67: 64 | B67: 49 | C67: 5 | D67: 35 | E67: 52 | F67: 15 | G67: 43 | H67: 75 | I67: 74 | J67: 4 | K67: 61 | L67: 80 | M67: 81 | N67: 1 | O67: 39 | P67: 68 | Q67: 51 | R67: 71 | S67: 24 | T67: 6 | U67: 33 | V67: 63 | W67: 8 | X67: 71 | Y67: 43 | Z67: 58 | AA67: 74 | AB67: 63 | AC67: 53 | AD67: 47 | AE67: 14 | AF67: 37 | AG67: 70 | AH67: 52 | AI67: 12 | AJ67: 52 | AK67: 58 | AL67: 72 | AM67: 75 | AN67: 4 | AO67: 28 | AP67: 17 | AQ67: 38 | AR67: 54 | AS67: 65 | AT67: 48 | AU67: 26 | AV67: 14 | AW67: 45 | AX67: 46 | AY67: 20 | AZ67: 13 | BA67: 47 | BB67: 6 | BC67: 50 | BD67: 60 | BE67: 33 | BF67: 13 | BG67: 36 | BH67: 76 | BI67: 11 | BJ67: =OR(B159:BI159) -> FALSE
A68: 65 | B68: 33 | C68: 3 | D68: 58 | E68: 38 | F68: 29 | G68: 52 | H68: 51 | I68: 34 | J68: 25 | K68: 45 | L68: 16 | M68: 72 | N68: 74 | O68: 48 | P68: 28 | Q68: 12 | R68: 36 | S68: 35 | T68: 51 | U68: 57 | V68: 3 | W68: 55 | X68: 54 | Y68: 30 | Z68: 24 | AA68: 47 | AB68: 69 | AC68: 76 | AD68: 75 | AE68: 65 | AF68: 65 | AG68: 2 | AH68: 12 | AI68: 75 | AJ68: 6 | AK68: 27 | AL68: 3 | AM68: 52 | AN68: 17 | AO68: 68 | AP68: 27 | AQ68: 31 | AR68: 24 | AS68: 75 | AT68: 80 | AU68: 60 | AV68: 30 | AW68: 52 | AX68: 72 | AY68: 46 | AZ68: 42 | BA68: 77 | BB68: 71 | BC68: 42 | BD68: 25 | BE68: 43 | BF68: 57 | BG68: 11 | BH68: 52 | BI68: 68 | BJ68: =OR(B159:BI159) -> FALSE
A69: 66 | B69: 38 | C69: 58 | D69: 48 | E69: 1 | F69: 21 | G69: 24 | H69: 13 | I69: 35 | J69: 39 | K69: 65 | L69: 2 | M69: 71 | N69: 42 | O69: 23 | P69: 66 | Q69: 10 | R69: 1 | S69: 56 | T69: 11 | U69: 34 | V69: 81 | W69: 79 | X69: 48 | Y69: 69 | Z69: 69 | AA69: 9 | AB69: 58 | AC69: 37 | AD69: 80 | AE69: 70 | AF69: 40 | AG69: 72 | AH69: 42 | AI69: 68 | AJ69: 12 | AK69: 78 | AL69: 48 | AM69: 79 | AN69: 41 | AO69: 70 | AP69: 26 | AQ69: 17 | AR69: 75 | AS69: 4 | AT69: 39 | AU69: 79 | AV69: 69 | AW69: 24 | AX69: 61 | AY69: 14 | AZ69: 2 | BA69: 41 | BB69: 68 | BC69: 31 | BD69: 31 | BE69: 23 | BF69: 8 | BG69: 63 | BH69: 68 | BI69: 12 | BJ69: =OR(B159:BI159) -> FALSE
A70: 67 | B70: 61 | C70: 12 | D70: 7 | E70: 59 | F70: 30 | G70: 56 | H70: 80 | I70: 27 | J70: 33 | K70: 75 | L70: 61 | M70: 54 | N70: 6 | O70: 11 | P70: 33 | Q70: 69 | R70: 30 | S70: 33 | T70: 47 | U70: 29 | V70: 66 | W70: 12 | X70: 3 | Y70: 6 | Z70: 59 | AA70: 58 | AB70: 68 | AC70: 29 | AD70: 56 | AE70: 50 | AF70: 26 | AG70: 65 | AH70: 54 | AI70: 44 | AJ70: 36 | AK70: 2 | AL70: 76 | AM70: 49 | AN70: 47 | AO70: 28 | AP70: 41 | AQ70: 24 | AR70: 17 | AS70: 10 | AT70: 23 | AU70: 80 | AV70: 6 | AW70: 37 | AX70: 8 | AY70: 80 | AZ70: 21 | BA70: 70 | BB70: 20 | BC70: 47 | BD70: 56 | BE70: 30 | BF70: 18 | BG70: 5 | BH70: 35 | BI70: 76 | BJ70: =OR(B162:BI162) -> FALSE
A71: 68 | B71: 4 | C71: 3 | D71: 27 | E71: 54 | F71: 80 | G71: 23 | H71: 36 | I71: 28 | J71: 78 | K71: 59 | L71: 11 | M71: 45 | N71: 78 | O71: 17 | P71: 69 | Q71: 62 | R71: 61 | S71: 15 | T71: 70 | U71: 69 | V71: 47 | W71: 77 | X71: 66 | Y71: 9 | Z71: 14 | AA71: 61 | AB71: 41 | AC71: 78 | AD71: 64 | AE71: 51 | AF71: 55 | AG71: 68 | AH71: 20 | AI71: 26 | AJ71: 17 | AK71: 1 | AL71: 56 | AM71: 28 | AN71: 51 | AO71: 39 | AP71: 80 | AQ71: 63 | AR71: 11 | AS71: 6 | AT71: 35 | AU71: 17 | AV71: 3 | AW71: 6 | AX71: 44 | AY71: 42 | AZ71: 37 | BA71: 9 | BB71: 56 | BC71: 76 | BD71: 12 | BE71: 22 | BF71: 25 | BG71: 7 | BH71: 41 | BI71: 73 | BJ71: =OR(B162:BI162) -> FALSE
A72: 69 | B72: 53 | C72: 65 | D72: 37 | E72: 11 | F72: 51 | G72: 11 | H72: 35 | I72: 38 | J72: 72 | K72: 35 | L72: 50 | M72: 24 | N72: 35 | O72: 63 | P72: 44 | Q72: 79 | R72: 54 | S72: 14 | T72: 22 | U72: 67 | V72: 22 | W72: 65 | X72: 9 | Y72: 26 | Z72: 34 | AA72: 33 | AB72: 78 | AC72: 41 | AD72: 7 | AE72: 42 | AF72: 65 | AG72: 1 | AH72: 55 | AI72: 38 | AJ72: 47 | AK72: 63 | AL72: 29 | AM72: 38 | AN72: 6 | AO72: 54 | AP72: 26 | AQ72: 43 | AR72: 33 | AS72: 14 | AT72: 24 | AU72: 51 | AV72: 60 | AW72: 38 | AX72: 72 | AY72: 44 | AZ72: 25 | BA72: 39 | BB72: 18 | BC72: 29 | BD72: 30 | BE72: 3 | BF72: 5 | BG72: 69 | BH72: 33 | BI72: 48 | BJ72: =OR(B162:BI162) -> FALSE
A73: 70 | B73: 29 | C73: 5 | D73: 75 | E73: 41 | F73: 14 | G73: 27 | H73: 57 | I73: 24 | J73: 78 | K73: 23 | L73: 11 | M73: 36 | N73: 79 | O73: 21 | P73: 56 | Q73: 31 | R73: 41 | S73: 45 | T73: 64 | U73: 21 | V73: 11 | W73: 26 | X73: 46 | Y73: 35 | Z73: 26 | AA73: 51 | AB73: 14 | AC73: 18 | AD73: 41 | AE73: 29 | AF73: 65 | AG73: 59 | AH73: 8 | AI73: 9 | AJ73: 48 | AK73: 53 | AL73: 22 | AM73: 60 | AN73: 24 | AO73: 10 | AP73: 81 | AQ73: 5 | AR73: 65 | AS73: 49 | AT73: 11 | AU73: 3 | AV73: 42 | AW73: 9 | AX73: 79 | AY73: 69 | AZ73: 28 | BA73: 54 | BB73: 31 | BC73: 37 | BD73: 17 | BE73: 35 | BF73: 35 | BG73: 56 | BH73: 59 | BI73: 24 | BJ73: =OR(B165:BI165) -> FALSE
A74: 71 | B74: 18 | C74: 44 | D74: 66 | E74: 40 | F74: 47 | G74: 81 | H74: 51 | I74: 30 | J74: 8 | K74: 20 | L74: 6 | M74: 57 | N74: 55 | O74: 80 | P74: 16 | Q74: 13 | R74: 65 | S74: 71 | T74: 73 | U74: 46 | V74: 5 | W74: 14 | X74: 57 | Y74: 53 | Z74: 19 | AA74: 69 | AB74: 6 | AC74: 9 | AD74: 11 | AE74: 35 | AF74: 60 | AG74: 39 | AH74: 4 | AI74: 61 | AJ74: 15 | AK74: 10 | AL74: 64 | AM74: 3 | AN74: 10 | AO74: 67 | AP74: 30 | AQ74: 14 | AR74: 34 | AS74: 32 | AT74: 68 | AU74: 35 | AV74: 1 | AW74: 29 | AX74: 5 | AY74: 21 | AZ74: 69 | BA74: 17 | BB74: 17 | BC74: 26 | BD74: 39 | BE74: 51 | BF74: 33 | BG74: 50 | BH74: 19 | BI74: 35 | BJ74: =OR(B165:BI165) -> FALSE
A75: 72 | B75: 11 | C75: 31 | D75: 12 | E75: 66 | F75: 43 | G75: 39 | H75: 15 | I75: 35 | J75: 46 | K75: 51 | L75: 80 | M75: 48 | N75: 23 | O75: 40 | P75: 66 | Q75: 23 | R75: 25 | S75: 59 | T75: 49 | U75: 6 | V75: 24 | W75: 46 | X75: 75 | Y75: 55 | Z75: 1 | AA75: 16 | AB75: 54 | AC75: 67 | AD75: 2 | AE75: 58 | AF75: 26 | AG75: 52 | AH75: 57 | AI75: 13 | AJ75: 17 | AK75: 38 | AL75: 14 | AM75: 41 | AN75: 68 | AO75: 79 | AP75: 54 | AQ75: 71 | AR75: 81 | AS75: 78 | AT75: 43 | AU75: 29 | AV75: 51 | AW75: 65 | AX75: 54 | AY75: 19 | AZ75: 27 | BA75: 73 | BB75: 63 | BC75: 81 | BD75: 50 | BE75: 53 | BF75: 58 | BG75: 62 | BH75: 75 | BI75: 13 | BJ75: =OR(B165:BI165) -> FALSE
A76: 73 | B76: 31 | C76: 2 | D76: 76 | E76: 74 | F76: 37 | G76: 50 | H76: 56 | I76: 18 | J76: 64 | K76: 44 | L76: 22 | M76: 66 | N76: 11 | O76: 27 | P76: 36 | Q76: 34 | R76: 25 | S76: 8 | T76: 30 | U76: 4 | V76: 35 | W76: 30 | X76: 12 | Y76: 28 | Z76: 61 | AA76: 73 | AB76: 40 | AC76: 26 | AD76: 60 | AE76: 45 | AF76: 45 | AG76: 71 | AH76: 27 | AI76: 64 | AJ76: 25 | AK76: 16 | AL76: 18 | AM76: 8 | AN76: 70 | AO76: 19 | AP76: 70 | AQ76: 61 | AR76: 48 | AS76: 71 | AT76: 11 | AU76: 14 | AV76: 33 | AW76: 51 | AX76: 69 | AY76: 37 | AZ76: 77 | BA76: 54 | BB76: 54 | BC76: 71 | BD76: 14 | BE76: 75 | BF76: 39 | BG76: 59 | BH76: 12 | BI76: 75 | BJ76: =OR(B168:BI168) -> FALSE
A77: 74 | B77: 81 | C77: 17 | D77: 63 | E77: 25 | F77: 51 | G77: 48 | H77: 62 | I77: 51 | J77: 5 | K77: 3 | L77: 4 | M77: 48 | N77: 36 | O77: 72 | P77: 16 | Q77: 31 | R77: 63 | S77: 13 | T77: 36 | U77: 15 | V77: 79 | W77: 26 | X77: 81 | Y77: 53 | Z77: 34 | AA77: 77 | AB77: 62 | AC77: 51 | AD77: 62 | AE77: 47 | AF77: 9 | AG77: 46 | AH77: 8 | AI77: 10 | AJ77: 49 | AK77: 78 | AL77: 27 | AM77: 24 | AN77: 8 | AO77: 35 | AP77: 69 | AQ77: 20 | AR77: 34 | AS77: 4 | AT77: 31 | AU77: 54 | AV77: 50 | AW77: 31 | AX77: 20 | AY77: 64 | AZ77: 3 | BA77: 59 | BB77: 19 | BC77: 37 | BD77: 15 | BE77: 43 | BF77: 5 | BG77: 72 | BH77: 38 | BI77: 72 | BJ77: =OR(B168:BI168) -> FALSE
A78: 75 | B78: 72 | C78: 62 | D78: 5 | E78: 46 | F78: 6 | G78: 51 | H78: 37 | I78: 38 | J78: 37 | K78: 64 | L78: 58 | M78: 27 | N78: 47 | O78: 45 | P78: 50 | Q78: 77 | R78: 61 | S78: 50 | T78: 21 | U78: 26 | V78: 29 | W78: 32 | X78: 35 | Y78: 31 | Z78: 9 | AA78: 33 | AB78: 20 | AC78: 31 | AD78: 57 | AE78: 73 | AF78: 61 | AG78: 80 | AH78: 26 | AI78: 43 | AJ78: 16 | AK78: 23 | AL78: 22 | AM78: 29 | AN78: 11 | AO78: 29 | AP78: 16 | AQ78: 49 | AR78: 61 | AS78: 54 | AT78: 41 | AU78: 20 | AV78: 38 | AW78: 16 | AX78: 57 | AY78: 48 | AZ78: 79 | BA78: 52 | BB78: 14 | BC78: 69 | BD78: 74 | BE78: 13 | BF78: 24 | BG78: 34 | BH78: 76 | BI78: 63 | BJ78: =OR(B168:BI168) -> FALSE
A79: 76 | B79: 49 | C79: 45 | D79: 33 | E79: 54 | F79: 61 | G79: 44 | H79: 22 | I79: 58 | J79: 8 | K79: 37 | L79: 29 | M79: 74 | N79: 27 | O79: 10 | P79: 60 | Q79: 50 | R79: 66 | S79: 32 | T79: 30 | U79: 11 | V79: 2 | W79: 69 | X79: 55 | Y79: 50 | Z79: 64 | AA79: 61 | AB79: 37 | AC79: 50 | AD79: 26 | AE79: 77 | AF79: 66 | AG79: 47 | AH79: 47 | AI79: 38 | AJ79: 56 | AK79: 36 | AL79: 65 | AM79: 33 | AN79: 50 | AO79: 55 | AP79: 62 | AQ79: 53 | AR79: 74 | AS79: 41 | AT79: 33 | AU79: 33 | AV79: 71 | AW79: 5 | AX79: 25 | AY79: 2 | AZ79: 48 | BA79: 53 | BB79: 29 | BC79: 41 | BD79: 44 | BE79: 48 | BF79: 71 | BG79: 4 | BH79: 23 | BI79: 58 | BJ79: =OR(B171:BI171) -> FALSE
A80: 77 | B80: 75 | C80: 27 | D80: 19 | E80: 69 | F80: 13 | G80: 15 | H80: 34 | I80: 81 | J80: 56 | K80: 53 | L80: 53 | M80: 23 | N80: 30 | O80: 24 | P80: 37 | Q80: 52 | R80: 67 | S80: 4 | T80: 18 | U80: 16 | V80: 60 | W80: 67 | X80: 58 | Y80: 13 | Z80: 22 | AA80: 15 | AB80: 75 | AC80: 68 | AD80: 50 | AE80: 12 | AF80: 24 | AG80: 66 | AH80: 51 | AI80: 12 | AJ80: 63 | AK80: 37 | AL80: 13 | AM80: 65 | AN80: 52 | AO80: 14 | AP80: 81 | AQ80: 40 | AR80: 76 | AS80: 78 | AT80: 47 | AU80: 74 | AV80: 27 | AW80: 35 | AX80: 22 | AY80: 71 | AZ80: 32 | BA80: 12 | BB80: 81 | BC80: 35 | BD80: 73 | BE80: 14 | BF80: 37 | BG80: 21 | BH80: 69 | BI80: 30 | BJ80: =OR(B171:BI171) -> FALSE
A81: 78 | B81: 4 | C81: 22 | D81: 61 | E81: 6 | F81: 54 | G81: 47 | H81: 25 | I81: 55 | J81: 61 | K81: 75 | L81: 72 | M81: 61 | N81: 58 | O81: 2 | P81: 10 | Q81: 74 | R81: 23 | S81: 19 | T81: 48 | U81: 4 | V81: 79 | W81: 11 | X81: 69 | Y81: 45 | Z81: 58 | AA81: 4 | AB81: 15 | AC81: 54 | AD81: 21 | AE81: 64 | AF81: 76 | AG81: 1 | AH81: 46 | AI81: 31 | AJ81: 22 | AK81: 66 | AL81: 37 | AM81: 64 | AN81: 15 | AO81: 51 | AP81: 80 | AQ81: 69 | AR81: 39 | AS81: 2 | AT81: 69 | AU81: 37 | AV81: 76 | AW81: 53 | AX81: 41 | AY81: 13 | AZ81: 64 | BA81: 16 | BB81: 40 | BC81: 33 | BD81: 42 | BE81: 27 | BF81: 46 | BG81: 32 | BH81: 27 | BI81: 3 | BJ81: =OR(B171:BI171) -> FALSE
A82: 79 | B82: 69 | C82: 68 | D82: 37 | E82: 68 | F82: 31 | G82: 31 | H82: 49 | I82: 64 | J82: 81 | K82: 55 | L82: 4 | M82: 59 | N82: 34 | O82: 51 | P82: 39 | Q82: 78 | R82: 58 | S82: 32 | T82: 48 | U82: 75 | V82: 72 | W82: 51 | X82: 24 | Y82: 30 | Z82: 14 | AA82: 10 | AB82: 36 | AC82: 25 | AD82: 25 | AE82: 41 | AF82: 55 | AG82: 55 | AH82: 69 | AI82: 6 | AJ82: 51 | AK82: 19 | AL82: 81 | AM82: 81 | AN82: 75 | AO82: 1 | AP82: 48 | AQ82: 69 | AR82: 5 | AS82: 44 | AT82: 17 | AU82: 76 | AV82: 78 | AW82: 53 | AX82: 45 | AY82: 12 | AZ82: 23 | BA82: 9 | BB82: 61 | BC82: 20 | BD82: 39 | BE82: 43 | BF82: 16 | BG82: 14 | BH82: 23 | BI82: 13 | BJ82: =OR(B174:BI174) -> FALSE
A83: 80 | B83: 52 | C83: 72 | D83: 47 | E83: 52 | F83: 81 | G83: 55 | H83: 46 | I83: 19 | J83: 67 | K83: 23 | L83: 49 | M83: 36 | N83: 73 | O83: 52 | P83: 27 | Q83: 60 | R83: 49 | S83: 26 | T83: 23 | U83: 66 | V83: 50 | W83: 21 | X83: 8 | Y83: 6 | Z83: 70 | AA83: 58 | AB83: 62 | AC83: 53 | AD83: 15 | AE83: 64 | AF83: 13 | AG83: 31 | AH83: 19 | AI83: 80 | AJ83: 64 | AK83: 5 | AL83: 29 | AM83: 52 | AN83: 66 | AO83: 71 | AP83: 52 | AQ83: 65 | AR83: 32 | AS83: 71 | AT83: 44 | AU83: 80 | AV83: 63 | AW83: 12 | AX83: 51 | AY83: 18 | AZ83: 58 | BA83: 21 | BB83: 19 | BC83: 16 | BD83: 20 | BE83: 68 | BF83: 64 | BG83: 65 | BH83: 72 | BI83: 8 | BJ83: =OR(B174:BI174) -> FALSE
A84: 81 | B84: 63 | C84: 80 | D84: 23 | E84: 29 | F84: 56 | G84: 3 | H84: 47 | I84: 14 | J84: 48 | K84: 76 | L84: 28 | M84: 22 | N84: 30 | O84: 41 | P84: 21 | Q84: 80 | R84: 2 | S84: 20 | T84: 39 | U84: 47 | V84: 52 | W84: 43 | X84: 27 | Y84: 10 | Z84: 80 | AA84: 42 | AB84: 13 | AC84: 78 | AD84: 56 | AE84: 28 | AF84: 12 | AG84: 20 | AH84: 55 | AI84: 56 | AJ84: 9 | AK84: 34 | AL84: 33 | AM84: 25 | AN84: 32 | AO84: 10 | AP84: 5 | AQ84: 47 | AR84: 81 | AS84: 80 | AT84: 38 | AU84: 25 | AV84: 17 | AW84: 49 | AX84: 74 | AY84: 51 | AZ84: 37 | BA84: 73 | BB84: 16 | BC84: 52 | BD84: 54 | BE84: 72 | BF84: 38 | BG84: 37 | BH84: 22 | BI84: 79 | BJ84: =OR(B174:BI174) -> FALSE
A85: 82 | B85: 40 | C85: 31 | D85: 31 | E85: 7 | F85: 80 | G85: 79 | H85: 3 | I85: 81 | J85: 49 | K85: 46 | L85: 37 | M85: 63 | N85: 41 | O85: 17 | P85: 26 | Q85: 66 | R85: 39 | S85: 45 | T85: 14 | U85: 12 | V85: 48 | W85: 52 | X85: 52 | Y85: 68 | Z85: 37 | AA85: 29 | AB85: 70 | AC85: 28 | AD85: 57 | AE85: 75 | AF85: 13 | AG85: 35 | AH85: 28 | AI85: 6 | AJ85: 67 | AK85: 79 | AL85: 8 | AM85: 28 | AN85: 4 | AO85: 69 | AP85: 59 | AQ85: 4 | AR85: 40 | AS85: 41 | AT85: 22 | AU85: 32 | AV85: 66 | AW85: 10 | AX85: 9 | AY85: 27 | AZ85: 6 | BA85: 63 | BB85: 14 | BC85: 61 | BD85: 73 | BE85: 75 | BF85: 47 | BG85: 10 | BH85: 10 | BI85: 56 | BJ85: =OR(B177:BI177) -> FALSE
A86: 83 | B86: 24 | C86: 59 | D86: 7 | E86: 8 | F86: 14 | G86: 61 | H86: 7 | I86: 54 | J86: 78 | K86: 50 | L86: 50 | M86: 19 | N86: 5 | O86: 79 | P86: 50 | Q86: 2 | R86: 22 | S86: 50 | T86: 6 | U86: 81 | V86: 61 | W86: 68 | X86: 26 | Y86: 19 | Z86: 73 | AA86: 6 | AB86: 71 | AC86: 16 | AD86: 81 | AE86: 58 | AF86: 70 | AG86: 16 | AH86: 36 | AI86: 22 | AJ86: 13 | AK86: 6 | AL86: 67 | AM86: 39 | AN86: 62 | AO86: 29 | AP86: 3 | AQ86: 31 | AR86: 65 | AS86: 81 | AT86: 76 | AU86: 51 | AV86: 67 | AW86: 15 | AX86: 75 | AY86: 73 | AZ86: 69 | BA86: 30 | BB86: 23 | BC86: 40 | BD86: 12 | BE86: 58 | BF86: 30 | BG86: 43 | BH86: 9 | BI86: 6 | BJ86: =OR(B177:BI177) -> FALSE
A87: 84 | B87: 46 | C87: 3 | D87: 25 | E87: 48 | F87: 67 | G87: 56 | H87: 12 | I87: 30 | J87: 81 | K87: 62 | L87: 20 | M87: 16 | N87: 55 | O87: 47 | P87: 39 | Q87: 47 | R87: 37 | S87: 75 | T87: 59 | U87: 43 | V87: 37 | W87: 11 | X87: 66 | Y87: 57 | Z87: 71 | AA87: 32 | AB87: 77 | AC87: 53 | AD87: 38 | AE87: 57 | AF87: 72 | AG87: 31 | AH87: 1 | AI87: 2 | AJ87: 38 | AK87: 30 | AL87: 42 | AM87: 76 | AN87: 48 | AO87: 59 | AP87: 72 | AQ87: 41 | AR87: 42 | AS87: 24 | AT87: 47 | AU87: 41 | AV87: 45 | AW87: 33 | AX87: 41 | AY87: 51 | AZ87: 9 | BA87: 37 | BB87: 50 | BC87: 62 | BD87: 66 | BE87: 51 | BF87: 31 | BG87: 73 | BH87: 63 | BI87: 81 | BJ87: =OR(B177:BI177) -> FALSE
A88: 85 | B88: 38 | C88: 14 | D88: 33 | E88: 56 | F88: 36 | G88: 13 | H88: 66 | I88: 23 | J88: 43 | K88: 77 | L88: 22 | M88: 18 | N88: 17 | O88: 28 | P88: 74 | Q88: 39 | R88: 77 | S88: 9 | T88: 58 | U88: 65 | V88: 38 | W88: 3 | X88: 21 | Y88: 63 | Z88: 44 | AA88: 34 | AB88: 34 | AC88: 5 | AD88: 48 | AE88: 5 | AF88: 37 | AG88: 6 | AH88: 73 | AI88: 36 | AJ88: 11 | AK88: 27 | AL88: 74 | AM88: 66 | AN88: 16 | AO88: 8 | AP88: 19 | AQ88: 45 | AR88: 19 | AS88: 10 | AT88: 16 | AU88: 11 | AV88: 41 | AW88: 9 | AX88: 43 | AY88: 36 | AZ88: 43 | BA88: 52 | BB88: 64 | BC88: 62 | BD88: 52 | BE88: 43 | BF88: 80 | BG88: 72 | BH88: 38 | BI88: 5 | BJ88: =OR(B180:BI180) -> FALSE
A89: 86 | B89: 13 | C89: 57 | D89: 44 | E89: 18 | F89: 23 | G89: 9 | H89: 55 | I89: 13 | J89: 40 | K89: 64 | L89: 58 | M89: 32 | N89: 47 | O89: 4 | P89: 58 | Q89: 73 | R89: 17 | S89: 26 | T89: 63 | U89: 41 | V89: 73 | W89: 77 | X89: 20 | Y89: 34 | Z89: 34 | AA89: 48 | AB89: 25 | AC89: 68 | AD89: 46 | AE89: 34 | AF89: 34 | AG89: 69 | AH89: 30 | AI89: 26 | AJ89: 79 | AK89: 52 | AL89: 47 | AM89: 79 | AN89: 21 | AO89: 76 | AP89: 61 | AQ89: 11 | AR89: 73 | AS89: 19 | AT89: 49 | AU89: 54 | AV89: 31 | AW89: 49 | AX89: 69 | AY89: 7 | AZ89: 37 | BA89: 26 | BB89: 11 | BC89: 4 | BD89: 5 | BE89: 49 | BF89: 33 | BG89: 56 | BH89: 10 | BI89: 78 | BJ89: =OR(B180:BI180) -> FALSE
A90: 87 | B90: 21 | C90: 30 | D90: 41 | E90: 44 | F90: 72 | G90: 15 | H90: 24 | I90: 18 | J90: 14 | K90: 25 | L90: 29 | M90: 70 | N90: 38 | O90: 39 | P90: 52 | Q90: 47 | R90: 51 | S90: 39 | T90: 55 | U90: 26 | V90: 17 | W90: 27 | X90: 40 | Y90: 73 | Z90: 29 | AA90: 19 | AB90: 21 | AC90: 2 | AD90: 32 | AE90: 60 | AF90: 70 | AG90: 13 | AH90: 11 | AI90: 6 | AJ90: 17 | AK90: 70 | AL90: 41 | AM90: 14 | AN90: 74 | AO90: 44 | AP90: 38 | AQ90: 33 | AR90: 18 | AS90: 16 | AT90: 5 | AU90: 33 | AV90: 14 | AW90: 63 | AX90: 58 | AY90: 3 | AZ90: 8 | BA90: 1 | BB90: 45 | BC90: 8 | BD90: 30 | BE90: 81 | BF90: 7 | BG90: 63 | BH90: 64 | BI90: 12 | BJ90: =OR(B180:BI180) -> FALSE
A91: 88 | B91: 12 | C91: 6 | D91: 21 | E91: 70 | F91: 44 | G91: 39 | H91: 22 | I91: 47 | J91: 27 | K91: 64 | L91: 64 | M91: 23 | N91: 28 | O91: 4 | P91: 39 | Q91: 2 | R91: 20 | S91: 18 | T91: 42 | U91: 6 | V91: 22 | W91: 31 | X91: 35 | Y91: 11 | Z91: 47 | AA91: 76 | AB91: 73 | AC91: 14 | AD91: 7 | AE91: 58 | AF91: 52 | AG91: 39 | AH91: 35 | AI91: 9 | AJ91: 21 | AK91: 48 | AL91: 12 | AM91: 8 | AN91: 36 | AO91: 9 | AP91: 62 | AQ91: 38 | AR91: 58 | AS91: 24 | AT91: 30 | AU91: 54 | AV91: 75 | AW91: 69 | AX91: 8 | AY91: 22 | AZ91: 48 | BA91: 14 | BB91: 3 | BC91: 67 | BD91: 54 | BE91: 52 | BF91: 75 | BG91: 26 | BH91: 37 | BI91: 56 | BJ91: =OR(B183:BI183) -> FALSE
A92: 89 | B92: 57 | C92: 39 | D92: 41 | E92: 54 | F92: 55 | G92: 54 | H92: 9 | I92: 57 | J92: 21 | K92: 29 | L92: 13 | M92: 12 | N92: 10 | O92: 52 | P92: 4 | Q92: 75 | R92: 15 | S92: 52 | T92: 79 | U92: 70 | V92: 57 | W92: 72 | X92: 47 | Y92: 6 | Z92: 36 | AA92: 81 | AB92: 12 | AC92: 22 | AD92: 50 | AE92: 15 | AF92: 6 | AG92: 28 | AH92: 22 | AI92: 71 | AJ92: 32 | AK92: 17 | AL92: 78 | AM92: 51 | AN92: 73 | AO92: 31 | AP92: 48 | AQ92: 46 | AR92: 60 | AS92: 62 | AT92: 70 | AU92: 2 | AV92: 6 | AW92: 52 | AX92: 35 | AY92: 48 | AZ92: 80 | BA92: 46 | BB92: 8 | BC92: 39 | BD92: 53 | BE92: 64 | BF92: 11 | BG92: 50 | BH92: 33 | BI92: 67 | BJ92: =OR(B183:BI183) -> FALSE
A93: 90 | B93: 6 | C93: 38 | D93: 33 | E93: 47 | F93: 52 | G93: 74 | H93: 26 | I93: 65 | J93: 5 | K93: 57 | L93: 4 | M93: 13 | N93: 22 | O93: 15 | P93: 14 | Q93: 29 | R93: 51 | S93: 20 | T93: 52 | U93: 67 | V93: 37 | W93: 35 | X93: 41 | Y93: 56 | Z93: 5 | AA93: 2 | AB93: 41 | AC93: 66 | AD93: 21 | AE93: 61 | AF93: 71 | AG93: 71 | AH93: 12 | AI93: 29 | AJ93: 67 | AK93: 16 | AL93: 67 | AM93: 18 | AN93: 74 | AO93: 24 | AP93: 67 | AQ93: 51 | AR93: 53 | AS93: 54 | AT93: 29 | AU93: 15 | AV93: 69 | AW93: 44 | AX93: 19 | AY93: 54 | AZ93: 28 | BA93: 9 | BB93: 70 | BC93: 25 | BD93: 7 | BE93: 48 | BF93: 4 | BG93: 37 | BH93: 34 | BI93: 29 | BJ93: =OR(B183:BI183) -> FALSE
A96: 1 | B96: =OR(B4=B5,B4=B6,B5=B6) -> FALSE | C96: =OR(C4=C5,C4=C6,C5=C6) -> FALSE | D96: =OR(D4=D5,D4=D6,D5=D6) -> FALSE | E96: =OR(E4=E5,E4=E6,E5=E6) -> FALSE | F96: =OR(F4=F5,F4=F6,F5=F6) -> FALSE | G96: =OR(G4=G5,G4=G6,G5=G6) -> FALSE | H96: =OR(H4=H5,H4=H6,H5=H6) -> FALSE | I96: =OR(I4=I5,I4=I6,I5=I6) -> FALSE | ... BI96: =OR(BI4=BI5,BI4=BI6,BI5=BI6) -> FALSE
A97: 2
A98: 3
A99: 4 | B99: =OR(B7=B8,B7=B9,B8=B9) -> FALSE | C99: =OR(C7=C8,C7=C9,C8=C9) -> FALSE | D99: =OR(D7=D8,D7=D9,D8=D9) -> FALSE | E99: =OR(E7=E8,E7=E9,E8=E9) -> FALSE | F99: =OR(F7=F8,F7=F9,F8=F9) -> FALSE | G99: =OR(G7=G8,G7=G9,G8=G9) -> FALSE | H99: =OR(H7=H8,H7=H9,H8=H9) -> FALSE | I99: =OR(I7=I8,I7=I9,I8=I9) -> FALSE | ... BI99: =OR(BI7=BI8,BI7=BI9,BI8=BI9) -> FALSE
A100: 5
A101: 6
A102: 7 | B102: =OR(B10=B11,B10=B12,B11=B12) -> FALSE | C102: =OR(C10=C11,C10=C12,C11=C12) -> FALSE | D102: =OR(D10=D11,D10=D12,D11=D12) -> FALSE | E102: =OR(E10=E11,E10=E12,E11=E12) -> FALSE | F102: =OR(F10=F11,F10=F12,F11=F12) -> FALSE | G102: =OR(G10=G11,G10=G12,G11=G12) -> FALSE | H102: =OR(H10=H11,H10=H12,H11=H12) -> FALSE | I102: =OR(I10=I11,I10=I12,I11=I12) -> FALSE | ... BI102: =OR(BI10=BI11,BI10=BI12,BI11=BI12) -> FALSE
...

Sheet RandomNumbersToCopyFrom
A1: Random numbers (adjusted to avoid duplicates in a question) | O1: upb= | P1: =COUNT(DOE!$A$4:$A$84) -> 81
B2: Student ID
A3: Option | B3: 1 | C3: 2 | D3: 3 | E3: 4 | F3: 5 | G3: 6 | H3: 7 | I3: 8 | J3: 9 | K3: 10 | L3: 11 | M3: 12 | N3: 13 | O3: 14 | P3: 15 | Q3: 16 | R3: 17 | S3: 18 | T3: 19 | U3: 20 | V3: 21 | W3: 22 | X3: 23 | Y3: 24 | Z3: 25 | AA3: 26 | AB3: 27 | AC3: 28 | AD3: 29 | AE3: 30 | AF3: 31 | AG3: 32 | AH3: 33 | AI3: 34 | AJ3: 35 | AK3: 36 | AL3: 37 | AM3: 38 | AN3: 39 | AO3: 40 | AP3: 41 | AQ3: 42 | AR3: 43 | AS3: 44 | AT3: 45 | AU3: 46 | AV3: 47 | AW3: 48 | AX3: 49 | AY3: 50 | AZ3: 51 | BA3: 52 | BB3: 53 | BC3: 54 | BD3: 55 | BE3: 56 | BF3: 57 | BG3: 58 | BH3: 59 | BI3: 60
A4: 1 | B4: =B101 -> 16 | C4: =C101 -> 39 | D4: =D101 -> 76 | E4: =E101 -> 49 | F4: =F101 -> 63 | G4: =G101 -> 69 | H4: =H101 -> 53 | I4: =I101 -> 37 | ... BI4: =BI101 -> 9
A5: 2 | B5: =IF(B102>=B101,B102+1,B102) -> 46 | C5: =IF(C102>=C101,C102+1,C102) -> 70 | D5: =IF(D102>=D101,D102+1,D102) -> 27 | E5: =IF(E102>=E101,E102+1,E102) -> 78 | F5: =IF(F102>=F101,F102+1,F102) -> 32 | G5: =IF(G102>=G101,G102+1,G102) -> 62 | H5: =IF(H102>=H101,H102+1,H102) -> 23 | I5: =IF(I102>=I101,I102+1,I102) -> 43 | ... BI5: =IF(BI102>=BI101,BI102+1,BI102) -> 21
A6: 3 | B6: =IF(B103>=MIN(B4,B5),IF((B103+1)>=MAX(B4,B5),B103+2,B103+1),B103) -> 69 | C6: =IF(C103>=MIN(C4,C5),IF((C103+1)>=MAX(C4,C5),C103+2,C103+1),C103) -> 38 | D6: =IF(D103>=MIN(D4,D5),IF((D103+1)>=MAX(D4,D5),D103+2,D103+1),D103) -> 62 | E6: =IF(E103>=MIN(E4,E5),IF((E103+1)>=MAX(E4,E5),E103+2,E103+1),E103) -> 12 | F6: =IF(F103>=MIN(F4,F5),IF((F103+1)>=MAX(F4,F5),F103+2,F103+1),F103) -> 34 | G6: =IF(G103>=MIN(G4,G5),IF((G103+1)>=MAX(G4,G5),G103+2,G103+1),G103) -> 56 | H6: =IF(H103>=MIN(H4,H5),IF((H103+1)>=MAX(H4,H5),H103+2,H103+1),H103) -> 16 | I6: =IF(I103>=MIN(I4,I5),IF((I103+1)>=MAX(I4,I5),I103+2,I103+1),I103) -> 15 | ... BI6: =IF(BI103>=MIN(BI4,BI5),IF((BI103+1)>=MAX(BI4,BI5),BI103+2,BI103+1),BI103) -> 45
A7: 4 | B7: =B104 -> 52 | C7: =C104 -> 73 | D7: =D104 -> 63 | E7: =E104 -> 37 | F7: =F104 -> 49 | G7: =G104 -> 80 | H7: =H104 -> 58 | I7: =I104 -> 77 | ... BI7: =BI104 -> 54
A8: 5 | B8: =IF(B105>=B104,B105+1,B105) -> 71 | C8: =IF(C105>=C104,C105+1,C105) -> 5 | D8: =IF(D105>=D104,D105+1,D105) -> 44 | E8: =IF(E105>=E104,E105+1,E105) -> 36 | F8: =IF(F105>=F104,F105+1,F105) -> 30 | G8: =IF(G105>=G104,G105+1,G105) -> 2 | H8: =IF(H105>=H104,H105+1,H105) -> 73 | I8: =IF(I105>=I104,I105+1,I105) -> 8 | ... BI8: =IF(BI105>=BI104,BI105+1,BI105) -> 30
A9: 6 | B9: =IF(B106>=MIN(B7,B8),IF((B106+1)>=MAX(B7,B8),B106+2,B106+1),B106) -> 60 | C9: =IF(C106>=MIN(C7,C8),IF((C106+1)>=MAX(C7,C8),C106+2,C106+1),C106) -> 68 | D9: =IF(D106>=MIN(D7,D8),IF((D106+1)>=MAX(D7,D8),D106+2,D106+1),D106) -> 6 | E9: =IF(E106>=MIN(E7,E8),IF((E106+1)>=MAX(E7,E8),E106+2,E106+1),E106) -> 43 | F9: =IF(F106>=MIN(F7,F8),IF((F106+1)>=MAX(F7,F8),F106+2,F106+1),F106) -> 31 | G9: =IF(G106>=MIN(G7,G8),IF((G106+1)>=MAX(G7,G8),G106+2,G106+1),G106) -> 58 | H9: =IF(H106>=MIN(H7,H8),IF((H106+1)>=MAX(H7,H8),H106+2,H106+1),H106) -> 49 | I9: =IF(I106>=MIN(I7,I8),IF((I106+1)>=MAX(I7,I8),I106+2,I106+1),I106) -> 22 | ... BI9: =IF(BI106>=MIN(BI7,BI8),IF((BI106+1)>=MAX(BI7,BI8),BI106+2,BI106+1),BI106) -> 45
A10: 7 | B10: =B107 -> 28 | C10: =C107 -> 52 | D10: =D107 -> 9 | E10: =E107 -> 33 | F10: =F107 -> 50 | G10: =G107 -> 18 | H10: =H107 -> 79 | I10: =I107 -> 72 | ... BI10: =BI107 -> 34
A11: 8 | B11: =IF(B108>=B107,B108+1,B108) -> 72 | C11: =IF(C108>=C107,C108+1,C108) -> 24 | D11: =IF(D108>=D107,D108+1,D108) -> 48 | E11: =IF(E108>=E107,E108+1,E108) -> 74 | F11: =IF(F108>=F107,F108+1,F108) -> 61 | G11: =IF(G108>=G107,G108+1,G108) -> 58 | H11: =IF(H108>=H107,H108+1,H108) -> 11 | I11: =IF(I108>=I107,I108+1,I108) -> 57 | ... BI11: =IF(BI108>=BI107,BI108+1,BI108) -> 52
A12: 9 | B12: =IF(B109>=MIN(B10,B11),IF((B109+1)>=MAX(B10,B11),B109+2,B109+1),B109) -> 69 | C12: =IF(C109>=MIN(C10,C11),IF((C109+1)>=MAX(C10,C11),C109+2,C109+1),C109) -> 35 | D12: =IF(D109>=MIN(D10,D11),IF((D109+1)>=MAX(D10,D11),D109+2,D109+1),D109) -> 79 | E12: =IF(E109>=MIN(E10,E11),IF((E109+1)>=MAX(E10,E11),E109+2,E109+1),E109) -> 26 | F12: =IF(F109>=MIN(F10,F11),IF((F109+1)>=MAX(F10,F11),F109+2,F109+1),F109) -> 25 | G12: =IF(G109>=MIN(G10,G11),IF((G109+1)>=MAX(G10,G11),G109+2,G109+1),G109) -> 47 | H12: =IF(H109>=MIN(H10,H11),IF((H109+1)>=MAX(H10,H11),H109+2,H109+1),H109) -> 16 | I12: =IF(I109>=MIN(I10,I11),IF((I109+1)>=MAX(I10,I11),I109+2,I109+1),I109) -> 54 | ... BI12: =IF(BI109>=MIN(BI10,BI11),IF((BI109+1)>=MAX(BI10,BI11),BI109+2,BI109+1),BI109) -> 7
A13: 10 | B13: =B110 -> 5 | C13: =C110 -> 17 | D13: =D110 -> 35 | E13: =E110 -> 61 | F13: =F110 -> 11 | G13: =G110 -> 37 | H13: =H110 -> 56 | I13: =I110 -> 51 | ... BI13: =BI110 -> 47
A14: 11 | B14: =IF(B111>=B110,B111+1,B111) -> 28 | C14: =IF(C111>=C110,C111+1,C111) -> 5 | D14: =IF(D111>=D110,D111+1,D111) -> 60 | E14: =IF(E111>=E110,E111+1,E111) -> 23 | F14: =IF(F111>=F110,F111+1,F111) -> 19 | G14: =IF(G111>=G110,G111+1,G111) -> 39 | H14: =IF(H111>=H110,H111+1,H111) -> 16 | I14: =IF(I111>=I110,I111+1,I111) -> 79 | ... BI14: =IF(BI111>=BI110,BI111+1,BI111) -> 69
A15: 12 | B15: =IF(B112>=MIN(B13,B14),IF((B112+1)>=MAX(B13,B14),B112+2,B112+1),B112) -> 15 | C15: =IF(C112>=MIN(C13,C14),IF((C112+1)>=MAX(C13,C14),C112+2,C112+1),C112) -> 70 | D15: =IF(D112>=MIN(D13,D14),IF((D112+1)>=MAX(D13,D14),D112+2,D112+1),D112) -> 3 | E15: =IF(E112>=MIN(E13,E14),IF((E112+1)>=MAX(E13,E14),E112+2,E112+1),E112) -> 20 | F15: =IF(F112>=MIN(F13,F14),IF((F112+1)>=MAX(F13,F14),F112+2,F112+1),F112) -> 9 | G15: =IF(G112>=MIN(G13,G14),IF((G112+1)>=MAX(G13,G14),G112+2,G112+1),G112) -> 31 | H15: =IF(H112>=MIN(H13,H14),IF((H112+1)>=MAX(H13,H14),H112+2,H112+1),H112) -> 54 | I15: =IF(I112>=MIN(I13,I14),IF((I112+1)>=MAX(I13,I14),I112+2,I112+1),I112) -> 28 | ... BI15: =IF(BI112>=MIN(BI13,BI14),IF((BI112+1)>=MAX(BI13,BI14),BI112+2,BI112+1),BI112) -> 67
A16: 13 | B16: =B113 -> 39 | C16: =C113 -> 11 | D16: =D113 -> 52 | E16: =E113 -> 12 | F16: =F113 -> 53 | G16: =G113 -> 38 | H16: =H113 -> 45 | I16: =I113 -> 71 | ... BI16: =BI113 -> 47
A17: 14 | B17: =IF(B114>=B113,B114+1,B114) -> 69 | C17: =IF(C114>=C113,C114+1,C114) -> 51 | D17: =IF(D114>=D113,D114+1,D114) -> 27 | E17: =IF(E114>=E113,E114+1,E114) -> 58 | F17: =IF(F114>=F113,F114+1,F114) -> 30 | G17: =IF(G114>=G113,G114+1,G114) -> 79 | H17: =IF(H114>=H113,H114+1,H114) -> 80 | I17: =IF(I114>=I113,I114+1,I114) -> 75 | ... BI17: =IF(BI114>=BI113,BI114+1,BI114) -> 17
A18: 15 | B18: =IF(B115>=MIN(B16,B17),IF((B115+1)>=MAX(B16,B17),B115+2,B115+1),B115) -> 52 | C18: =IF(C115>=MIN(C16,C17),IF((C115+1)>=MAX(C16,C17),C115+2,C115+1),C115) -> 40 | D18: =IF(D115>=MIN(D16,D17),IF((D115+1)>=MAX(D16,D17),D115+2,D115+1),D115) -> 21 | E18: =IF(E115>=MIN(E16,E17),IF((E115+1)>=MAX(E16,E17),E115+2,E115+1),E115) -> 35 | F18: =IF(F115>=MIN(F16,F17),IF((F115+1)>=MAX(F16,F17),F115+2,F115+1),F115) -> 29 | G18: =IF(G115>=MIN(G16,G17),IF((G115+1)>=MAX(G16,G17),G115+2,G115+1),G115) -> 43 | H18: =IF(H115>=MIN(H16,H17),IF((H115+1)>=MAX(H16,H17),H115+2,H115+1),H115) -> 40 | I18: =IF(I115>=MIN(I16,I17),IF((I115+1)>=MAX(I16,I17),I115+2,I115+1),I115) -> 78 | ... BI18: =IF(BI115>=MIN(BI16,BI17),IF((BI115+1)>=MAX(BI16,BI17),BI115+2,BI115+1),BI115) -> 60
A19: 16 | B19: =B116 -> 18 | C19: =C116 -> 13 | D19: =D116 -> 56 | E19: =E116 -> 1 | F19: =F116 -> 16 | G19: =G116 -> 79 | H19: =H116 -> 75 | I19: =I116 -> 2 | ... BI19: =BI116 -> 75
A20: 17 | B20: =IF(B117>=B116,B117+1,B117) -> 56 | C20: =IF(C117>=C116,C117+1,C117) -> 37 | D20: =IF(D117>=D116,D117+1,D117) -> 1 | E20: =IF(E117>=E116,E117+1,E117) -> 17 | F20: =IF(F117>=F116,F117+1,F117) -> 72 | G20: =IF(G117>=G116,G117+1,G117) -> 44 | H20: =IF(H117>=H116,H117+1,H117) -> 42 | I20: =IF(I117>=I116,I117+1,I117) -> 35 | ... BI20: =IF(BI117>=BI116,BI117+1,BI117) -> 28
A21: 18 | B21: =IF(B118>=MIN(B19,B20),IF((B118+1)>=MAX(B19,B20),B118+2,B118+1),B118) -> 59 | C21: =IF(C118>=MIN(C19,C20),IF((C118+1)>=MAX(C19,C20),C118+2,C118+1),C118) -> 45 | D21: =IF(D118>=MIN(D19,D20),IF((D118+1)>=MAX(D19,D20),D118+2,D118+1),D118) -> 5 | E21: =IF(E118>=MIN(E19,E20),IF((E118+1)>=MAX(E19,E20),E118+2,E118+1),E118) -> 75 | F21: =IF(F118>=MIN(F19,F20),IF((F118+1)>=MAX(F19,F20),F118+2,F118+1),F118) -> 15 | G21: =IF(G118>=MIN(G19,G20),IF((G118+1)>=MAX(G19,G20),G118+2,G118+1),G118) -> 4 | H21: =IF(H118>=MIN(H19,H20),IF((H118+1)>=MAX(H19,H20),H118+2,H118+1),H118) -> 14 | I21: =IF(I118>=MIN(I19,I20),IF((I118+1)>=MAX(I19,I20),I118+2,I118+1),I118) -> 3 | ... BI21: =IF(BI118>=MIN(BI19,BI20),IF((BI118+1)>=MAX(BI19,BI20),BI118+2,BI118+1),BI118) -> 1
A22: 19 | B22: =B119 -> 71 | C22: =C119 -> 45 | D22: =D119 -> 3 | E22: =E119 -> 30 | F22: =F119 -> 17 | G22: =G119 -> 71 | H22: =H119 -> 56 | I22: =I119 -> 5 | ... BI22: =BI119 -> 11
A23: 20 | B23: =IF(B120>=B119,B120+1,B120) -> 18 | C23: =IF(C120>=C119,C120+1,C120) -> 60 | D23: =IF(D120>=D119,D120+1,D120) -> 53 | E23: =IF(E120>=E119,E120+1,E120) -> 20 | F23: =IF(F120>=F119,F120+1,F120) -> 18 | G23: =IF(G120>=G119,G120+1,G120) -> 69 | H23: =IF(H120>=H119,H120+1,H120) -> 77 | I23: =IF(I120>=I119,I120+1,I120) -> 73 | ... BI23: =IF(BI120>=BI119,BI120+1,BI120) -> 6
A24: 21 | B24: =IF(B121>=MIN(B22,B23),IF((B121+1)>=MAX(B22,B23),B121+2,B121+1),B121) -> 16 | C24: =IF(C121>=MIN(C22,C23),IF((C121+1)>=MAX(C22,C23),C121+2,C121+1),C121) -> 23 | D24: =IF(D121>=MIN(D22,D23),IF((D121+1)>=MAX(D22,D23),D121+2,D121+1),D121) -> 11 | E24: =IF(E121>=MIN(E22,E23),IF((E121+1)>=MAX(E22,E23),E121+2,E121+1),E121) -> 24 | F24: =IF(F121>=MIN(F22,F23),IF((F121+1)>=MAX(F22,F23),F121+2,F121+1),F121) -> 27 | G24: =IF(G121>=MIN(G22,G23),IF((G121+1)>=MAX(G22,G23),G121+2,G121+1),G121) -> 56 | H24: =IF(H121>=MIN(H22,H23),IF((H121+1)>=MAX(H22,H23),H121+2,H121+1),H121) -> 36 | I24: =IF(I121>=MIN(I22,I23),IF((I121+1)>=MAX(I22,I23),I121+2,I121+1),I121) -> 78 | ... BI24: =IF(BI121>=MIN(BI22,BI23),IF((BI121+1)>=MAX(BI22,BI23),BI121+2,BI121+1),BI121) -> 1
